Compiled from "AESCryptol.java"
public class AESCryptol extends java.lang.Object{
public AESCryptol();
  Code:
   0:	aload_0
   1:	invokespecial	#1; //Method java/lang/Object."<init>":()V
   4:	return

public static void run(int[], int[], int[]);
  Code:
   0:	iconst_2
   1:	newarray int
   3:	astore	32
   5:	iconst_2
   6:	newarray int
   8:	astore	33
   10:	aload_1
   11:	iconst_0
   12:	iaload
   13:	istore_3
   14:	aload_1
   15:	iconst_0
   16:	iaload
   17:	bipush	8
   19:	ishr
   20:	istore	4
   22:	aload_1
   23:	iconst_0
   24:	iaload
   25:	bipush	16
   27:	ishr
   28:	istore	5
   30:	aload_1
   31:	iconst_0
   32:	iaload
   33:	bipush	24
   35:	ishr
   36:	istore	6
   38:	aload_1
   39:	iconst_1
   40:	iaload
   41:	istore	7
   43:	aload_1
   44:	iconst_1
   45:	iaload
   46:	bipush	8
   48:	ishr
   49:	istore	8
   51:	aload_1
   52:	iconst_1
   53:	iaload
   54:	bipush	16
   56:	ishr
   57:	istore	9
   59:	aload_1
   60:	iconst_1
   61:	iaload
   62:	bipush	24
   64:	ishr
   65:	istore	10
   67:	aload_1
   68:	iconst_2
   69:	iaload
   70:	istore	11
   72:	aload_1
   73:	iconst_2
   74:	iaload
   75:	bipush	8
   77:	ishr
   78:	istore	12
   80:	aload_1
   81:	iconst_2
   82:	iaload
   83:	bipush	16
   85:	ishr
   86:	istore	13
   88:	aload_1
   89:	iconst_2
   90:	iaload
   91:	bipush	24
   93:	ishr
   94:	istore	14
   96:	aload_1
   97:	iconst_3
   98:	iaload
   99:	istore	15
   101:	aload_1
   102:	iconst_3
   103:	iaload
   104:	bipush	8
   106:	ishr
   107:	istore	16
   109:	aload_1
   110:	iconst_3
   111:	iaload
   112:	bipush	16
   114:	ishr
   115:	istore	17
   117:	aload_1
   118:	iconst_3
   119:	iaload
   120:	bipush	24
   122:	ishr
   123:	istore	18
   125:	iload	18
   127:	sipush	255
   130:	iand
   131:	istore	18
   133:	iload	17
   135:	bipush	8
   137:	ishl
   138:	iload	18
   140:	ior
   141:	istore	18
   143:	iload	16
   145:	sipush	255
   148:	iand
   149:	istore	16
   151:	iload	15
   153:	bipush	8
   155:	ishl
   156:	iload	16
   158:	ior
   159:	istore	16
   161:	iload	18
   163:	ldc	#2; //int 65535
   165:	iand
   166:	istore	18
   168:	iload	16
   170:	bipush	16
   172:	ishl
   173:	iload	18
   175:	ior
   176:	istore	16
   178:	aload_0
   179:	iconst_0
   180:	iaload
   181:	istore	18
   183:	aload_0
   184:	iconst_0
   185:	iaload
   186:	bipush	8
   188:	ishr
   189:	istore	15
   191:	aload_0
   192:	iconst_0
   193:	iaload
   194:	bipush	16
   196:	ishr
   197:	istore	17
   199:	aload_0
   200:	iconst_0
   201:	iaload
   202:	bipush	24
   204:	ishr
   205:	istore	19
   207:	aload_0
   208:	iconst_1
   209:	iaload
   210:	istore	20
   212:	aload_0
   213:	iconst_1
   214:	iaload
   215:	bipush	8
   217:	ishr
   218:	istore	21
   220:	aload_0
   221:	iconst_1
   222:	iaload
   223:	bipush	16
   225:	ishr
   226:	istore	22
   228:	aload_0
   229:	iconst_1
   230:	iaload
   231:	bipush	24
   233:	ishr
   234:	istore	23
   236:	aload_0
   237:	iconst_2
   238:	iaload
   239:	istore	24
   241:	aload_0
   242:	iconst_2
   243:	iaload
   244:	bipush	8
   246:	ishr
   247:	istore	25
   249:	aload_0
   250:	iconst_2
   251:	iaload
   252:	bipush	16
   254:	ishr
   255:	istore	26
   257:	aload_0
   258:	iconst_2
   259:	iaload
   260:	bipush	24
   262:	ishr
   263:	istore	27
   265:	aload_0
   266:	iconst_3
   267:	iaload
   268:	istore	28
   270:	aload_0
   271:	iconst_3
   272:	iaload
   273:	bipush	8
   275:	ishr
   276:	istore	29
   278:	aload_0
   279:	iconst_3
   280:	iaload
   281:	bipush	16
   283:	ishr
   284:	istore	30
   286:	aload_0
   287:	iconst_3
   288:	iaload
   289:	bipush	24
   291:	ishr
   292:	istore	31
   294:	iload	31
   296:	sipush	255
   299:	iand
   300:	istore	31
   302:	iload	30
   304:	bipush	8
   306:	ishl
   307:	iload	31
   309:	ior
   310:	istore	31
   312:	iload	29
   314:	sipush	255
   317:	iand
   318:	istore	29
   320:	iload	28
   322:	bipush	8
   324:	ishl
   325:	iload	29
   327:	ior
   328:	istore	29
   330:	iload	31
   332:	ldc	#2; //int 65535
   334:	iand
   335:	istore	31
   337:	iload	29
   339:	bipush	16
   341:	ishl
   342:	iload	31
   344:	ior
   345:	istore	29
   347:	iload	16
   349:	iload	29
   351:	ixor
   352:	istore	16
   354:	iload	16
   356:	iconst_0
   357:	ishr
   358:	istore	31
   360:	iload	16
   362:	bipush	8
   364:	ishr
   365:	istore	28
   367:	iload	16
   369:	bipush	16
   371:	ishr
   372:	istore	30
   374:	iload	16
   376:	bipush	24
   378:	ishr
   379:	istore	16
   381:	iload	14
   383:	sipush	255
   386:	iand
   387:	istore	14
   389:	iload	13
   391:	bipush	8
   393:	ishl
   394:	iload	14
   396:	ior
   397:	istore	14
   399:	iload	12
   401:	sipush	255
   404:	iand
   405:	istore	12
   407:	iload	11
   409:	bipush	8
   411:	ishl
   412:	iload	12
   414:	ior
   415:	istore	12
   417:	iload	14
   419:	ldc	#2; //int 65535
   421:	iand
   422:	istore	14
   424:	iload	12
   426:	bipush	16
   428:	ishl
   429:	iload	14
   431:	ior
   432:	istore	12
   434:	iload	27
   436:	sipush	255
   439:	iand
   440:	istore	27
   442:	iload	26
   444:	bipush	8
   446:	ishl
   447:	iload	27
   449:	ior
   450:	istore	27
   452:	iload	25
   454:	sipush	255
   457:	iand
   458:	istore	25
   460:	iload	24
   462:	bipush	8
   464:	ishl
   465:	iload	25
   467:	ior
   468:	istore	25
   470:	iload	27
   472:	ldc	#2; //int 65535
   474:	iand
   475:	istore	27
   477:	iload	25
   479:	bipush	16
   481:	ishl
   482:	iload	27
   484:	ior
   485:	istore	25
   487:	iload	12
   489:	iload	25
   491:	ixor
   492:	istore	12
   494:	iload	12
   496:	iconst_0
   497:	ishr
   498:	istore	27
   500:	iload	12
   502:	bipush	8
   504:	ishr
   505:	istore	24
   507:	iload	12
   509:	bipush	16
   511:	ishr
   512:	istore	26
   514:	iload	12
   516:	bipush	24
   518:	ishr
   519:	istore	12
   521:	iload	10
   523:	sipush	255
   526:	iand
   527:	istore	10
   529:	iload	9
   531:	bipush	8
   533:	ishl
   534:	iload	10
   536:	ior
   537:	istore	10
   539:	iload	8
   541:	sipush	255
   544:	iand
   545:	istore	8
   547:	iload	7
   549:	bipush	8
   551:	ishl
   552:	iload	8
   554:	ior
   555:	istore	8
   557:	iload	10
   559:	ldc	#2; //int 65535
   561:	iand
   562:	istore	10
   564:	iload	8
   566:	bipush	16
   568:	ishl
   569:	iload	10
   571:	ior
   572:	istore	8
   574:	iload	23
   576:	sipush	255
   579:	iand
   580:	istore	23
   582:	iload	22
   584:	bipush	8
   586:	ishl
   587:	iload	23
   589:	ior
   590:	istore	23
   592:	iload	21
   594:	sipush	255
   597:	iand
   598:	istore	21
   600:	iload	20
   602:	bipush	8
   604:	ishl
   605:	iload	21
   607:	ior
   608:	istore	21
   610:	iload	23
   612:	ldc	#2; //int 65535
   614:	iand
   615:	istore	23
   617:	iload	21
   619:	bipush	16
   621:	ishl
   622:	iload	23
   624:	ior
   625:	istore	21
   627:	iload	8
   629:	iload	21
   631:	ixor
   632:	istore	8
   634:	iload	8
   636:	iconst_0
   637:	ishr
   638:	istore	23
   640:	iload	8
   642:	bipush	8
   644:	ishr
   645:	istore	20
   647:	iload	8
   649:	bipush	16
   651:	ishr
   652:	istore	22
   654:	iload	8
   656:	bipush	24
   658:	ishr
   659:	istore	8
   661:	iload	6
   663:	sipush	255
   666:	iand
   667:	istore	6
   669:	iload	5
   671:	bipush	8
   673:	ishl
   674:	iload	6
   676:	ior
   677:	istore	6
   679:	iload	4
   681:	sipush	255
   684:	iand
   685:	istore	4
   687:	iload_3
   688:	bipush	8
   690:	ishl
   691:	iload	4
   693:	ior
   694:	istore	4
   696:	iload	6
   698:	ldc	#2; //int 65535
   700:	iand
   701:	istore	6
   703:	iload	4
   705:	bipush	16
   707:	ishl
   708:	iload	6
   710:	ior
   711:	istore	4
   713:	iload	19
   715:	sipush	255
   718:	iand
   719:	istore	19
   721:	iload	17
   723:	bipush	8
   725:	ishl
   726:	iload	19
   728:	ior
   729:	istore	19
   731:	iload	15
   733:	sipush	255
   736:	iand
   737:	istore	15
   739:	iload	18
   741:	bipush	8
   743:	ishl
   744:	iload	15
   746:	ior
   747:	istore	15
   749:	iload	19
   751:	ldc	#2; //int 65535
   753:	iand
   754:	istore	19
   756:	iload	15
   758:	bipush	16
   760:	ishl
   761:	iload	19
   763:	ior
   764:	istore	15
   766:	iload	4
   768:	iload	15
   770:	ixor
   771:	istore	4
   773:	iload	4
   775:	iconst_0
   776:	ishr
   777:	istore	19
   779:	iload	4
   781:	bipush	8
   783:	ishr
   784:	istore	18
   786:	iload	4
   788:	bipush	16
   790:	ishr
   791:	istore	17
   793:	iload	4
   795:	bipush	24
   797:	ishr
   798:	istore	4
   800:	iload	31
   802:	sipush	255
   805:	iand
   806:	istore	31
   808:	getstatic	#3; //Field gtable0:[I
   811:	iload	31
   813:	iaload
   814:	istore	31
   816:	iload	24
   818:	sipush	255
   821:	iand
   822:	istore	24
   824:	getstatic	#4; //Field gtable1:[I
   827:	iload	24
   829:	iaload
   830:	istore	24
   832:	iload	31
   834:	iload	24
   836:	ixor
   837:	istore	24
   839:	iload	22
   841:	sipush	255
   844:	iand
   845:	istore	22
   847:	getstatic	#5; //Field gtable2:[I
   850:	iload	22
   852:	iaload
   853:	istore	22
   855:	iload	24
   857:	iload	22
   859:	ixor
   860:	istore	22
   862:	iload	4
   864:	sipush	255
   867:	iand
   868:	istore	4
   870:	getstatic	#6; //Field gtable3:[I
   873:	iload	4
   875:	iaload
   876:	istore	4
   878:	iload	22
   880:	iload	4
   882:	ixor
   883:	istore	4
   885:	iload	15
   887:	bipush	24
   889:	ishl
   890:	iload	15
   892:	bipush	8
   894:	iushr
   895:	ior
   896:	istore	22
   898:	iload	22
   900:	iconst_0
   901:	ishr
   902:	istore	24
   904:	iload	22
   906:	bipush	8
   908:	ishr
   909:	istore	31
   911:	iload	22
   913:	bipush	16
   915:	ishr
   916:	istore	6
   918:	iload	22
   920:	bipush	24
   922:	ishr
   923:	istore	22
   925:	iload	24
   927:	sipush	255
   930:	iand
   931:	istore	24
   933:	getstatic	#7; //Field gtable4:[I
   936:	iload	24
   938:	iaload
   939:	istore	24
   941:	iload	31
   943:	sipush	255
   946:	iand
   947:	istore	31
   949:	getstatic	#7; //Field gtable4:[I
   952:	iload	31
   954:	iaload
   955:	istore	31
   957:	iload	24
   959:	sipush	255
   962:	iand
   963:	istore	24
   965:	iload	31
   967:	bipush	8
   969:	ishl
   970:	iload	24
   972:	ior
   973:	istore	31
   975:	iload	6
   977:	sipush	255
   980:	iand
   981:	istore	6
   983:	getstatic	#7; //Field gtable4:[I
   986:	iload	6
   988:	iaload
   989:	istore	6
   991:	iload	22
   993:	sipush	255
   996:	iand
   997:	istore	22
   999:	getstatic	#7; //Field gtable4:[I
   1002:	iload	22
   1004:	iaload
   1005:	istore	22
   1007:	iload	6
   1009:	sipush	255
   1012:	iand
   1013:	istore	6
   1015:	iload	22
   1017:	bipush	8
   1019:	ishl
   1020:	iload	6
   1022:	ior
   1023:	istore	22
   1025:	iload	31
   1027:	ldc	#2; //int 65535
   1029:	iand
   1030:	istore	31
   1032:	iload	22
   1034:	bipush	16
   1036:	ishl
   1037:	iload	31
   1039:	ior
   1040:	istore	22
   1042:	iload	22
   1044:	iconst_1
   1045:	ixor
   1046:	istore	22
   1048:	iload	29
   1050:	iload	22
   1052:	ixor
   1053:	istore	22
   1055:	iload	4
   1057:	iload	22
   1059:	ixor
   1060:	istore	4
   1062:	iload	4
   1064:	iconst_0
   1065:	ishr
   1066:	istore	29
   1068:	iload	4
   1070:	bipush	8
   1072:	ishr
   1073:	istore	31
   1075:	iload	4
   1077:	bipush	16
   1079:	ishr
   1080:	istore	6
   1082:	iload	4
   1084:	bipush	24
   1086:	ishr
   1087:	istore	4
   1089:	iload	27
   1091:	sipush	255
   1094:	iand
   1095:	istore	27
   1097:	getstatic	#3; //Field gtable0:[I
   1100:	iload	27
   1102:	iaload
   1103:	istore	27
   1105:	iload	20
   1107:	sipush	255
   1110:	iand
   1111:	istore	20
   1113:	getstatic	#4; //Field gtable1:[I
   1116:	iload	20
   1118:	iaload
   1119:	istore	20
   1121:	iload	27
   1123:	iload	20
   1125:	ixor
   1126:	istore	20
   1128:	iload	17
   1130:	sipush	255
   1133:	iand
   1134:	istore	17
   1136:	getstatic	#5; //Field gtable2:[I
   1139:	iload	17
   1141:	iaload
   1142:	istore	17
   1144:	iload	20
   1146:	iload	17
   1148:	ixor
   1149:	istore	17
   1151:	iload	16
   1153:	sipush	255
   1156:	iand
   1157:	istore	16
   1159:	getstatic	#6; //Field gtable3:[I
   1162:	iload	16
   1164:	iaload
   1165:	istore	16
   1167:	iload	17
   1169:	iload	16
   1171:	ixor
   1172:	istore	16
   1174:	iload	25
   1176:	iload	22
   1178:	ixor
   1179:	istore	25
   1181:	iload	16
   1183:	iload	25
   1185:	ixor
   1186:	istore	16
   1188:	iload	16
   1190:	iconst_0
   1191:	ishr
   1192:	istore	17
   1194:	iload	16
   1196:	bipush	8
   1198:	ishr
   1199:	istore	20
   1201:	iload	16
   1203:	bipush	16
   1205:	ishr
   1206:	istore	27
   1208:	iload	16
   1210:	bipush	24
   1212:	ishr
   1213:	istore	16
   1215:	iload	23
   1217:	sipush	255
   1220:	iand
   1221:	istore	23
   1223:	getstatic	#3; //Field gtable0:[I
   1226:	iload	23
   1228:	iaload
   1229:	istore	23
   1231:	iload	18
   1233:	sipush	255
   1236:	iand
   1237:	istore	18
   1239:	getstatic	#4; //Field gtable1:[I
   1242:	iload	18
   1244:	iaload
   1245:	istore	18
   1247:	iload	23
   1249:	iload	18
   1251:	ixor
   1252:	istore	18
   1254:	iload	30
   1256:	sipush	255
   1259:	iand
   1260:	istore	30
   1262:	getstatic	#5; //Field gtable2:[I
   1265:	iload	30
   1267:	iaload
   1268:	istore	30
   1270:	iload	18
   1272:	iload	30
   1274:	ixor
   1275:	istore	30
   1277:	iload	12
   1279:	sipush	255
   1282:	iand
   1283:	istore	12
   1285:	getstatic	#6; //Field gtable3:[I
   1288:	iload	12
   1290:	iaload
   1291:	istore	12
   1293:	iload	30
   1295:	iload	12
   1297:	ixor
   1298:	istore	12
   1300:	iload	21
   1302:	iload	25
   1304:	ixor
   1305:	istore	21
   1307:	iload	12
   1309:	iload	21
   1311:	ixor
   1312:	istore	12
   1314:	iload	12
   1316:	iconst_0
   1317:	ishr
   1318:	istore	30
   1320:	iload	12
   1322:	bipush	8
   1324:	ishr
   1325:	istore	18
   1327:	iload	12
   1329:	bipush	16
   1331:	ishr
   1332:	istore	23
   1334:	iload	12
   1336:	bipush	24
   1338:	ishr
   1339:	istore	12
   1341:	iload	19
   1343:	sipush	255
   1346:	iand
   1347:	istore	19
   1349:	getstatic	#3; //Field gtable0:[I
   1352:	iload	19
   1354:	iaload
   1355:	istore	19
   1357:	iload	28
   1359:	sipush	255
   1362:	iand
   1363:	istore	28
   1365:	getstatic	#4; //Field gtable1:[I
   1368:	iload	28
   1370:	iaload
   1371:	istore	28
   1373:	iload	19
   1375:	iload	28
   1377:	ixor
   1378:	istore	28
   1380:	iload	26
   1382:	sipush	255
   1385:	iand
   1386:	istore	26
   1388:	getstatic	#5; //Field gtable2:[I
   1391:	iload	26
   1393:	iaload
   1394:	istore	26
   1396:	iload	28
   1398:	iload	26
   1400:	ixor
   1401:	istore	26
   1403:	iload	8
   1405:	sipush	255
   1408:	iand
   1409:	istore	8
   1411:	getstatic	#6; //Field gtable3:[I
   1414:	iload	8
   1416:	iaload
   1417:	istore	8
   1419:	iload	26
   1421:	iload	8
   1423:	ixor
   1424:	istore	8
   1426:	iload	15
   1428:	iload	21
   1430:	ixor
   1431:	istore	15
   1433:	iload	8
   1435:	iload	15
   1437:	ixor
   1438:	istore	8
   1440:	iload	8
   1442:	iconst_0
   1443:	ishr
   1444:	istore	26
   1446:	iload	8
   1448:	bipush	8
   1450:	ishr
   1451:	istore	28
   1453:	iload	8
   1455:	bipush	16
   1457:	ishr
   1458:	istore	19
   1460:	iload	8
   1462:	bipush	24
   1464:	ishr
   1465:	istore	8
   1467:	iload	29
   1469:	sipush	255
   1472:	iand
   1473:	istore	29
   1475:	getstatic	#3; //Field gtable0:[I
   1478:	iload	29
   1480:	iaload
   1481:	istore	29
   1483:	iload	20
   1485:	sipush	255
   1488:	iand
   1489:	istore	20
   1491:	getstatic	#4; //Field gtable1:[I
   1494:	iload	20
   1496:	iaload
   1497:	istore	20
   1499:	iload	29
   1501:	iload	20
   1503:	ixor
   1504:	istore	20
   1506:	iload	23
   1508:	sipush	255
   1511:	iand
   1512:	istore	23
   1514:	getstatic	#5; //Field gtable2:[I
   1517:	iload	23
   1519:	iaload
   1520:	istore	23
   1522:	iload	20
   1524:	iload	23
   1526:	ixor
   1527:	istore	23
   1529:	iload	8
   1531:	sipush	255
   1534:	iand
   1535:	istore	8
   1537:	getstatic	#6; //Field gtable3:[I
   1540:	iload	8
   1542:	iaload
   1543:	istore	8
   1545:	iload	23
   1547:	iload	8
   1549:	ixor
   1550:	istore	8
   1552:	iload	15
   1554:	bipush	24
   1556:	ishl
   1557:	iload	15
   1559:	bipush	8
   1561:	iushr
   1562:	ior
   1563:	istore	23
   1565:	iload	23
   1567:	iconst_0
   1568:	ishr
   1569:	istore	20
   1571:	iload	23
   1573:	bipush	8
   1575:	ishr
   1576:	istore	29
   1578:	iload	23
   1580:	bipush	16
   1582:	ishr
   1583:	istore	24
   1585:	iload	23
   1587:	bipush	24
   1589:	ishr
   1590:	istore	23
   1592:	iload	20
   1594:	sipush	255
   1597:	iand
   1598:	istore	20
   1600:	getstatic	#7; //Field gtable4:[I
   1603:	iload	20
   1605:	iaload
   1606:	istore	20
   1608:	iload	29
   1610:	sipush	255
   1613:	iand
   1614:	istore	29
   1616:	getstatic	#7; //Field gtable4:[I
   1619:	iload	29
   1621:	iaload
   1622:	istore	29
   1624:	iload	20
   1626:	sipush	255
   1629:	iand
   1630:	istore	20
   1632:	iload	29
   1634:	bipush	8
   1636:	ishl
   1637:	iload	20
   1639:	ior
   1640:	istore	29
   1642:	iload	24
   1644:	sipush	255
   1647:	iand
   1648:	istore	24
   1650:	getstatic	#7; //Field gtable4:[I
   1653:	iload	24
   1655:	iaload
   1656:	istore	24
   1658:	iload	23
   1660:	sipush	255
   1663:	iand
   1664:	istore	23
   1666:	getstatic	#7; //Field gtable4:[I
   1669:	iload	23
   1671:	iaload
   1672:	istore	23
   1674:	iload	24
   1676:	sipush	255
   1679:	iand
   1680:	istore	24
   1682:	iload	23
   1684:	bipush	8
   1686:	ishl
   1687:	iload	24
   1689:	ior
   1690:	istore	23
   1692:	iload	29
   1694:	ldc	#2; //int 65535
   1696:	iand
   1697:	istore	29
   1699:	iload	23
   1701:	bipush	16
   1703:	ishl
   1704:	iload	29
   1706:	ior
   1707:	istore	23
   1709:	iload	23
   1711:	iconst_2
   1712:	ixor
   1713:	istore	23
   1715:	iload	22
   1717:	iload	23
   1719:	ixor
   1720:	istore	23
   1722:	iload	8
   1724:	iload	23
   1726:	ixor
   1727:	istore	8
   1729:	iload	8
   1731:	iconst_0
   1732:	ishr
   1733:	istore	22
   1735:	iload	8
   1737:	bipush	8
   1739:	ishr
   1740:	istore	29
   1742:	iload	8
   1744:	bipush	16
   1746:	ishr
   1747:	istore	24
   1749:	iload	8
   1751:	bipush	24
   1753:	ishr
   1754:	istore	8
   1756:	iload	17
   1758:	sipush	255
   1761:	iand
   1762:	istore	17
   1764:	getstatic	#3; //Field gtable0:[I
   1767:	iload	17
   1769:	iaload
   1770:	istore	17
   1772:	iload	18
   1774:	sipush	255
   1777:	iand
   1778:	istore	18
   1780:	getstatic	#4; //Field gtable1:[I
   1783:	iload	18
   1785:	iaload
   1786:	istore	18
   1788:	iload	17
   1790:	iload	18
   1792:	ixor
   1793:	istore	18
   1795:	iload	19
   1797:	sipush	255
   1800:	iand
   1801:	istore	19
   1803:	getstatic	#5; //Field gtable2:[I
   1806:	iload	19
   1808:	iaload
   1809:	istore	19
   1811:	iload	18
   1813:	iload	19
   1815:	ixor
   1816:	istore	19
   1818:	iload	4
   1820:	sipush	255
   1823:	iand
   1824:	istore	4
   1826:	getstatic	#6; //Field gtable3:[I
   1829:	iload	4
   1831:	iaload
   1832:	istore	4
   1834:	iload	19
   1836:	iload	4
   1838:	ixor
   1839:	istore	4
   1841:	iload	25
   1843:	iload	23
   1845:	ixor
   1846:	istore	25
   1848:	iload	4
   1850:	iload	25
   1852:	ixor
   1853:	istore	4
   1855:	iload	4
   1857:	iconst_0
   1858:	ishr
   1859:	istore	19
   1861:	iload	4
   1863:	bipush	8
   1865:	ishr
   1866:	istore	18
   1868:	iload	4
   1870:	bipush	16
   1872:	ishr
   1873:	istore	17
   1875:	iload	4
   1877:	bipush	24
   1879:	ishr
   1880:	istore	4
   1882:	iload	30
   1884:	sipush	255
   1887:	iand
   1888:	istore	30
   1890:	getstatic	#3; //Field gtable0:[I
   1893:	iload	30
   1895:	iaload
   1896:	istore	30
   1898:	iload	28
   1900:	sipush	255
   1903:	iand
   1904:	istore	28
   1906:	getstatic	#4; //Field gtable1:[I
   1909:	iload	28
   1911:	iaload
   1912:	istore	28
   1914:	iload	30
   1916:	iload	28
   1918:	ixor
   1919:	istore	28
   1921:	iload	6
   1923:	sipush	255
   1926:	iand
   1927:	istore	6
   1929:	getstatic	#5; //Field gtable2:[I
   1932:	iload	6
   1934:	iaload
   1935:	istore	6
   1937:	iload	28
   1939:	iload	6
   1941:	ixor
   1942:	istore	6
   1944:	iload	16
   1946:	sipush	255
   1949:	iand
   1950:	istore	16
   1952:	getstatic	#6; //Field gtable3:[I
   1955:	iload	16
   1957:	iaload
   1958:	istore	16
   1960:	iload	6
   1962:	iload	16
   1964:	ixor
   1965:	istore	16
   1967:	iload	21
   1969:	iload	25
   1971:	ixor
   1972:	istore	21
   1974:	iload	16
   1976:	iload	21
   1978:	ixor
   1979:	istore	16
   1981:	iload	16
   1983:	iconst_0
   1984:	ishr
   1985:	istore	6
   1987:	iload	16
   1989:	bipush	8
   1991:	ishr
   1992:	istore	28
   1994:	iload	16
   1996:	bipush	16
   1998:	ishr
   1999:	istore	30
   2001:	iload	16
   2003:	bipush	24
   2005:	ishr
   2006:	istore	16
   2008:	iload	26
   2010:	sipush	255
   2013:	iand
   2014:	istore	26
   2016:	getstatic	#3; //Field gtable0:[I
   2019:	iload	26
   2021:	iaload
   2022:	istore	26
   2024:	iload	31
   2026:	sipush	255
   2029:	iand
   2030:	istore	31
   2032:	getstatic	#4; //Field gtable1:[I
   2035:	iload	31
   2037:	iaload
   2038:	istore	31
   2040:	iload	26
   2042:	iload	31
   2044:	ixor
   2045:	istore	31
   2047:	iload	27
   2049:	sipush	255
   2052:	iand
   2053:	istore	27
   2055:	getstatic	#5; //Field gtable2:[I
   2058:	iload	27
   2060:	iaload
   2061:	istore	27
   2063:	iload	31
   2065:	iload	27
   2067:	ixor
   2068:	istore	27
   2070:	iload	12
   2072:	sipush	255
   2075:	iand
   2076:	istore	12
   2078:	getstatic	#6; //Field gtable3:[I
   2081:	iload	12
   2083:	iaload
   2084:	istore	12
   2086:	iload	27
   2088:	iload	12
   2090:	ixor
   2091:	istore	12
   2093:	iload	15
   2095:	iload	21
   2097:	ixor
   2098:	istore	15
   2100:	iload	12
   2102:	iload	15
   2104:	ixor
   2105:	istore	12
   2107:	iload	12
   2109:	iconst_0
   2110:	ishr
   2111:	istore	27
   2113:	iload	12
   2115:	bipush	8
   2117:	ishr
   2118:	istore	31
   2120:	iload	12
   2122:	bipush	16
   2124:	ishr
   2125:	istore	26
   2127:	iload	12
   2129:	bipush	24
   2131:	ishr
   2132:	istore	12
   2134:	iload	22
   2136:	sipush	255
   2139:	iand
   2140:	istore	22
   2142:	getstatic	#3; //Field gtable0:[I
   2145:	iload	22
   2147:	iaload
   2148:	istore	22
   2150:	iload	18
   2152:	sipush	255
   2155:	iand
   2156:	istore	18
   2158:	getstatic	#4; //Field gtable1:[I
   2161:	iload	18
   2163:	iaload
   2164:	istore	18
   2166:	iload	22
   2168:	iload	18
   2170:	ixor
   2171:	istore	18
   2173:	iload	30
   2175:	sipush	255
   2178:	iand
   2179:	istore	30
   2181:	getstatic	#5; //Field gtable2:[I
   2184:	iload	30
   2186:	iaload
   2187:	istore	30
   2189:	iload	18
   2191:	iload	30
   2193:	ixor
   2194:	istore	30
   2196:	iload	12
   2198:	sipush	255
   2201:	iand
   2202:	istore	12
   2204:	getstatic	#6; //Field gtable3:[I
   2207:	iload	12
   2209:	iaload
   2210:	istore	12
   2212:	iload	30
   2214:	iload	12
   2216:	ixor
   2217:	istore	12
   2219:	iload	15
   2221:	bipush	24
   2223:	ishl
   2224:	iload	15
   2226:	bipush	8
   2228:	iushr
   2229:	ior
   2230:	istore	30
   2232:	iload	30
   2234:	iconst_0
   2235:	ishr
   2236:	istore	18
   2238:	iload	30
   2240:	bipush	8
   2242:	ishr
   2243:	istore	22
   2245:	iload	30
   2247:	bipush	16
   2249:	ishr
   2250:	istore	20
   2252:	iload	30
   2254:	bipush	24
   2256:	ishr
   2257:	istore	30
   2259:	iload	18
   2261:	sipush	255
   2264:	iand
   2265:	istore	18
   2267:	getstatic	#7; //Field gtable4:[I
   2270:	iload	18
   2272:	iaload
   2273:	istore	18
   2275:	iload	22
   2277:	sipush	255
   2280:	iand
   2281:	istore	22
   2283:	getstatic	#7; //Field gtable4:[I
   2286:	iload	22
   2288:	iaload
   2289:	istore	22
   2291:	iload	18
   2293:	sipush	255
   2296:	iand
   2297:	istore	18
   2299:	iload	22
   2301:	bipush	8
   2303:	ishl
   2304:	iload	18
   2306:	ior
   2307:	istore	22
   2309:	iload	20
   2311:	sipush	255
   2314:	iand
   2315:	istore	20
   2317:	getstatic	#7; //Field gtable4:[I
   2320:	iload	20
   2322:	iaload
   2323:	istore	20
   2325:	iload	30
   2327:	sipush	255
   2330:	iand
   2331:	istore	30
   2333:	getstatic	#7; //Field gtable4:[I
   2336:	iload	30
   2338:	iaload
   2339:	istore	30
   2341:	iload	20
   2343:	sipush	255
   2346:	iand
   2347:	istore	20
   2349:	iload	30
   2351:	bipush	8
   2353:	ishl
   2354:	iload	20
   2356:	ior
   2357:	istore	30
   2359:	iload	22
   2361:	ldc	#2; //int 65535
   2363:	iand
   2364:	istore	22
   2366:	iload	30
   2368:	bipush	16
   2370:	ishl
   2371:	iload	22
   2373:	ior
   2374:	istore	30
   2376:	iload	30
   2378:	iconst_4
   2379:	ixor
   2380:	istore	30
   2382:	iload	23
   2384:	iload	30
   2386:	ixor
   2387:	istore	30
   2389:	iload	12
   2391:	iload	30
   2393:	ixor
   2394:	istore	12
   2396:	iload	12
   2398:	iconst_0
   2399:	ishr
   2400:	istore	23
   2402:	iload	12
   2404:	bipush	8
   2406:	ishr
   2407:	istore	22
   2409:	iload	12
   2411:	bipush	16
   2413:	ishr
   2414:	istore	20
   2416:	iload	12
   2418:	bipush	24
   2420:	ishr
   2421:	istore	12
   2423:	iload	19
   2425:	sipush	255
   2428:	iand
   2429:	istore	19
   2431:	getstatic	#3; //Field gtable0:[I
   2434:	iload	19
   2436:	iaload
   2437:	istore	19
   2439:	iload	28
   2441:	sipush	255
   2444:	iand
   2445:	istore	28
   2447:	getstatic	#4; //Field gtable1:[I
   2450:	iload	28
   2452:	iaload
   2453:	istore	28
   2455:	iload	19
   2457:	iload	28
   2459:	ixor
   2460:	istore	28
   2462:	iload	26
   2464:	sipush	255
   2467:	iand
   2468:	istore	26
   2470:	getstatic	#5; //Field gtable2:[I
   2473:	iload	26
   2475:	iaload
   2476:	istore	26
   2478:	iload	28
   2480:	iload	26
   2482:	ixor
   2483:	istore	26
   2485:	iload	8
   2487:	sipush	255
   2490:	iand
   2491:	istore	8
   2493:	getstatic	#6; //Field gtable3:[I
   2496:	iload	8
   2498:	iaload
   2499:	istore	8
   2501:	iload	26
   2503:	iload	8
   2505:	ixor
   2506:	istore	8
   2508:	iload	25
   2510:	iload	30
   2512:	ixor
   2513:	istore	25
   2515:	iload	8
   2517:	iload	25
   2519:	ixor
   2520:	istore	8
   2522:	iload	8
   2524:	iconst_0
   2525:	ishr
   2526:	istore	26
   2528:	iload	8
   2530:	bipush	8
   2532:	ishr
   2533:	istore	28
   2535:	iload	8
   2537:	bipush	16
   2539:	ishr
   2540:	istore	19
   2542:	iload	8
   2544:	bipush	24
   2546:	ishr
   2547:	istore	8
   2549:	iload	6
   2551:	sipush	255
   2554:	iand
   2555:	istore	6
   2557:	getstatic	#3; //Field gtable0:[I
   2560:	iload	6
   2562:	iaload
   2563:	istore	6
   2565:	iload	31
   2567:	sipush	255
   2570:	iand
   2571:	istore	31
   2573:	getstatic	#4; //Field gtable1:[I
   2576:	iload	31
   2578:	iaload
   2579:	istore	31
   2581:	iload	6
   2583:	iload	31
   2585:	ixor
   2586:	istore	31
   2588:	iload	24
   2590:	sipush	255
   2593:	iand
   2594:	istore	24
   2596:	getstatic	#5; //Field gtable2:[I
   2599:	iload	24
   2601:	iaload
   2602:	istore	24
   2604:	iload	31
   2606:	iload	24
   2608:	ixor
   2609:	istore	24
   2611:	iload	4
   2613:	sipush	255
   2616:	iand
   2617:	istore	4
   2619:	getstatic	#6; //Field gtable3:[I
   2622:	iload	4
   2624:	iaload
   2625:	istore	4
   2627:	iload	24
   2629:	iload	4
   2631:	ixor
   2632:	istore	4
   2634:	iload	21
   2636:	iload	25
   2638:	ixor
   2639:	istore	21
   2641:	iload	4
   2643:	iload	21
   2645:	ixor
   2646:	istore	4
   2648:	iload	4
   2650:	iconst_0
   2651:	ishr
   2652:	istore	24
   2654:	iload	4
   2656:	bipush	8
   2658:	ishr
   2659:	istore	31
   2661:	iload	4
   2663:	bipush	16
   2665:	ishr
   2666:	istore	6
   2668:	iload	4
   2670:	bipush	24
   2672:	ishr
   2673:	istore	4
   2675:	iload	27
   2677:	sipush	255
   2680:	iand
   2681:	istore	27
   2683:	getstatic	#3; //Field gtable0:[I
   2686:	iload	27
   2688:	iaload
   2689:	istore	27
   2691:	iload	29
   2693:	sipush	255
   2696:	iand
   2697:	istore	29
   2699:	getstatic	#4; //Field gtable1:[I
   2702:	iload	29
   2704:	iaload
   2705:	istore	29
   2707:	iload	27
   2709:	iload	29
   2711:	ixor
   2712:	istore	29
   2714:	iload	17
   2716:	sipush	255
   2719:	iand
   2720:	istore	17
   2722:	getstatic	#5; //Field gtable2:[I
   2725:	iload	17
   2727:	iaload
   2728:	istore	17
   2730:	iload	29
   2732:	iload	17
   2734:	ixor
   2735:	istore	17
   2737:	iload	16
   2739:	sipush	255
   2742:	iand
   2743:	istore	16
   2745:	getstatic	#6; //Field gtable3:[I
   2748:	iload	16
   2750:	iaload
   2751:	istore	16
   2753:	iload	17
   2755:	iload	16
   2757:	ixor
   2758:	istore	16
   2760:	iload	15
   2762:	iload	21
   2764:	ixor
   2765:	istore	15
   2767:	iload	16
   2769:	iload	15
   2771:	ixor
   2772:	istore	16
   2774:	iload	16
   2776:	iconst_0
   2777:	ishr
   2778:	istore	17
   2780:	iload	16
   2782:	bipush	8
   2784:	ishr
   2785:	istore	29
   2787:	iload	16
   2789:	bipush	16
   2791:	ishr
   2792:	istore	27
   2794:	iload	16
   2796:	bipush	24
   2798:	ishr
   2799:	istore	16
   2801:	iload	23
   2803:	sipush	255
   2806:	iand
   2807:	istore	23
   2809:	getstatic	#3; //Field gtable0:[I
   2812:	iload	23
   2814:	iaload
   2815:	istore	23
   2817:	iload	28
   2819:	sipush	255
   2822:	iand
   2823:	istore	28
   2825:	getstatic	#4; //Field gtable1:[I
   2828:	iload	28
   2830:	iaload
   2831:	istore	28
   2833:	iload	23
   2835:	iload	28
   2837:	ixor
   2838:	istore	28
   2840:	iload	6
   2842:	sipush	255
   2845:	iand
   2846:	istore	6
   2848:	getstatic	#5; //Field gtable2:[I
   2851:	iload	6
   2853:	iaload
   2854:	istore	6
   2856:	iload	28
   2858:	iload	6
   2860:	ixor
   2861:	istore	6
   2863:	iload	16
   2865:	sipush	255
   2868:	iand
   2869:	istore	16
   2871:	getstatic	#6; //Field gtable3:[I
   2874:	iload	16
   2876:	iaload
   2877:	istore	16
   2879:	iload	6
   2881:	iload	16
   2883:	ixor
   2884:	istore	16
   2886:	iload	15
   2888:	bipush	24
   2890:	ishl
   2891:	iload	15
   2893:	bipush	8
   2895:	iushr
   2896:	ior
   2897:	istore	6
   2899:	iload	6
   2901:	iconst_0
   2902:	ishr
   2903:	istore	28
   2905:	iload	6
   2907:	bipush	8
   2909:	ishr
   2910:	istore	23
   2912:	iload	6
   2914:	bipush	16
   2916:	ishr
   2917:	istore	18
   2919:	iload	6
   2921:	bipush	24
   2923:	ishr
   2924:	istore	6
   2926:	iload	28
   2928:	sipush	255
   2931:	iand
   2932:	istore	28
   2934:	getstatic	#7; //Field gtable4:[I
   2937:	iload	28
   2939:	iaload
   2940:	istore	28
   2942:	iload	23
   2944:	sipush	255
   2947:	iand
   2948:	istore	23
   2950:	getstatic	#7; //Field gtable4:[I
   2953:	iload	23
   2955:	iaload
   2956:	istore	23
   2958:	iload	28
   2960:	sipush	255
   2963:	iand
   2964:	istore	28
   2966:	iload	23
   2968:	bipush	8
   2970:	ishl
   2971:	iload	28
   2973:	ior
   2974:	istore	23
   2976:	iload	18
   2978:	sipush	255
   2981:	iand
   2982:	istore	18
   2984:	getstatic	#7; //Field gtable4:[I
   2987:	iload	18
   2989:	iaload
   2990:	istore	18
   2992:	iload	6
   2994:	sipush	255
   2997:	iand
   2998:	istore	6
   3000:	getstatic	#7; //Field gtable4:[I
   3003:	iload	6
   3005:	iaload
   3006:	istore	6
   3008:	iload	18
   3010:	sipush	255
   3013:	iand
   3014:	istore	18
   3016:	iload	6
   3018:	bipush	8
   3020:	ishl
   3021:	iload	18
   3023:	ior
   3024:	istore	6
   3026:	iload	23
   3028:	ldc	#2; //int 65535
   3030:	iand
   3031:	istore	23
   3033:	iload	6
   3035:	bipush	16
   3037:	ishl
   3038:	iload	23
   3040:	ior
   3041:	istore	6
   3043:	iload	6
   3045:	bipush	8
   3047:	ixor
   3048:	istore	6
   3050:	iload	30
   3052:	iload	6
   3054:	ixor
   3055:	istore	6
   3057:	iload	16
   3059:	iload	6
   3061:	ixor
   3062:	istore	16
   3064:	iload	16
   3066:	iconst_0
   3067:	ishr
   3068:	istore	30
   3070:	iload	16
   3072:	bipush	8
   3074:	ishr
   3075:	istore	23
   3077:	iload	16
   3079:	bipush	16
   3081:	ishr
   3082:	istore	18
   3084:	iload	16
   3086:	bipush	24
   3088:	ishr
   3089:	istore	16
   3091:	iload	26
   3093:	sipush	255
   3096:	iand
   3097:	istore	26
   3099:	getstatic	#3; //Field gtable0:[I
   3102:	iload	26
   3104:	iaload
   3105:	istore	26
   3107:	iload	31
   3109:	sipush	255
   3112:	iand
   3113:	istore	31
   3115:	getstatic	#4; //Field gtable1:[I
   3118:	iload	31
   3120:	iaload
   3121:	istore	31
   3123:	iload	26
   3125:	iload	31
   3127:	ixor
   3128:	istore	31
   3130:	iload	27
   3132:	sipush	255
   3135:	iand
   3136:	istore	27
   3138:	getstatic	#5; //Field gtable2:[I
   3141:	iload	27
   3143:	iaload
   3144:	istore	27
   3146:	iload	31
   3148:	iload	27
   3150:	ixor
   3151:	istore	27
   3153:	iload	12
   3155:	sipush	255
   3158:	iand
   3159:	istore	12
   3161:	getstatic	#6; //Field gtable3:[I
   3164:	iload	12
   3166:	iaload
   3167:	istore	12
   3169:	iload	27
   3171:	iload	12
   3173:	ixor
   3174:	istore	12
   3176:	iload	25
   3178:	iload	6
   3180:	ixor
   3181:	istore	25
   3183:	iload	12
   3185:	iload	25
   3187:	ixor
   3188:	istore	12
   3190:	iload	12
   3192:	iconst_0
   3193:	ishr
   3194:	istore	27
   3196:	iload	12
   3198:	bipush	8
   3200:	ishr
   3201:	istore	31
   3203:	iload	12
   3205:	bipush	16
   3207:	ishr
   3208:	istore	26
   3210:	iload	12
   3212:	bipush	24
   3214:	ishr
   3215:	istore	12
   3217:	iload	24
   3219:	sipush	255
   3222:	iand
   3223:	istore	24
   3225:	getstatic	#3; //Field gtable0:[I
   3228:	iload	24
   3230:	iaload
   3231:	istore	24
   3233:	iload	29
   3235:	sipush	255
   3238:	iand
   3239:	istore	29
   3241:	getstatic	#4; //Field gtable1:[I
   3244:	iload	29
   3246:	iaload
   3247:	istore	29
   3249:	iload	24
   3251:	iload	29
   3253:	ixor
   3254:	istore	29
   3256:	iload	20
   3258:	sipush	255
   3261:	iand
   3262:	istore	20
   3264:	getstatic	#5; //Field gtable2:[I
   3267:	iload	20
   3269:	iaload
   3270:	istore	20
   3272:	iload	29
   3274:	iload	20
   3276:	ixor
   3277:	istore	20
   3279:	iload	8
   3281:	sipush	255
   3284:	iand
   3285:	istore	8
   3287:	getstatic	#6; //Field gtable3:[I
   3290:	iload	8
   3292:	iaload
   3293:	istore	8
   3295:	iload	20
   3297:	iload	8
   3299:	ixor
   3300:	istore	8
   3302:	iload	21
   3304:	iload	25
   3306:	ixor
   3307:	istore	21
   3309:	iload	8
   3311:	iload	21
   3313:	ixor
   3314:	istore	8
   3316:	iload	8
   3318:	iconst_0
   3319:	ishr
   3320:	istore	20
   3322:	iload	8
   3324:	bipush	8
   3326:	ishr
   3327:	istore	29
   3329:	iload	8
   3331:	bipush	16
   3333:	ishr
   3334:	istore	24
   3336:	iload	8
   3338:	bipush	24
   3340:	ishr
   3341:	istore	8
   3343:	iload	17
   3345:	sipush	255
   3348:	iand
   3349:	istore	17
   3351:	getstatic	#3; //Field gtable0:[I
   3354:	iload	17
   3356:	iaload
   3357:	istore	17
   3359:	iload	22
   3361:	sipush	255
   3364:	iand
   3365:	istore	22
   3367:	getstatic	#4; //Field gtable1:[I
   3370:	iload	22
   3372:	iaload
   3373:	istore	22
   3375:	iload	17
   3377:	iload	22
   3379:	ixor
   3380:	istore	22
   3382:	iload	19
   3384:	sipush	255
   3387:	iand
   3388:	istore	19
   3390:	getstatic	#5; //Field gtable2:[I
   3393:	iload	19
   3395:	iaload
   3396:	istore	19
   3398:	iload	22
   3400:	iload	19
   3402:	ixor
   3403:	istore	19
   3405:	iload	4
   3407:	sipush	255
   3410:	iand
   3411:	istore	4
   3413:	getstatic	#6; //Field gtable3:[I
   3416:	iload	4
   3418:	iaload
   3419:	istore	4
   3421:	iload	19
   3423:	iload	4
   3425:	ixor
   3426:	istore	4
   3428:	iload	15
   3430:	iload	21
   3432:	ixor
   3433:	istore	15
   3435:	iload	4
   3437:	iload	15
   3439:	ixor
   3440:	istore	4
   3442:	iload	4
   3444:	iconst_0
   3445:	ishr
   3446:	istore	19
   3448:	iload	4
   3450:	bipush	8
   3452:	ishr
   3453:	istore	22
   3455:	iload	4
   3457:	bipush	16
   3459:	ishr
   3460:	istore	17
   3462:	iload	4
   3464:	bipush	24
   3466:	ishr
   3467:	istore	4
   3469:	iload	30
   3471:	sipush	255
   3474:	iand
   3475:	istore	30
   3477:	getstatic	#3; //Field gtable0:[I
   3480:	iload	30
   3482:	iaload
   3483:	istore	30
   3485:	iload	31
   3487:	sipush	255
   3490:	iand
   3491:	istore	31
   3493:	getstatic	#4; //Field gtable1:[I
   3496:	iload	31
   3498:	iaload
   3499:	istore	31
   3501:	iload	30
   3503:	iload	31
   3505:	ixor
   3506:	istore	31
   3508:	iload	24
   3510:	sipush	255
   3513:	iand
   3514:	istore	24
   3516:	getstatic	#5; //Field gtable2:[I
   3519:	iload	24
   3521:	iaload
   3522:	istore	24
   3524:	iload	31
   3526:	iload	24
   3528:	ixor
   3529:	istore	24
   3531:	iload	4
   3533:	sipush	255
   3536:	iand
   3537:	istore	4
   3539:	getstatic	#6; //Field gtable3:[I
   3542:	iload	4
   3544:	iaload
   3545:	istore	4
   3547:	iload	24
   3549:	iload	4
   3551:	ixor
   3552:	istore	4
   3554:	iload	15
   3556:	bipush	24
   3558:	ishl
   3559:	iload	15
   3561:	bipush	8
   3563:	iushr
   3564:	ior
   3565:	istore	24
   3567:	iload	24
   3569:	iconst_0
   3570:	ishr
   3571:	istore	31
   3573:	iload	24
   3575:	bipush	8
   3577:	ishr
   3578:	istore	30
   3580:	iload	24
   3582:	bipush	16
   3584:	ishr
   3585:	istore	28
   3587:	iload	24
   3589:	bipush	24
   3591:	ishr
   3592:	istore	24
   3594:	iload	31
   3596:	sipush	255
   3599:	iand
   3600:	istore	31
   3602:	getstatic	#7; //Field gtable4:[I
   3605:	iload	31
   3607:	iaload
   3608:	istore	31
   3610:	iload	30
   3612:	sipush	255
   3615:	iand
   3616:	istore	30
   3618:	getstatic	#7; //Field gtable4:[I
   3621:	iload	30
   3623:	iaload
   3624:	istore	30
   3626:	iload	31
   3628:	sipush	255
   3631:	iand
   3632:	istore	31
   3634:	iload	30
   3636:	bipush	8
   3638:	ishl
   3639:	iload	31
   3641:	ior
   3642:	istore	30
   3644:	iload	28
   3646:	sipush	255
   3649:	iand
   3650:	istore	28
   3652:	getstatic	#7; //Field gtable4:[I
   3655:	iload	28
   3657:	iaload
   3658:	istore	28
   3660:	iload	24
   3662:	sipush	255
   3665:	iand
   3666:	istore	24
   3668:	getstatic	#7; //Field gtable4:[I
   3671:	iload	24
   3673:	iaload
   3674:	istore	24
   3676:	iload	28
   3678:	sipush	255
   3681:	iand
   3682:	istore	28
   3684:	iload	24
   3686:	bipush	8
   3688:	ishl
   3689:	iload	28
   3691:	ior
   3692:	istore	24
   3694:	iload	30
   3696:	ldc	#2; //int 65535
   3698:	iand
   3699:	istore	30
   3701:	iload	24
   3703:	bipush	16
   3705:	ishl
   3706:	iload	30
   3708:	ior
   3709:	istore	24
   3711:	iload	24
   3713:	bipush	16
   3715:	ixor
   3716:	istore	24
   3718:	iload	6
   3720:	iload	24
   3722:	ixor
   3723:	istore	24
   3725:	iload	4
   3727:	iload	24
   3729:	ixor
   3730:	istore	4
   3732:	iload	4
   3734:	iconst_0
   3735:	ishr
   3736:	istore	6
   3738:	iload	4
   3740:	bipush	8
   3742:	ishr
   3743:	istore	30
   3745:	iload	4
   3747:	bipush	16
   3749:	ishr
   3750:	istore	28
   3752:	iload	4
   3754:	bipush	24
   3756:	ishr
   3757:	istore	4
   3759:	iload	27
   3761:	sipush	255
   3764:	iand
   3765:	istore	27
   3767:	getstatic	#3; //Field gtable0:[I
   3770:	iload	27
   3772:	iaload
   3773:	istore	27
   3775:	iload	29
   3777:	sipush	255
   3780:	iand
   3781:	istore	29
   3783:	getstatic	#4; //Field gtable1:[I
   3786:	iload	29
   3788:	iaload
   3789:	istore	29
   3791:	iload	27
   3793:	iload	29
   3795:	ixor
   3796:	istore	29
   3798:	iload	17
   3800:	sipush	255
   3803:	iand
   3804:	istore	17
   3806:	getstatic	#5; //Field gtable2:[I
   3809:	iload	17
   3811:	iaload
   3812:	istore	17
   3814:	iload	29
   3816:	iload	17
   3818:	ixor
   3819:	istore	17
   3821:	iload	16
   3823:	sipush	255
   3826:	iand
   3827:	istore	16
   3829:	getstatic	#6; //Field gtable3:[I
   3832:	iload	16
   3834:	iaload
   3835:	istore	16
   3837:	iload	17
   3839:	iload	16
   3841:	ixor
   3842:	istore	16
   3844:	iload	25
   3846:	iload	24
   3848:	ixor
   3849:	istore	25
   3851:	iload	16
   3853:	iload	25
   3855:	ixor
   3856:	istore	16
   3858:	iload	16
   3860:	iconst_0
   3861:	ishr
   3862:	istore	17
   3864:	iload	16
   3866:	bipush	8
   3868:	ishr
   3869:	istore	29
   3871:	iload	16
   3873:	bipush	16
   3875:	ishr
   3876:	istore	27
   3878:	iload	16
   3880:	bipush	24
   3882:	ishr
   3883:	istore	16
   3885:	iload	20
   3887:	sipush	255
   3890:	iand
   3891:	istore	20
   3893:	getstatic	#3; //Field gtable0:[I
   3896:	iload	20
   3898:	iaload
   3899:	istore	20
   3901:	iload	22
   3903:	sipush	255
   3906:	iand
   3907:	istore	22
   3909:	getstatic	#4; //Field gtable1:[I
   3912:	iload	22
   3914:	iaload
   3915:	istore	22
   3917:	iload	20
   3919:	iload	22
   3921:	ixor
   3922:	istore	22
   3924:	iload	18
   3926:	sipush	255
   3929:	iand
   3930:	istore	18
   3932:	getstatic	#5; //Field gtable2:[I
   3935:	iload	18
   3937:	iaload
   3938:	istore	18
   3940:	iload	22
   3942:	iload	18
   3944:	ixor
   3945:	istore	18
   3947:	iload	12
   3949:	sipush	255
   3952:	iand
   3953:	istore	12
   3955:	getstatic	#6; //Field gtable3:[I
   3958:	iload	12
   3960:	iaload
   3961:	istore	12
   3963:	iload	18
   3965:	iload	12
   3967:	ixor
   3968:	istore	12
   3970:	iload	21
   3972:	iload	25
   3974:	ixor
   3975:	istore	21
   3977:	iload	12
   3979:	iload	21
   3981:	ixor
   3982:	istore	12
   3984:	iload	12
   3986:	iconst_0
   3987:	ishr
   3988:	istore	18
   3990:	iload	12
   3992:	bipush	8
   3994:	ishr
   3995:	istore	22
   3997:	iload	12
   3999:	bipush	16
   4001:	ishr
   4002:	istore	20
   4004:	iload	12
   4006:	bipush	24
   4008:	ishr
   4009:	istore	12
   4011:	iload	19
   4013:	sipush	255
   4016:	iand
   4017:	istore	19
   4019:	getstatic	#3; //Field gtable0:[I
   4022:	iload	19
   4024:	iaload
   4025:	istore	19
   4027:	iload	23
   4029:	sipush	255
   4032:	iand
   4033:	istore	23
   4035:	getstatic	#4; //Field gtable1:[I
   4038:	iload	23
   4040:	iaload
   4041:	istore	23
   4043:	iload	19
   4045:	iload	23
   4047:	ixor
   4048:	istore	23
   4050:	iload	26
   4052:	sipush	255
   4055:	iand
   4056:	istore	26
   4058:	getstatic	#5; //Field gtable2:[I
   4061:	iload	26
   4063:	iaload
   4064:	istore	26
   4066:	iload	23
   4068:	iload	26
   4070:	ixor
   4071:	istore	26
   4073:	iload	8
   4075:	sipush	255
   4078:	iand
   4079:	istore	8
   4081:	getstatic	#6; //Field gtable3:[I
   4084:	iload	8
   4086:	iaload
   4087:	istore	8
   4089:	iload	26
   4091:	iload	8
   4093:	ixor
   4094:	istore	8
   4096:	iload	15
   4098:	iload	21
   4100:	ixor
   4101:	istore	15
   4103:	iload	8
   4105:	iload	15
   4107:	ixor
   4108:	istore	8
   4110:	iload	8
   4112:	iconst_0
   4113:	ishr
   4114:	istore	26
   4116:	iload	8
   4118:	bipush	8
   4120:	ishr
   4121:	istore	23
   4123:	iload	8
   4125:	bipush	16
   4127:	ishr
   4128:	istore	19
   4130:	iload	8
   4132:	bipush	24
   4134:	ishr
   4135:	istore	8
   4137:	iload	6
   4139:	sipush	255
   4142:	iand
   4143:	istore	6
   4145:	getstatic	#3; //Field gtable0:[I
   4148:	iload	6
   4150:	iaload
   4151:	istore	6
   4153:	iload	29
   4155:	sipush	255
   4158:	iand
   4159:	istore	29
   4161:	getstatic	#4; //Field gtable1:[I
   4164:	iload	29
   4166:	iaload
   4167:	istore	29
   4169:	iload	6
   4171:	iload	29
   4173:	ixor
   4174:	istore	29
   4176:	iload	20
   4178:	sipush	255
   4181:	iand
   4182:	istore	20
   4184:	getstatic	#5; //Field gtable2:[I
   4187:	iload	20
   4189:	iaload
   4190:	istore	20
   4192:	iload	29
   4194:	iload	20
   4196:	ixor
   4197:	istore	20
   4199:	iload	8
   4201:	sipush	255
   4204:	iand
   4205:	istore	8
   4207:	getstatic	#6; //Field gtable3:[I
   4210:	iload	8
   4212:	iaload
   4213:	istore	8
   4215:	iload	20
   4217:	iload	8
   4219:	ixor
   4220:	istore	8
   4222:	iload	15
   4224:	bipush	24
   4226:	ishl
   4227:	iload	15
   4229:	bipush	8
   4231:	iushr
   4232:	ior
   4233:	istore	20
   4235:	iload	20
   4237:	iconst_0
   4238:	ishr
   4239:	istore	29
   4241:	iload	20
   4243:	bipush	8
   4245:	ishr
   4246:	istore	6
   4248:	iload	20
   4250:	bipush	16
   4252:	ishr
   4253:	istore	31
   4255:	iload	20
   4257:	bipush	24
   4259:	ishr
   4260:	istore	20
   4262:	iload	29
   4264:	sipush	255
   4267:	iand
   4268:	istore	29
   4270:	getstatic	#7; //Field gtable4:[I
   4273:	iload	29
   4275:	iaload
   4276:	istore	29
   4278:	iload	6
   4280:	sipush	255
   4283:	iand
   4284:	istore	6
   4286:	getstatic	#7; //Field gtable4:[I
   4289:	iload	6
   4291:	iaload
   4292:	istore	6
   4294:	iload	29
   4296:	sipush	255
   4299:	iand
   4300:	istore	29
   4302:	iload	6
   4304:	bipush	8
   4306:	ishl
   4307:	iload	29
   4309:	ior
   4310:	istore	6
   4312:	iload	31
   4314:	sipush	255
   4317:	iand
   4318:	istore	31
   4320:	getstatic	#7; //Field gtable4:[I
   4323:	iload	31
   4325:	iaload
   4326:	istore	31
   4328:	iload	20
   4330:	sipush	255
   4333:	iand
   4334:	istore	20
   4336:	getstatic	#7; //Field gtable4:[I
   4339:	iload	20
   4341:	iaload
   4342:	istore	20
   4344:	iload	31
   4346:	sipush	255
   4349:	iand
   4350:	istore	31
   4352:	iload	20
   4354:	bipush	8
   4356:	ishl
   4357:	iload	31
   4359:	ior
   4360:	istore	20
   4362:	iload	6
   4364:	ldc	#2; //int 65535
   4366:	iand
   4367:	istore	6
   4369:	iload	20
   4371:	bipush	16
   4373:	ishl
   4374:	iload	6
   4376:	ior
   4377:	istore	20
   4379:	iload	20
   4381:	bipush	32
   4383:	ixor
   4384:	istore	20
   4386:	iload	24
   4388:	iload	20
   4390:	ixor
   4391:	istore	20
   4393:	iload	8
   4395:	iload	20
   4397:	ixor
   4398:	istore	8
   4400:	iload	8
   4402:	iconst_0
   4403:	ishr
   4404:	istore	24
   4406:	iload	8
   4408:	bipush	8
   4410:	ishr
   4411:	istore	6
   4413:	iload	8
   4415:	bipush	16
   4417:	ishr
   4418:	istore	31
   4420:	iload	8
   4422:	bipush	24
   4424:	ishr
   4425:	istore	8
   4427:	iload	17
   4429:	sipush	255
   4432:	iand
   4433:	istore	17
   4435:	getstatic	#3; //Field gtable0:[I
   4438:	iload	17
   4440:	iaload
   4441:	istore	17
   4443:	iload	22
   4445:	sipush	255
   4448:	iand
   4449:	istore	22
   4451:	getstatic	#4; //Field gtable1:[I
   4454:	iload	22
   4456:	iaload
   4457:	istore	22
   4459:	iload	17
   4461:	iload	22
   4463:	ixor
   4464:	istore	22
   4466:	iload	19
   4468:	sipush	255
   4471:	iand
   4472:	istore	19
   4474:	getstatic	#5; //Field gtable2:[I
   4477:	iload	19
   4479:	iaload
   4480:	istore	19
   4482:	iload	22
   4484:	iload	19
   4486:	ixor
   4487:	istore	19
   4489:	iload	4
   4491:	sipush	255
   4494:	iand
   4495:	istore	4
   4497:	getstatic	#6; //Field gtable3:[I
   4500:	iload	4
   4502:	iaload
   4503:	istore	4
   4505:	iload	19
   4507:	iload	4
   4509:	ixor
   4510:	istore	4
   4512:	iload	25
   4514:	iload	20
   4516:	ixor
   4517:	istore	25
   4519:	iload	4
   4521:	iload	25
   4523:	ixor
   4524:	istore	4
   4526:	iload	4
   4528:	iconst_0
   4529:	ishr
   4530:	istore	19
   4532:	iload	4
   4534:	bipush	8
   4536:	ishr
   4537:	istore	22
   4539:	iload	4
   4541:	bipush	16
   4543:	ishr
   4544:	istore	17
   4546:	iload	4
   4548:	bipush	24
   4550:	ishr
   4551:	istore	4
   4553:	iload	18
   4555:	sipush	255
   4558:	iand
   4559:	istore	18
   4561:	getstatic	#3; //Field gtable0:[I
   4564:	iload	18
   4566:	iaload
   4567:	istore	18
   4569:	iload	23
   4571:	sipush	255
   4574:	iand
   4575:	istore	23
   4577:	getstatic	#4; //Field gtable1:[I
   4580:	iload	23
   4582:	iaload
   4583:	istore	23
   4585:	iload	18
   4587:	iload	23
   4589:	ixor
   4590:	istore	23
   4592:	iload	28
   4594:	sipush	255
   4597:	iand
   4598:	istore	28
   4600:	getstatic	#5; //Field gtable2:[I
   4603:	iload	28
   4605:	iaload
   4606:	istore	28
   4608:	iload	23
   4610:	iload	28
   4612:	ixor
   4613:	istore	28
   4615:	iload	16
   4617:	sipush	255
   4620:	iand
   4621:	istore	16
   4623:	getstatic	#6; //Field gtable3:[I
   4626:	iload	16
   4628:	iaload
   4629:	istore	16
   4631:	iload	28
   4633:	iload	16
   4635:	ixor
   4636:	istore	16
   4638:	iload	21
   4640:	iload	25
   4642:	ixor
   4643:	istore	21
   4645:	iload	16
   4647:	iload	21
   4649:	ixor
   4650:	istore	16
   4652:	iload	16
   4654:	iconst_0
   4655:	ishr
   4656:	istore	28
   4658:	iload	16
   4660:	bipush	8
   4662:	ishr
   4663:	istore	23
   4665:	iload	16
   4667:	bipush	16
   4669:	ishr
   4670:	istore	18
   4672:	iload	16
   4674:	bipush	24
   4676:	ishr
   4677:	istore	16
   4679:	iload	26
   4681:	sipush	255
   4684:	iand
   4685:	istore	26
   4687:	getstatic	#3; //Field gtable0:[I
   4690:	iload	26
   4692:	iaload
   4693:	istore	26
   4695:	iload	30
   4697:	sipush	255
   4700:	iand
   4701:	istore	30
   4703:	getstatic	#4; //Field gtable1:[I
   4706:	iload	30
   4708:	iaload
   4709:	istore	30
   4711:	iload	26
   4713:	iload	30
   4715:	ixor
   4716:	istore	30
   4718:	iload	27
   4720:	sipush	255
   4723:	iand
   4724:	istore	27
   4726:	getstatic	#5; //Field gtable2:[I
   4729:	iload	27
   4731:	iaload
   4732:	istore	27
   4734:	iload	30
   4736:	iload	27
   4738:	ixor
   4739:	istore	27
   4741:	iload	12
   4743:	sipush	255
   4746:	iand
   4747:	istore	12
   4749:	getstatic	#6; //Field gtable3:[I
   4752:	iload	12
   4754:	iaload
   4755:	istore	12
   4757:	iload	27
   4759:	iload	12
   4761:	ixor
   4762:	istore	12
   4764:	iload	15
   4766:	iload	21
   4768:	ixor
   4769:	istore	15
   4771:	iload	12
   4773:	iload	15
   4775:	ixor
   4776:	istore	12
   4778:	iload	12
   4780:	iconst_0
   4781:	ishr
   4782:	istore	27
   4784:	iload	12
   4786:	bipush	8
   4788:	ishr
   4789:	istore	30
   4791:	iload	12
   4793:	bipush	16
   4795:	ishr
   4796:	istore	26
   4798:	iload	12
   4800:	bipush	24
   4802:	ishr
   4803:	istore	12
   4805:	iload	24
   4807:	sipush	255
   4810:	iand
   4811:	istore	24
   4813:	getstatic	#3; //Field gtable0:[I
   4816:	iload	24
   4818:	iaload
   4819:	istore	24
   4821:	iload	22
   4823:	sipush	255
   4826:	iand
   4827:	istore	22
   4829:	getstatic	#4; //Field gtable1:[I
   4832:	iload	22
   4834:	iaload
   4835:	istore	22
   4837:	iload	24
   4839:	iload	22
   4841:	ixor
   4842:	istore	22
   4844:	iload	18
   4846:	sipush	255
   4849:	iand
   4850:	istore	18
   4852:	getstatic	#5; //Field gtable2:[I
   4855:	iload	18
   4857:	iaload
   4858:	istore	18
   4860:	iload	22
   4862:	iload	18
   4864:	ixor
   4865:	istore	18
   4867:	iload	12
   4869:	sipush	255
   4872:	iand
   4873:	istore	12
   4875:	getstatic	#6; //Field gtable3:[I
   4878:	iload	12
   4880:	iaload
   4881:	istore	12
   4883:	iload	18
   4885:	iload	12
   4887:	ixor
   4888:	istore	12
   4890:	iload	15
   4892:	bipush	24
   4894:	ishl
   4895:	iload	15
   4897:	bipush	8
   4899:	iushr
   4900:	ior
   4901:	istore	18
   4903:	iload	18
   4905:	iconst_0
   4906:	ishr
   4907:	istore	22
   4909:	iload	18
   4911:	bipush	8
   4913:	ishr
   4914:	istore	24
   4916:	iload	18
   4918:	bipush	16
   4920:	ishr
   4921:	istore	29
   4923:	iload	18
   4925:	bipush	24
   4927:	ishr
   4928:	istore	18
   4930:	iload	22
   4932:	sipush	255
   4935:	iand
   4936:	istore	22
   4938:	getstatic	#7; //Field gtable4:[I
   4941:	iload	22
   4943:	iaload
   4944:	istore	22
   4946:	iload	24
   4948:	sipush	255
   4951:	iand
   4952:	istore	24
   4954:	getstatic	#7; //Field gtable4:[I
   4957:	iload	24
   4959:	iaload
   4960:	istore	24
   4962:	iload	22
   4964:	sipush	255
   4967:	iand
   4968:	istore	22
   4970:	iload	24
   4972:	bipush	8
   4974:	ishl
   4975:	iload	22
   4977:	ior
   4978:	istore	24
   4980:	iload	29
   4982:	sipush	255
   4985:	iand
   4986:	istore	29
   4988:	getstatic	#7; //Field gtable4:[I
   4991:	iload	29
   4993:	iaload
   4994:	istore	29
   4996:	iload	18
   4998:	sipush	255
   5001:	iand
   5002:	istore	18
   5004:	getstatic	#7; //Field gtable4:[I
   5007:	iload	18
   5009:	iaload
   5010:	istore	18
   5012:	iload	29
   5014:	sipush	255
   5017:	iand
   5018:	istore	29
   5020:	iload	18
   5022:	bipush	8
   5024:	ishl
   5025:	iload	29
   5027:	ior
   5028:	istore	18
   5030:	iload	24
   5032:	ldc	#2; //int 65535
   5034:	iand
   5035:	istore	24
   5037:	iload	18
   5039:	bipush	16
   5041:	ishl
   5042:	iload	24
   5044:	ior
   5045:	istore	18
   5047:	iload	18
   5049:	bipush	64
   5051:	ixor
   5052:	istore	18
   5054:	iload	20
   5056:	iload	18
   5058:	ixor
   5059:	istore	18
   5061:	iload	12
   5063:	iload	18
   5065:	ixor
   5066:	istore	12
   5068:	iload	12
   5070:	iconst_0
   5071:	ishr
   5072:	istore	20
   5074:	iload	12
   5076:	bipush	8
   5078:	ishr
   5079:	istore	24
   5081:	iload	12
   5083:	bipush	16
   5085:	ishr
   5086:	istore	29
   5088:	iload	12
   5090:	bipush	24
   5092:	ishr
   5093:	istore	12
   5095:	iload	19
   5097:	sipush	255
   5100:	iand
   5101:	istore	19
   5103:	getstatic	#3; //Field gtable0:[I
   5106:	iload	19
   5108:	iaload
   5109:	istore	19
   5111:	iload	23
   5113:	sipush	255
   5116:	iand
   5117:	istore	23
   5119:	getstatic	#4; //Field gtable1:[I
   5122:	iload	23
   5124:	iaload
   5125:	istore	23
   5127:	iload	19
   5129:	iload	23
   5131:	ixor
   5132:	istore	23
   5134:	iload	26
   5136:	sipush	255
   5139:	iand
   5140:	istore	26
   5142:	getstatic	#5; //Field gtable2:[I
   5145:	iload	26
   5147:	iaload
   5148:	istore	26
   5150:	iload	23
   5152:	iload	26
   5154:	ixor
   5155:	istore	26
   5157:	iload	8
   5159:	sipush	255
   5162:	iand
   5163:	istore	8
   5165:	getstatic	#6; //Field gtable3:[I
   5168:	iload	8
   5170:	iaload
   5171:	istore	8
   5173:	iload	26
   5175:	iload	8
   5177:	ixor
   5178:	istore	8
   5180:	iload	25
   5182:	iload	18
   5184:	ixor
   5185:	istore	25
   5187:	iload	8
   5189:	iload	25
   5191:	ixor
   5192:	istore	8
   5194:	iload	8
   5196:	iconst_0
   5197:	ishr
   5198:	istore	26
   5200:	iload	8
   5202:	bipush	8
   5204:	ishr
   5205:	istore	23
   5207:	iload	8
   5209:	bipush	16
   5211:	ishr
   5212:	istore	19
   5214:	iload	8
   5216:	bipush	24
   5218:	ishr
   5219:	istore	8
   5221:	iload	28
   5223:	sipush	255
   5226:	iand
   5227:	istore	28
   5229:	getstatic	#3; //Field gtable0:[I
   5232:	iload	28
   5234:	iaload
   5235:	istore	28
   5237:	iload	30
   5239:	sipush	255
   5242:	iand
   5243:	istore	30
   5245:	getstatic	#4; //Field gtable1:[I
   5248:	iload	30
   5250:	iaload
   5251:	istore	30
   5253:	iload	28
   5255:	iload	30
   5257:	ixor
   5258:	istore	30
   5260:	iload	31
   5262:	sipush	255
   5265:	iand
   5266:	istore	31
   5268:	getstatic	#5; //Field gtable2:[I
   5271:	iload	31
   5273:	iaload
   5274:	istore	31
   5276:	iload	30
   5278:	iload	31
   5280:	ixor
   5281:	istore	31
   5283:	iload	4
   5285:	sipush	255
   5288:	iand
   5289:	istore	4
   5291:	getstatic	#6; //Field gtable3:[I
   5294:	iload	4
   5296:	iaload
   5297:	istore	4
   5299:	iload	31
   5301:	iload	4
   5303:	ixor
   5304:	istore	4
   5306:	iload	21
   5308:	iload	25
   5310:	ixor
   5311:	istore	21
   5313:	iload	4
   5315:	iload	21
   5317:	ixor
   5318:	istore	4
   5320:	iload	4
   5322:	iconst_0
   5323:	ishr
   5324:	istore	31
   5326:	iload	4
   5328:	bipush	8
   5330:	ishr
   5331:	istore	30
   5333:	iload	4
   5335:	bipush	16
   5337:	ishr
   5338:	istore	28
   5340:	iload	4
   5342:	bipush	24
   5344:	ishr
   5345:	istore	4
   5347:	iload	27
   5349:	sipush	255
   5352:	iand
   5353:	istore	27
   5355:	getstatic	#3; //Field gtable0:[I
   5358:	iload	27
   5360:	iaload
   5361:	istore	27
   5363:	iload	6
   5365:	sipush	255
   5368:	iand
   5369:	istore	6
   5371:	getstatic	#4; //Field gtable1:[I
   5374:	iload	6
   5376:	iaload
   5377:	istore	6
   5379:	iload	27
   5381:	iload	6
   5383:	ixor
   5384:	istore	6
   5386:	iload	17
   5388:	sipush	255
   5391:	iand
   5392:	istore	17
   5394:	getstatic	#5; //Field gtable2:[I
   5397:	iload	17
   5399:	iaload
   5400:	istore	17
   5402:	iload	6
   5404:	iload	17
   5406:	ixor
   5407:	istore	17
   5409:	iload	16
   5411:	sipush	255
   5414:	iand
   5415:	istore	16
   5417:	getstatic	#6; //Field gtable3:[I
   5420:	iload	16
   5422:	iaload
   5423:	istore	16
   5425:	iload	17
   5427:	iload	16
   5429:	ixor
   5430:	istore	16
   5432:	iload	15
   5434:	iload	21
   5436:	ixor
   5437:	istore	15
   5439:	iload	16
   5441:	iload	15
   5443:	ixor
   5444:	istore	16
   5446:	iload	16
   5448:	iconst_0
   5449:	ishr
   5450:	istore	17
   5452:	iload	16
   5454:	bipush	8
   5456:	ishr
   5457:	istore	6
   5459:	iload	16
   5461:	bipush	16
   5463:	ishr
   5464:	istore	27
   5466:	iload	16
   5468:	bipush	24
   5470:	ishr
   5471:	istore	16
   5473:	iload	20
   5475:	sipush	255
   5478:	iand
   5479:	istore	20
   5481:	getstatic	#3; //Field gtable0:[I
   5484:	iload	20
   5486:	iaload
   5487:	istore	20
   5489:	iload	23
   5491:	sipush	255
   5494:	iand
   5495:	istore	23
   5497:	getstatic	#4; //Field gtable1:[I
   5500:	iload	23
   5502:	iaload
   5503:	istore	23
   5505:	iload	20
   5507:	iload	23
   5509:	ixor
   5510:	istore	23
   5512:	iload	28
   5514:	sipush	255
   5517:	iand
   5518:	istore	28
   5520:	getstatic	#5; //Field gtable2:[I
   5523:	iload	28
   5525:	iaload
   5526:	istore	28
   5528:	iload	23
   5530:	iload	28
   5532:	ixor
   5533:	istore	28
   5535:	iload	16
   5537:	sipush	255
   5540:	iand
   5541:	istore	16
   5543:	getstatic	#6; //Field gtable3:[I
   5546:	iload	16
   5548:	iaload
   5549:	istore	16
   5551:	iload	28
   5553:	iload	16
   5555:	ixor
   5556:	istore	16
   5558:	iload	15
   5560:	bipush	24
   5562:	ishl
   5563:	iload	15
   5565:	bipush	8
   5567:	iushr
   5568:	ior
   5569:	istore	28
   5571:	iload	28
   5573:	iconst_0
   5574:	ishr
   5575:	istore	23
   5577:	iload	28
   5579:	bipush	8
   5581:	ishr
   5582:	istore	20
   5584:	iload	28
   5586:	bipush	16
   5588:	ishr
   5589:	istore	22
   5591:	iload	28
   5593:	bipush	24
   5595:	ishr
   5596:	istore	28
   5598:	iload	23
   5600:	sipush	255
   5603:	iand
   5604:	istore	23
   5606:	getstatic	#7; //Field gtable4:[I
   5609:	iload	23
   5611:	iaload
   5612:	istore	23
   5614:	iload	20
   5616:	sipush	255
   5619:	iand
   5620:	istore	20
   5622:	getstatic	#7; //Field gtable4:[I
   5625:	iload	20
   5627:	iaload
   5628:	istore	20
   5630:	iload	23
   5632:	sipush	255
   5635:	iand
   5636:	istore	23
   5638:	iload	20
   5640:	bipush	8
   5642:	ishl
   5643:	iload	23
   5645:	ior
   5646:	istore	20
   5648:	iload	22
   5650:	sipush	255
   5653:	iand
   5654:	istore	22
   5656:	getstatic	#7; //Field gtable4:[I
   5659:	iload	22
   5661:	iaload
   5662:	istore	22
   5664:	iload	28
   5666:	sipush	255
   5669:	iand
   5670:	istore	28
   5672:	getstatic	#7; //Field gtable4:[I
   5675:	iload	28
   5677:	iaload
   5678:	istore	28
   5680:	iload	22
   5682:	sipush	255
   5685:	iand
   5686:	istore	22
   5688:	iload	28
   5690:	bipush	8
   5692:	ishl
   5693:	iload	22
   5695:	ior
   5696:	istore	28
   5698:	iload	20
   5700:	ldc	#2; //int 65535
   5702:	iand
   5703:	istore	20
   5705:	iload	28
   5707:	bipush	16
   5709:	ishl
   5710:	iload	20
   5712:	ior
   5713:	istore	28
   5715:	iload	28
   5717:	sipush	128
   5720:	ixor
   5721:	istore	28
   5723:	iload	18
   5725:	iload	28
   5727:	ixor
   5728:	istore	28
   5730:	iload	16
   5732:	iload	28
   5734:	ixor
   5735:	istore	16
   5737:	iload	16
   5739:	iconst_0
   5740:	ishr
   5741:	istore	18
   5743:	iload	16
   5745:	bipush	8
   5747:	ishr
   5748:	istore	20
   5750:	iload	16
   5752:	bipush	16
   5754:	ishr
   5755:	istore	22
   5757:	iload	16
   5759:	bipush	24
   5761:	ishr
   5762:	istore	16
   5764:	iload	26
   5766:	sipush	255
   5769:	iand
   5770:	istore	26
   5772:	getstatic	#3; //Field gtable0:[I
   5775:	iload	26
   5777:	iaload
   5778:	istore	26
   5780:	iload	30
   5782:	sipush	255
   5785:	iand
   5786:	istore	30
   5788:	getstatic	#4; //Field gtable1:[I
   5791:	iload	30
   5793:	iaload
   5794:	istore	30
   5796:	iload	26
   5798:	iload	30
   5800:	ixor
   5801:	istore	30
   5803:	iload	27
   5805:	sipush	255
   5808:	iand
   5809:	istore	27
   5811:	getstatic	#5; //Field gtable2:[I
   5814:	iload	27
   5816:	iaload
   5817:	istore	27
   5819:	iload	30
   5821:	iload	27
   5823:	ixor
   5824:	istore	27
   5826:	iload	12
   5828:	sipush	255
   5831:	iand
   5832:	istore	12
   5834:	getstatic	#6; //Field gtable3:[I
   5837:	iload	12
   5839:	iaload
   5840:	istore	12
   5842:	iload	27
   5844:	iload	12
   5846:	ixor
   5847:	istore	12
   5849:	iload	25
   5851:	iload	28
   5853:	ixor
   5854:	istore	25
   5856:	iload	12
   5858:	iload	25
   5860:	ixor
   5861:	istore	12
   5863:	iload	12
   5865:	iconst_0
   5866:	ishr
   5867:	istore	27
   5869:	iload	12
   5871:	bipush	8
   5873:	ishr
   5874:	istore	30
   5876:	iload	12
   5878:	bipush	16
   5880:	ishr
   5881:	istore	26
   5883:	iload	12
   5885:	bipush	24
   5887:	ishr
   5888:	istore	12
   5890:	iload	31
   5892:	sipush	255
   5895:	iand
   5896:	istore	31
   5898:	getstatic	#3; //Field gtable0:[I
   5901:	iload	31
   5903:	iaload
   5904:	istore	31
   5906:	iload	6
   5908:	sipush	255
   5911:	iand
   5912:	istore	6
   5914:	getstatic	#4; //Field gtable1:[I
   5917:	iload	6
   5919:	iaload
   5920:	istore	6
   5922:	iload	31
   5924:	iload	6
   5926:	ixor
   5927:	istore	6
   5929:	iload	29
   5931:	sipush	255
   5934:	iand
   5935:	istore	29
   5937:	getstatic	#5; //Field gtable2:[I
   5940:	iload	29
   5942:	iaload
   5943:	istore	29
   5945:	iload	6
   5947:	iload	29
   5949:	ixor
   5950:	istore	29
   5952:	iload	8
   5954:	sipush	255
   5957:	iand
   5958:	istore	8
   5960:	getstatic	#6; //Field gtable3:[I
   5963:	iload	8
   5965:	iaload
   5966:	istore	8
   5968:	iload	29
   5970:	iload	8
   5972:	ixor
   5973:	istore	8
   5975:	iload	21
   5977:	iload	25
   5979:	ixor
   5980:	istore	21
   5982:	iload	8
   5984:	iload	21
   5986:	ixor
   5987:	istore	8
   5989:	iload	8
   5991:	iconst_0
   5992:	ishr
   5993:	istore	29
   5995:	iload	8
   5997:	bipush	8
   5999:	ishr
   6000:	istore	6
   6002:	iload	8
   6004:	bipush	16
   6006:	ishr
   6007:	istore	31
   6009:	iload	8
   6011:	bipush	24
   6013:	ishr
   6014:	istore	8
   6016:	iload	17
   6018:	sipush	255
   6021:	iand
   6022:	istore	17
   6024:	getstatic	#3; //Field gtable0:[I
   6027:	iload	17
   6029:	iaload
   6030:	istore	17
   6032:	iload	24
   6034:	sipush	255
   6037:	iand
   6038:	istore	24
   6040:	getstatic	#4; //Field gtable1:[I
   6043:	iload	24
   6045:	iaload
   6046:	istore	24
   6048:	iload	17
   6050:	iload	24
   6052:	ixor
   6053:	istore	24
   6055:	iload	19
   6057:	sipush	255
   6060:	iand
   6061:	istore	19
   6063:	getstatic	#5; //Field gtable2:[I
   6066:	iload	19
   6068:	iaload
   6069:	istore	19
   6071:	iload	24
   6073:	iload	19
   6075:	ixor
   6076:	istore	19
   6078:	iload	4
   6080:	sipush	255
   6083:	iand
   6084:	istore	4
   6086:	getstatic	#6; //Field gtable3:[I
   6089:	iload	4
   6091:	iaload
   6092:	istore	4
   6094:	iload	19
   6096:	iload	4
   6098:	ixor
   6099:	istore	4
   6101:	iload	15
   6103:	iload	21
   6105:	ixor
   6106:	istore	15
   6108:	iload	4
   6110:	iload	15
   6112:	ixor
   6113:	istore	4
   6115:	iload	4
   6117:	iconst_0
   6118:	ishr
   6119:	istore	19
   6121:	iload	4
   6123:	bipush	8
   6125:	ishr
   6126:	istore	24
   6128:	iload	4
   6130:	bipush	16
   6132:	ishr
   6133:	istore	17
   6135:	iload	4
   6137:	bipush	24
   6139:	ishr
   6140:	istore	4
   6142:	iload	18
   6144:	sipush	255
   6147:	iand
   6148:	istore	18
   6150:	getstatic	#3; //Field gtable0:[I
   6153:	iload	18
   6155:	iaload
   6156:	istore	18
   6158:	iload	30
   6160:	sipush	255
   6163:	iand
   6164:	istore	30
   6166:	getstatic	#4; //Field gtable1:[I
   6169:	iload	30
   6171:	iaload
   6172:	istore	30
   6174:	iload	18
   6176:	iload	30
   6178:	ixor
   6179:	istore	30
   6181:	iload	31
   6183:	sipush	255
   6186:	iand
   6187:	istore	31
   6189:	getstatic	#5; //Field gtable2:[I
   6192:	iload	31
   6194:	iaload
   6195:	istore	31
   6197:	iload	30
   6199:	iload	31
   6201:	ixor
   6202:	istore	31
   6204:	iload	4
   6206:	sipush	255
   6209:	iand
   6210:	istore	4
   6212:	getstatic	#6; //Field gtable3:[I
   6215:	iload	4
   6217:	iaload
   6218:	istore	4
   6220:	iload	31
   6222:	iload	4
   6224:	ixor
   6225:	istore	4
   6227:	iload	15
   6229:	bipush	24
   6231:	ishl
   6232:	iload	15
   6234:	bipush	8
   6236:	iushr
   6237:	ior
   6238:	istore	31
   6240:	iload	31
   6242:	iconst_0
   6243:	ishr
   6244:	istore	30
   6246:	iload	31
   6248:	bipush	8
   6250:	ishr
   6251:	istore	18
   6253:	iload	31
   6255:	bipush	16
   6257:	ishr
   6258:	istore	23
   6260:	iload	31
   6262:	bipush	24
   6264:	ishr
   6265:	istore	31
   6267:	iload	30
   6269:	sipush	255
   6272:	iand
   6273:	istore	30
   6275:	getstatic	#7; //Field gtable4:[I
   6278:	iload	30
   6280:	iaload
   6281:	istore	30
   6283:	iload	18
   6285:	sipush	255
   6288:	iand
   6289:	istore	18
   6291:	getstatic	#7; //Field gtable4:[I
   6294:	iload	18
   6296:	iaload
   6297:	istore	18
   6299:	iload	30
   6301:	sipush	255
   6304:	iand
   6305:	istore	30
   6307:	iload	18
   6309:	bipush	8
   6311:	ishl
   6312:	iload	30
   6314:	ior
   6315:	istore	18
   6317:	iload	23
   6319:	sipush	255
   6322:	iand
   6323:	istore	23
   6325:	getstatic	#7; //Field gtable4:[I
   6328:	iload	23
   6330:	iaload
   6331:	istore	23
   6333:	iload	31
   6335:	sipush	255
   6338:	iand
   6339:	istore	31
   6341:	getstatic	#7; //Field gtable4:[I
   6344:	iload	31
   6346:	iaload
   6347:	istore	31
   6349:	iload	23
   6351:	sipush	255
   6354:	iand
   6355:	istore	23
   6357:	iload	31
   6359:	bipush	8
   6361:	ishl
   6362:	iload	23
   6364:	ior
   6365:	istore	31
   6367:	iload	18
   6369:	ldc	#2; //int 65535
   6371:	iand
   6372:	istore	18
   6374:	iload	31
   6376:	bipush	16
   6378:	ishl
   6379:	iload	18
   6381:	ior
   6382:	istore	31
   6384:	iload	31
   6386:	bipush	27
   6388:	ixor
   6389:	istore	31
   6391:	iload	28
   6393:	iload	31
   6395:	ixor
   6396:	istore	31
   6398:	iload	4
   6400:	iload	31
   6402:	ixor
   6403:	istore	4
   6405:	iload	4
   6407:	iconst_0
   6408:	ishr
   6409:	istore	28
   6411:	iload	4
   6413:	bipush	8
   6415:	ishr
   6416:	istore	18
   6418:	iload	4
   6420:	bipush	16
   6422:	ishr
   6423:	istore	23
   6425:	iload	4
   6427:	bipush	24
   6429:	ishr
   6430:	istore	4
   6432:	iload	27
   6434:	sipush	255
   6437:	iand
   6438:	istore	27
   6440:	getstatic	#3; //Field gtable0:[I
   6443:	iload	27
   6445:	iaload
   6446:	istore	27
   6448:	iload	6
   6450:	sipush	255
   6453:	iand
   6454:	istore	6
   6456:	getstatic	#4; //Field gtable1:[I
   6459:	iload	6
   6461:	iaload
   6462:	istore	6
   6464:	iload	27
   6466:	iload	6
   6468:	ixor
   6469:	istore	6
   6471:	iload	17
   6473:	sipush	255
   6476:	iand
   6477:	istore	17
   6479:	getstatic	#5; //Field gtable2:[I
   6482:	iload	17
   6484:	iaload
   6485:	istore	17
   6487:	iload	6
   6489:	iload	17
   6491:	ixor
   6492:	istore	17
   6494:	iload	16
   6496:	sipush	255
   6499:	iand
   6500:	istore	16
   6502:	getstatic	#6; //Field gtable3:[I
   6505:	iload	16
   6507:	iaload
   6508:	istore	16
   6510:	iload	17
   6512:	iload	16
   6514:	ixor
   6515:	istore	16
   6517:	iload	25
   6519:	iload	31
   6521:	ixor
   6522:	istore	25
   6524:	iload	16
   6526:	iload	25
   6528:	ixor
   6529:	istore	16
   6531:	iload	16
   6533:	iconst_0
   6534:	ishr
   6535:	istore	17
   6537:	iload	16
   6539:	bipush	8
   6541:	ishr
   6542:	istore	6
   6544:	iload	16
   6546:	bipush	16
   6548:	ishr
   6549:	istore	27
   6551:	iload	16
   6553:	bipush	24
   6555:	ishr
   6556:	istore	16
   6558:	iload	29
   6560:	sipush	255
   6563:	iand
   6564:	istore	29
   6566:	getstatic	#3; //Field gtable0:[I
   6569:	iload	29
   6571:	iaload
   6572:	istore	29
   6574:	iload	24
   6576:	sipush	255
   6579:	iand
   6580:	istore	24
   6582:	getstatic	#4; //Field gtable1:[I
   6585:	iload	24
   6587:	iaload
   6588:	istore	24
   6590:	iload	29
   6592:	iload	24
   6594:	ixor
   6595:	istore	24
   6597:	iload	22
   6599:	sipush	255
   6602:	iand
   6603:	istore	22
   6605:	getstatic	#5; //Field gtable2:[I
   6608:	iload	22
   6610:	iaload
   6611:	istore	22
   6613:	iload	24
   6615:	iload	22
   6617:	ixor
   6618:	istore	22
   6620:	iload	12
   6622:	sipush	255
   6625:	iand
   6626:	istore	12
   6628:	getstatic	#6; //Field gtable3:[I
   6631:	iload	12
   6633:	iaload
   6634:	istore	12
   6636:	iload	22
   6638:	iload	12
   6640:	ixor
   6641:	istore	12
   6643:	iload	21
   6645:	iload	25
   6647:	ixor
   6648:	istore	21
   6650:	iload	12
   6652:	iload	21
   6654:	ixor
   6655:	istore	12
   6657:	iload	12
   6659:	iconst_0
   6660:	ishr
   6661:	istore	22
   6663:	iload	12
   6665:	bipush	8
   6667:	ishr
   6668:	istore	24
   6670:	iload	12
   6672:	bipush	16
   6674:	ishr
   6675:	istore	29
   6677:	iload	12
   6679:	bipush	24
   6681:	ishr
   6682:	istore	12
   6684:	iload	19
   6686:	sipush	255
   6689:	iand
   6690:	istore	19
   6692:	getstatic	#3; //Field gtable0:[I
   6695:	iload	19
   6697:	iaload
   6698:	istore	19
   6700:	iload	20
   6702:	sipush	255
   6705:	iand
   6706:	istore	20
   6708:	getstatic	#4; //Field gtable1:[I
   6711:	iload	20
   6713:	iaload
   6714:	istore	20
   6716:	iload	19
   6718:	iload	20
   6720:	ixor
   6721:	istore	20
   6723:	iload	26
   6725:	sipush	255
   6728:	iand
   6729:	istore	26
   6731:	getstatic	#5; //Field gtable2:[I
   6734:	iload	26
   6736:	iaload
   6737:	istore	26
   6739:	iload	20
   6741:	iload	26
   6743:	ixor
   6744:	istore	26
   6746:	iload	8
   6748:	sipush	255
   6751:	iand
   6752:	istore	8
   6754:	getstatic	#6; //Field gtable3:[I
   6757:	iload	8
   6759:	iaload
   6760:	istore	8
   6762:	iload	26
   6764:	iload	8
   6766:	ixor
   6767:	istore	8
   6769:	iload	15
   6771:	iload	21
   6773:	ixor
   6774:	istore	15
   6776:	iload	8
   6778:	iload	15
   6780:	ixor
   6781:	istore	8
   6783:	iload	8
   6785:	iconst_0
   6786:	ishr
   6787:	istore	26
   6789:	iload	8
   6791:	bipush	8
   6793:	ishr
   6794:	istore	20
   6796:	iload	8
   6798:	bipush	16
   6800:	ishr
   6801:	istore	19
   6803:	iload	8
   6805:	bipush	24
   6807:	ishr
   6808:	istore	8
   6810:	iload	28
   6812:	sipush	255
   6815:	iand
   6816:	istore	28
   6818:	getstatic	#7; //Field gtable4:[I
   6821:	iload	28
   6823:	iaload
   6824:	istore	28
   6826:	iload	28
   6828:	sipush	255
   6831:	iand
   6832:	istore	28
   6834:	iconst_0
   6835:	iload	28
   6837:	ior
   6838:	istore	28
   6840:	iload	6
   6842:	sipush	255
   6845:	iand
   6846:	istore	6
   6848:	getstatic	#7; //Field gtable4:[I
   6851:	iload	6
   6853:	iaload
   6854:	istore	6
   6856:	iload	6
   6858:	sipush	255
   6861:	iand
   6862:	istore	6
   6864:	iconst_0
   6865:	iload	6
   6867:	ior
   6868:	istore	6
   6870:	iload	6
   6872:	bipush	8
   6874:	ishl
   6875:	istore	6
   6877:	iload	28
   6879:	iload	6
   6881:	ixor
   6882:	istore	6
   6884:	iload	29
   6886:	sipush	255
   6889:	iand
   6890:	istore	29
   6892:	getstatic	#7; //Field gtable4:[I
   6895:	iload	29
   6897:	iaload
   6898:	istore	29
   6900:	iload	29
   6902:	sipush	255
   6905:	iand
   6906:	istore	29
   6908:	iconst_0
   6909:	iload	29
   6911:	ior
   6912:	istore	29
   6914:	iload	29
   6916:	bipush	16
   6918:	ishl
   6919:	istore	29
   6921:	iload	6
   6923:	iload	29
   6925:	ixor
   6926:	istore	29
   6928:	iload	8
   6930:	sipush	255
   6933:	iand
   6934:	istore	8
   6936:	getstatic	#7; //Field gtable4:[I
   6939:	iload	8
   6941:	iaload
   6942:	istore	8
   6944:	iload	8
   6946:	sipush	255
   6949:	iand
   6950:	istore	8
   6952:	iconst_0
   6953:	iload	8
   6955:	ior
   6956:	istore	8
   6958:	iload	8
   6960:	bipush	24
   6962:	ishl
   6963:	istore	8
   6965:	iload	29
   6967:	iload	8
   6969:	ixor
   6970:	istore	8
   6972:	iload	15
   6974:	bipush	24
   6976:	ishl
   6977:	iload	15
   6979:	bipush	8
   6981:	iushr
   6982:	ior
   6983:	istore	29
   6985:	iload	29
   6987:	iconst_0
   6988:	ishr
   6989:	istore	6
   6991:	iload	29
   6993:	bipush	8
   6995:	ishr
   6996:	istore	28
   6998:	iload	29
   7000:	bipush	16
   7002:	ishr
   7003:	istore	30
   7005:	iload	29
   7007:	bipush	24
   7009:	ishr
   7010:	istore	29
   7012:	iload	6
   7014:	sipush	255
   7017:	iand
   7018:	istore	6
   7020:	getstatic	#7; //Field gtable4:[I
   7023:	iload	6
   7025:	iaload
   7026:	istore	6
   7028:	iload	28
   7030:	sipush	255
   7033:	iand
   7034:	istore	28
   7036:	getstatic	#7; //Field gtable4:[I
   7039:	iload	28
   7041:	iaload
   7042:	istore	28
   7044:	iload	6
   7046:	sipush	255
   7049:	iand
   7050:	istore	6
   7052:	iload	28
   7054:	bipush	8
   7056:	ishl
   7057:	iload	6
   7059:	ior
   7060:	istore	28
   7062:	iload	30
   7064:	sipush	255
   7067:	iand
   7068:	istore	30
   7070:	getstatic	#7; //Field gtable4:[I
   7073:	iload	30
   7075:	iaload
   7076:	istore	30
   7078:	iload	29
   7080:	sipush	255
   7083:	iand
   7084:	istore	29
   7086:	getstatic	#7; //Field gtable4:[I
   7089:	iload	29
   7091:	iaload
   7092:	istore	29
   7094:	iload	30
   7096:	sipush	255
   7099:	iand
   7100:	istore	30
   7102:	iload	29
   7104:	bipush	8
   7106:	ishl
   7107:	iload	30
   7109:	ior
   7110:	istore	29
   7112:	iload	28
   7114:	ldc	#2; //int 65535
   7116:	iand
   7117:	istore	28
   7119:	iload	29
   7121:	bipush	16
   7123:	ishl
   7124:	iload	28
   7126:	ior
   7127:	istore	29
   7129:	iload	29
   7131:	bipush	54
   7133:	ixor
   7134:	istore	29
   7136:	iload	31
   7138:	iload	29
   7140:	ixor
   7141:	istore	29
   7143:	iload	8
   7145:	iload	29
   7147:	ixor
   7148:	istore	8
   7150:	iload	8
   7152:	iconst_0
   7153:	ishr
   7154:	istore	31
   7156:	iload	8
   7158:	bipush	8
   7160:	ishr
   7161:	istore	28
   7163:	iload	8
   7165:	bipush	16
   7167:	ishr
   7168:	istore	30
   7170:	iload	8
   7172:	bipush	24
   7174:	ishr
   7175:	istore	8
   7177:	iload	17
   7179:	sipush	255
   7182:	iand
   7183:	istore	17
   7185:	getstatic	#7; //Field gtable4:[I
   7188:	iload	17
   7190:	iaload
   7191:	istore	17
   7193:	iload	17
   7195:	sipush	255
   7198:	iand
   7199:	istore	17
   7201:	iconst_0
   7202:	iload	17
   7204:	ior
   7205:	istore	17
   7207:	iload	24
   7209:	sipush	255
   7212:	iand
   7213:	istore	24
   7215:	getstatic	#7; //Field gtable4:[I
   7218:	iload	24
   7220:	iaload
   7221:	istore	24
   7223:	iload	24
   7225:	sipush	255
   7228:	iand
   7229:	istore	24
   7231:	iconst_0
   7232:	iload	24
   7234:	ior
   7235:	istore	24
   7237:	iload	24
   7239:	bipush	8
   7241:	ishl
   7242:	istore	24
   7244:	iload	17
   7246:	iload	24
   7248:	ixor
   7249:	istore	24
   7251:	iload	19
   7253:	sipush	255
   7256:	iand
   7257:	istore	19
   7259:	getstatic	#7; //Field gtable4:[I
   7262:	iload	19
   7264:	iaload
   7265:	istore	19
   7267:	iload	19
   7269:	sipush	255
   7272:	iand
   7273:	istore	19
   7275:	iconst_0
   7276:	iload	19
   7278:	ior
   7279:	istore	19
   7281:	iload	19
   7283:	bipush	16
   7285:	ishl
   7286:	istore	19
   7288:	iload	24
   7290:	iload	19
   7292:	ixor
   7293:	istore	19
   7295:	iload	4
   7297:	sipush	255
   7300:	iand
   7301:	istore	4
   7303:	getstatic	#7; //Field gtable4:[I
   7306:	iload	4
   7308:	iaload
   7309:	istore	4
   7311:	iload	4
   7313:	sipush	255
   7316:	iand
   7317:	istore	4
   7319:	iconst_0
   7320:	iload	4
   7322:	ior
   7323:	istore	4
   7325:	iload	4
   7327:	bipush	24
   7329:	ishl
   7330:	istore	4
   7332:	iload	19
   7334:	iload	4
   7336:	ixor
   7337:	istore	4
   7339:	iload	25
   7341:	iload	29
   7343:	ixor
   7344:	istore	29
   7346:	iload	4
   7348:	iload	29
   7350:	ixor
   7351:	istore	4
   7353:	iload	4
   7355:	iconst_0
   7356:	ishr
   7357:	istore	25
   7359:	iload	4
   7361:	bipush	8
   7363:	ishr
   7364:	istore	19
   7366:	iload	4
   7368:	bipush	16
   7370:	ishr
   7371:	istore	24
   7373:	iload	4
   7375:	bipush	24
   7377:	ishr
   7378:	istore	4
   7380:	iload	22
   7382:	sipush	255
   7385:	iand
   7386:	istore	22
   7388:	getstatic	#7; //Field gtable4:[I
   7391:	iload	22
   7393:	iaload
   7394:	istore	22
   7396:	iload	22
   7398:	sipush	255
   7401:	iand
   7402:	istore	22
   7404:	iconst_0
   7405:	iload	22
   7407:	ior
   7408:	istore	22
   7410:	iload	20
   7412:	sipush	255
   7415:	iand
   7416:	istore	20
   7418:	getstatic	#7; //Field gtable4:[I
   7421:	iload	20
   7423:	iaload
   7424:	istore	20
   7426:	iload	20
   7428:	sipush	255
   7431:	iand
   7432:	istore	20
   7434:	iconst_0
   7435:	iload	20
   7437:	ior
   7438:	istore	20
   7440:	iload	20
   7442:	bipush	8
   7444:	ishl
   7445:	istore	20
   7447:	iload	22
   7449:	iload	20
   7451:	ixor
   7452:	istore	20
   7454:	iload	23
   7456:	sipush	255
   7459:	iand
   7460:	istore	23
   7462:	getstatic	#7; //Field gtable4:[I
   7465:	iload	23
   7467:	iaload
   7468:	istore	23
   7470:	iload	23
   7472:	sipush	255
   7475:	iand
   7476:	istore	23
   7478:	iconst_0
   7479:	iload	23
   7481:	ior
   7482:	istore	23
   7484:	iload	23
   7486:	bipush	16
   7488:	ishl
   7489:	istore	23
   7491:	iload	20
   7493:	iload	23
   7495:	ixor
   7496:	istore	23
   7498:	iload	16
   7500:	sipush	255
   7503:	iand
   7504:	istore	16
   7506:	getstatic	#7; //Field gtable4:[I
   7509:	iload	16
   7511:	iaload
   7512:	istore	16
   7514:	iload	16
   7516:	sipush	255
   7519:	iand
   7520:	istore	16
   7522:	iconst_0
   7523:	iload	16
   7525:	ior
   7526:	istore	16
   7528:	iload	16
   7530:	bipush	24
   7532:	ishl
   7533:	istore	16
   7535:	iload	23
   7537:	iload	16
   7539:	ixor
   7540:	istore	16
   7542:	iload	21
   7544:	iload	29
   7546:	ixor
   7547:	istore	29
   7549:	iload	16
   7551:	iload	29
   7553:	ixor
   7554:	istore	16
   7556:	iload	16
   7558:	iconst_0
   7559:	ishr
   7560:	istore	21
   7562:	iload	16
   7564:	bipush	8
   7566:	ishr
   7567:	istore	23
   7569:	iload	16
   7571:	bipush	16
   7573:	ishr
   7574:	istore	20
   7576:	iload	16
   7578:	bipush	24
   7580:	ishr
   7581:	istore	16
   7583:	iload	26
   7585:	sipush	255
   7588:	iand
   7589:	istore	26
   7591:	getstatic	#7; //Field gtable4:[I
   7594:	iload	26
   7596:	iaload
   7597:	istore	26
   7599:	iload	26
   7601:	sipush	255
   7604:	iand
   7605:	istore	26
   7607:	iconst_0
   7608:	iload	26
   7610:	ior
   7611:	istore	26
   7613:	iload	18
   7615:	sipush	255
   7618:	iand
   7619:	istore	18
   7621:	getstatic	#7; //Field gtable4:[I
   7624:	iload	18
   7626:	iaload
   7627:	istore	18
   7629:	iload	18
   7631:	sipush	255
   7634:	iand
   7635:	istore	18
   7637:	iconst_0
   7638:	iload	18
   7640:	ior
   7641:	istore	18
   7643:	iload	18
   7645:	bipush	8
   7647:	ishl
   7648:	istore	18
   7650:	iload	26
   7652:	iload	18
   7654:	ixor
   7655:	istore	18
   7657:	iload	27
   7659:	sipush	255
   7662:	iand
   7663:	istore	27
   7665:	getstatic	#7; //Field gtable4:[I
   7668:	iload	27
   7670:	iaload
   7671:	istore	27
   7673:	iload	27
   7675:	sipush	255
   7678:	iand
   7679:	istore	27
   7681:	iconst_0
   7682:	iload	27
   7684:	ior
   7685:	istore	27
   7687:	iload	27
   7689:	bipush	16
   7691:	ishl
   7692:	istore	27
   7694:	iload	18
   7696:	iload	27
   7698:	ixor
   7699:	istore	27
   7701:	iload	12
   7703:	sipush	255
   7706:	iand
   7707:	istore	12
   7709:	getstatic	#7; //Field gtable4:[I
   7712:	iload	12
   7714:	iaload
   7715:	istore	12
   7717:	iload	12
   7719:	sipush	255
   7722:	iand
   7723:	istore	12
   7725:	iconst_0
   7726:	iload	12
   7728:	ior
   7729:	istore	12
   7731:	iload	12
   7733:	bipush	24
   7735:	ishl
   7736:	istore	12
   7738:	iload	27
   7740:	iload	12
   7742:	ixor
   7743:	istore	12
   7745:	iload	15
   7747:	iload	29
   7749:	ixor
   7750:	istore	29
   7752:	iload	12
   7754:	iload	29
   7756:	ixor
   7757:	istore	29
   7759:	iload	29
   7761:	iconst_0
   7762:	ishr
   7763:	istore	12
   7765:	iload	29
   7767:	bipush	8
   7769:	ishr
   7770:	istore	15
   7772:	iload	29
   7774:	bipush	16
   7776:	ishr
   7777:	istore	27
   7779:	iload	29
   7781:	bipush	24
   7783:	ishr
   7784:	istore	29
   7786:	iload	29
   7788:	sipush	255
   7791:	iand
   7792:	istore	29
   7794:	iload	27
   7796:	bipush	8
   7798:	ishl
   7799:	iload	29
   7801:	ior
   7802:	istore	29
   7804:	iload	15
   7806:	sipush	255
   7809:	iand
   7810:	istore	15
   7812:	iload	12
   7814:	bipush	8
   7816:	ishl
   7817:	iload	15
   7819:	ior
   7820:	istore	15
   7822:	iload	29
   7824:	ldc	#2; //int 65535
   7826:	iand
   7827:	istore	29
   7829:	iload	15
   7831:	bipush	16
   7833:	ishl
   7834:	iload	29
   7836:	ior
   7837:	istore	15
   7839:	iload	16
   7841:	sipush	255
   7844:	iand
   7845:	istore	16
   7847:	iload	20
   7849:	bipush	8
   7851:	ishl
   7852:	iload	16
   7854:	ior
   7855:	istore	16
   7857:	iload	23
   7859:	sipush	255
   7862:	iand
   7863:	istore	23
   7865:	iload	21
   7867:	bipush	8
   7869:	ishl
   7870:	iload	23
   7872:	ior
   7873:	istore	23
   7875:	iload	16
   7877:	ldc	#2; //int 65535
   7879:	iand
   7880:	istore	16
   7882:	iload	23
   7884:	bipush	16
   7886:	ishl
   7887:	iload	16
   7889:	ior
   7890:	istore	23
   7892:	aload	32
   7894:	iconst_0
   7895:	iload	15
   7897:	iastore
   7898:	aload	32
   7900:	iconst_1
   7901:	iload	23
   7903:	iastore
   7904:	iload	4
   7906:	sipush	255
   7909:	iand
   7910:	istore	4
   7912:	iload	24
   7914:	bipush	8
   7916:	ishl
   7917:	iload	4
   7919:	ior
   7920:	istore	4
   7922:	iload	19
   7924:	sipush	255
   7927:	iand
   7928:	istore	19
   7930:	iload	25
   7932:	bipush	8
   7934:	ishl
   7935:	iload	19
   7937:	ior
   7938:	istore	19
   7940:	iload	4
   7942:	ldc	#2; //int 65535
   7944:	iand
   7945:	istore	4
   7947:	iload	19
   7949:	bipush	16
   7951:	ishl
   7952:	iload	4
   7954:	ior
   7955:	istore	19
   7957:	iload	8
   7959:	sipush	255
   7962:	iand
   7963:	istore	8
   7965:	iload	30
   7967:	bipush	8
   7969:	ishl
   7970:	iload	8
   7972:	ior
   7973:	istore	8
   7975:	iload	28
   7977:	sipush	255
   7980:	iand
   7981:	istore	28
   7983:	iload	31
   7985:	bipush	8
   7987:	ishl
   7988:	iload	28
   7990:	ior
   7991:	istore	28
   7993:	iload	8
   7995:	ldc	#2; //int 65535
   7997:	iand
   7998:	istore	8
   8000:	iload	28
   8002:	bipush	16
   8004:	ishl
   8005:	iload	8
   8007:	ior
   8008:	istore	28
   8010:	aload	33
   8012:	iconst_0
   8013:	iload	19
   8015:	iastore
   8016:	aload	33
   8018:	iconst_1
   8019:	iload	28
   8021:	iastore
   8022:	aload_2
   8023:	iconst_0
   8024:	aload	32
   8026:	iconst_0
   8027:	iaload
   8028:	iastore
   8029:	aload_2
   8030:	iconst_1
   8031:	aload	32
   8033:	iconst_1
   8034:	iaload
   8035:	iastore
   8036:	aload_2
   8037:	iconst_2
   8038:	aload	33
   8040:	iconst_0
   8041:	iaload
   8042:	iastore
   8043:	aload_2
   8044:	iconst_3
   8045:	aload	33
   8047:	iconst_1
   8048:	iaload
   8049:	iastore
   8050:	return

static {};
  Code:
   0:	sipush	256
   3:	newarray int
   5:	dup
   6:	iconst_0
   7:	bipush	99
   9:	iastore
   10:	dup
   11:	iconst_1
   12:	bipush	124
   14:	iastore
   15:	dup
   16:	iconst_2
   17:	bipush	119
   19:	iastore
   20:	dup
   21:	iconst_3
   22:	bipush	123
   24:	iastore
   25:	dup
   26:	iconst_4
   27:	sipush	242
   30:	iastore
   31:	dup
   32:	iconst_5
   33:	bipush	107
   35:	iastore
   36:	dup
   37:	bipush	6
   39:	bipush	111
   41:	iastore
   42:	dup
   43:	bipush	7
   45:	sipush	197
   48:	iastore
   49:	dup
   50:	bipush	8
   52:	bipush	48
   54:	iastore
   55:	dup
   56:	bipush	9
   58:	iconst_1
   59:	iastore
   60:	dup
   61:	bipush	10
   63:	bipush	103
   65:	iastore
   66:	dup
   67:	bipush	11
   69:	bipush	43
   71:	iastore
   72:	dup
   73:	bipush	12
   75:	sipush	254
   78:	iastore
   79:	dup
   80:	bipush	13
   82:	sipush	215
   85:	iastore
   86:	dup
   87:	bipush	14
   89:	sipush	171
   92:	iastore
   93:	dup
   94:	bipush	15
   96:	bipush	118
   98:	iastore
   99:	dup
   100:	bipush	16
   102:	sipush	202
   105:	iastore
   106:	dup
   107:	bipush	17
   109:	sipush	130
   112:	iastore
   113:	dup
   114:	bipush	18
   116:	sipush	201
   119:	iastore
   120:	dup
   121:	bipush	19
   123:	bipush	125
   125:	iastore
   126:	dup
   127:	bipush	20
   129:	sipush	250
   132:	iastore
   133:	dup
   134:	bipush	21
   136:	bipush	89
   138:	iastore
   139:	dup
   140:	bipush	22
   142:	bipush	71
   144:	iastore
   145:	dup
   146:	bipush	23
   148:	sipush	240
   151:	iastore
   152:	dup
   153:	bipush	24
   155:	sipush	173
   158:	iastore
   159:	dup
   160:	bipush	25
   162:	sipush	212
   165:	iastore
   166:	dup
   167:	bipush	26
   169:	sipush	162
   172:	iastore
   173:	dup
   174:	bipush	27
   176:	sipush	175
   179:	iastore
   180:	dup
   181:	bipush	28
   183:	sipush	156
   186:	iastore
   187:	dup
   188:	bipush	29
   190:	sipush	164
   193:	iastore
   194:	dup
   195:	bipush	30
   197:	bipush	114
   199:	iastore
   200:	dup
   201:	bipush	31
   203:	sipush	192
   206:	iastore
   207:	dup
   208:	bipush	32
   210:	sipush	183
   213:	iastore
   214:	dup
   215:	bipush	33
   217:	sipush	253
   220:	iastore
   221:	dup
   222:	bipush	34
   224:	sipush	147
   227:	iastore
   228:	dup
   229:	bipush	35
   231:	bipush	38
   233:	iastore
   234:	dup
   235:	bipush	36
   237:	bipush	54
   239:	iastore
   240:	dup
   241:	bipush	37
   243:	bipush	63
   245:	iastore
   246:	dup
   247:	bipush	38
   249:	sipush	247
   252:	iastore
   253:	dup
   254:	bipush	39
   256:	sipush	204
   259:	iastore
   260:	dup
   261:	bipush	40
   263:	bipush	52
   265:	iastore
   266:	dup
   267:	bipush	41
   269:	sipush	165
   272:	iastore
   273:	dup
   274:	bipush	42
   276:	sipush	229
   279:	iastore
   280:	dup
   281:	bipush	43
   283:	sipush	241
   286:	iastore
   287:	dup
   288:	bipush	44
   290:	bipush	113
   292:	iastore
   293:	dup
   294:	bipush	45
   296:	sipush	216
   299:	iastore
   300:	dup
   301:	bipush	46
   303:	bipush	49
   305:	iastore
   306:	dup
   307:	bipush	47
   309:	bipush	21
   311:	iastore
   312:	dup
   313:	bipush	48
   315:	iconst_4
   316:	iastore
   317:	dup
   318:	bipush	49
   320:	sipush	199
   323:	iastore
   324:	dup
   325:	bipush	50
   327:	bipush	35
   329:	iastore
   330:	dup
   331:	bipush	51
   333:	sipush	195
   336:	iastore
   337:	dup
   338:	bipush	52
   340:	bipush	24
   342:	iastore
   343:	dup
   344:	bipush	53
   346:	sipush	150
   349:	iastore
   350:	dup
   351:	bipush	54
   353:	iconst_5
   354:	iastore
   355:	dup
   356:	bipush	55
   358:	sipush	154
   361:	iastore
   362:	dup
   363:	bipush	56
   365:	bipush	7
   367:	iastore
   368:	dup
   369:	bipush	57
   371:	bipush	18
   373:	iastore
   374:	dup
   375:	bipush	58
   377:	sipush	128
   380:	iastore
   381:	dup
   382:	bipush	59
   384:	sipush	226
   387:	iastore
   388:	dup
   389:	bipush	60
   391:	sipush	235
   394:	iastore
   395:	dup
   396:	bipush	61
   398:	bipush	39
   400:	iastore
   401:	dup
   402:	bipush	62
   404:	sipush	178
   407:	iastore
   408:	dup
   409:	bipush	63
   411:	bipush	117
   413:	iastore
   414:	dup
   415:	bipush	64
   417:	bipush	9
   419:	iastore
   420:	dup
   421:	bipush	65
   423:	sipush	131
   426:	iastore
   427:	dup
   428:	bipush	66
   430:	bipush	44
   432:	iastore
   433:	dup
   434:	bipush	67
   436:	bipush	26
   438:	iastore
   439:	dup
   440:	bipush	68
   442:	bipush	27
   444:	iastore
   445:	dup
   446:	bipush	69
   448:	bipush	110
   450:	iastore
   451:	dup
   452:	bipush	70
   454:	bipush	90
   456:	iastore
   457:	dup
   458:	bipush	71
   460:	sipush	160
   463:	iastore
   464:	dup
   465:	bipush	72
   467:	bipush	82
   469:	iastore
   470:	dup
   471:	bipush	73
   473:	bipush	59
   475:	iastore
   476:	dup
   477:	bipush	74
   479:	sipush	214
   482:	iastore
   483:	dup
   484:	bipush	75
   486:	sipush	179
   489:	iastore
   490:	dup
   491:	bipush	76
   493:	bipush	41
   495:	iastore
   496:	dup
   497:	bipush	77
   499:	sipush	227
   502:	iastore
   503:	dup
   504:	bipush	78
   506:	bipush	47
   508:	iastore
   509:	dup
   510:	bipush	79
   512:	sipush	132
   515:	iastore
   516:	dup
   517:	bipush	80
   519:	bipush	83
   521:	iastore
   522:	dup
   523:	bipush	81
   525:	sipush	209
   528:	iastore
   529:	dup
   530:	bipush	82
   532:	iconst_0
   533:	iastore
   534:	dup
   535:	bipush	83
   537:	sipush	237
   540:	iastore
   541:	dup
   542:	bipush	84
   544:	bipush	32
   546:	iastore
   547:	dup
   548:	bipush	85
   550:	sipush	252
   553:	iastore
   554:	dup
   555:	bipush	86
   557:	sipush	177
   560:	iastore
   561:	dup
   562:	bipush	87
   564:	bipush	91
   566:	iastore
   567:	dup
   568:	bipush	88
   570:	bipush	106
   572:	iastore
   573:	dup
   574:	bipush	89
   576:	sipush	203
   579:	iastore
   580:	dup
   581:	bipush	90
   583:	sipush	190
   586:	iastore
   587:	dup
   588:	bipush	91
   590:	bipush	57
   592:	iastore
   593:	dup
   594:	bipush	92
   596:	bipush	74
   598:	iastore
   599:	dup
   600:	bipush	93
   602:	bipush	76
   604:	iastore
   605:	dup
   606:	bipush	94
   608:	bipush	88
   610:	iastore
   611:	dup
   612:	bipush	95
   614:	sipush	207
   617:	iastore
   618:	dup
   619:	bipush	96
   621:	sipush	208
   624:	iastore
   625:	dup
   626:	bipush	97
   628:	sipush	239
   631:	iastore
   632:	dup
   633:	bipush	98
   635:	sipush	170
   638:	iastore
   639:	dup
   640:	bipush	99
   642:	sipush	251
   645:	iastore
   646:	dup
   647:	bipush	100
   649:	bipush	67
   651:	iastore
   652:	dup
   653:	bipush	101
   655:	bipush	77
   657:	iastore
   658:	dup
   659:	bipush	102
   661:	bipush	51
   663:	iastore
   664:	dup
   665:	bipush	103
   667:	sipush	133
   670:	iastore
   671:	dup
   672:	bipush	104
   674:	bipush	69
   676:	iastore
   677:	dup
   678:	bipush	105
   680:	sipush	249
   683:	iastore
   684:	dup
   685:	bipush	106
   687:	iconst_2
   688:	iastore
   689:	dup
   690:	bipush	107
   692:	bipush	127
   694:	iastore
   695:	dup
   696:	bipush	108
   698:	bipush	80
   700:	iastore
   701:	dup
   702:	bipush	109
   704:	bipush	60
   706:	iastore
   707:	dup
   708:	bipush	110
   710:	sipush	159
   713:	iastore
   714:	dup
   715:	bipush	111
   717:	sipush	168
   720:	iastore
   721:	dup
   722:	bipush	112
   724:	bipush	81
   726:	iastore
   727:	dup
   728:	bipush	113
   730:	sipush	163
   733:	iastore
   734:	dup
   735:	bipush	114
   737:	bipush	64
   739:	iastore
   740:	dup
   741:	bipush	115
   743:	sipush	143
   746:	iastore
   747:	dup
   748:	bipush	116
   750:	sipush	146
   753:	iastore
   754:	dup
   755:	bipush	117
   757:	sipush	157
   760:	iastore
   761:	dup
   762:	bipush	118
   764:	bipush	56
   766:	iastore
   767:	dup
   768:	bipush	119
   770:	sipush	245
   773:	iastore
   774:	dup
   775:	bipush	120
   777:	sipush	188
   780:	iastore
   781:	dup
   782:	bipush	121
   784:	sipush	182
   787:	iastore
   788:	dup
   789:	bipush	122
   791:	sipush	218
   794:	iastore
   795:	dup
   796:	bipush	123
   798:	bipush	33
   800:	iastore
   801:	dup
   802:	bipush	124
   804:	bipush	16
   806:	iastore
   807:	dup
   808:	bipush	125
   810:	sipush	255
   813:	iastore
   814:	dup
   815:	bipush	126
   817:	sipush	243
   820:	iastore
   821:	dup
   822:	bipush	127
   824:	sipush	210
   827:	iastore
   828:	dup
   829:	sipush	128
   832:	sipush	205
   835:	iastore
   836:	dup
   837:	sipush	129
   840:	bipush	12
   842:	iastore
   843:	dup
   844:	sipush	130
   847:	bipush	19
   849:	iastore
   850:	dup
   851:	sipush	131
   854:	sipush	236
   857:	iastore
   858:	dup
   859:	sipush	132
   862:	bipush	95
   864:	iastore
   865:	dup
   866:	sipush	133
   869:	sipush	151
   872:	iastore
   873:	dup
   874:	sipush	134
   877:	bipush	68
   879:	iastore
   880:	dup
   881:	sipush	135
   884:	bipush	23
   886:	iastore
   887:	dup
   888:	sipush	136
   891:	sipush	196
   894:	iastore
   895:	dup
   896:	sipush	137
   899:	sipush	167
   902:	iastore
   903:	dup
   904:	sipush	138
   907:	bipush	126
   909:	iastore
   910:	dup
   911:	sipush	139
   914:	bipush	61
   916:	iastore
   917:	dup
   918:	sipush	140
   921:	bipush	100
   923:	iastore
   924:	dup
   925:	sipush	141
   928:	bipush	93
   930:	iastore
   931:	dup
   932:	sipush	142
   935:	bipush	25
   937:	iastore
   938:	dup
   939:	sipush	143
   942:	bipush	115
   944:	iastore
   945:	dup
   946:	sipush	144
   949:	bipush	96
   951:	iastore
   952:	dup
   953:	sipush	145
   956:	sipush	129
   959:	iastore
   960:	dup
   961:	sipush	146
   964:	bipush	79
   966:	iastore
   967:	dup
   968:	sipush	147
   971:	sipush	220
   974:	iastore
   975:	dup
   976:	sipush	148
   979:	bipush	34
   981:	iastore
   982:	dup
   983:	sipush	149
   986:	bipush	42
   988:	iastore
   989:	dup
   990:	sipush	150
   993:	sipush	144
   996:	iastore
   997:	dup
   998:	sipush	151
   1001:	sipush	136
   1004:	iastore
   1005:	dup
   1006:	sipush	152
   1009:	bipush	70
   1011:	iastore
   1012:	dup
   1013:	sipush	153
   1016:	sipush	238
   1019:	iastore
   1020:	dup
   1021:	sipush	154
   1024:	sipush	184
   1027:	iastore
   1028:	dup
   1029:	sipush	155
   1032:	bipush	20
   1034:	iastore
   1035:	dup
   1036:	sipush	156
   1039:	sipush	222
   1042:	iastore
   1043:	dup
   1044:	sipush	157
   1047:	bipush	94
   1049:	iastore
   1050:	dup
   1051:	sipush	158
   1054:	bipush	11
   1056:	iastore
   1057:	dup
   1058:	sipush	159
   1061:	sipush	219
   1064:	iastore
   1065:	dup
   1066:	sipush	160
   1069:	sipush	224
   1072:	iastore
   1073:	dup
   1074:	sipush	161
   1077:	bipush	50
   1079:	iastore
   1080:	dup
   1081:	sipush	162
   1084:	bipush	58
   1086:	iastore
   1087:	dup
   1088:	sipush	163
   1091:	bipush	10
   1093:	iastore
   1094:	dup
   1095:	sipush	164
   1098:	bipush	73
   1100:	iastore
   1101:	dup
   1102:	sipush	165
   1105:	bipush	6
   1107:	iastore
   1108:	dup
   1109:	sipush	166
   1112:	bipush	36
   1114:	iastore
   1115:	dup
   1116:	sipush	167
   1119:	bipush	92
   1121:	iastore
   1122:	dup
   1123:	sipush	168
   1126:	sipush	194
   1129:	iastore
   1130:	dup
   1131:	sipush	169
   1134:	sipush	211
   1137:	iastore
   1138:	dup
   1139:	sipush	170
   1142:	sipush	172
   1145:	iastore
   1146:	dup
   1147:	sipush	171
   1150:	bipush	98
   1152:	iastore
   1153:	dup
   1154:	sipush	172
   1157:	sipush	145
   1160:	iastore
   1161:	dup
   1162:	sipush	173
   1165:	sipush	149
   1168:	iastore
   1169:	dup
   1170:	sipush	174
   1173:	sipush	228
   1176:	iastore
   1177:	dup
   1178:	sipush	175
   1181:	bipush	121
   1183:	iastore
   1184:	dup
   1185:	sipush	176
   1188:	sipush	231
   1191:	iastore
   1192:	dup
   1193:	sipush	177
   1196:	sipush	200
   1199:	iastore
   1200:	dup
   1201:	sipush	178
   1204:	bipush	55
   1206:	iastore
   1207:	dup
   1208:	sipush	179
   1211:	bipush	109
   1213:	iastore
   1214:	dup
   1215:	sipush	180
   1218:	sipush	141
   1221:	iastore
   1222:	dup
   1223:	sipush	181
   1226:	sipush	213
   1229:	iastore
   1230:	dup
   1231:	sipush	182
   1234:	bipush	78
   1236:	iastore
   1237:	dup
   1238:	sipush	183
   1241:	sipush	169
   1244:	iastore
   1245:	dup
   1246:	sipush	184
   1249:	bipush	108
   1251:	iastore
   1252:	dup
   1253:	sipush	185
   1256:	bipush	86
   1258:	iastore
   1259:	dup
   1260:	sipush	186
   1263:	sipush	244
   1266:	iastore
   1267:	dup
   1268:	sipush	187
   1271:	sipush	234
   1274:	iastore
   1275:	dup
   1276:	sipush	188
   1279:	bipush	101
   1281:	iastore
   1282:	dup
   1283:	sipush	189
   1286:	bipush	122
   1288:	iastore
   1289:	dup
   1290:	sipush	190
   1293:	sipush	174
   1296:	iastore
   1297:	dup
   1298:	sipush	191
   1301:	bipush	8
   1303:	iastore
   1304:	dup
   1305:	sipush	192
   1308:	sipush	186
   1311:	iastore
   1312:	dup
   1313:	sipush	193
   1316:	bipush	120
   1318:	iastore
   1319:	dup
   1320:	sipush	194
   1323:	bipush	37
   1325:	iastore
   1326:	dup
   1327:	sipush	195
   1330:	bipush	46
   1332:	iastore
   1333:	dup
   1334:	sipush	196
   1337:	bipush	28
   1339:	iastore
   1340:	dup
   1341:	sipush	197
   1344:	sipush	166
   1347:	iastore
   1348:	dup
   1349:	sipush	198
   1352:	sipush	180
   1355:	iastore
   1356:	dup
   1357:	sipush	199
   1360:	sipush	198
   1363:	iastore
   1364:	dup
   1365:	sipush	200
   1368:	sipush	232
   1371:	iastore
   1372:	dup
   1373:	sipush	201
   1376:	sipush	221
   1379:	iastore
   1380:	dup
   1381:	sipush	202
   1384:	bipush	116
   1386:	iastore
   1387:	dup
   1388:	sipush	203
   1391:	bipush	31
   1393:	iastore
   1394:	dup
   1395:	sipush	204
   1398:	bipush	75
   1400:	iastore
   1401:	dup
   1402:	sipush	205
   1405:	sipush	189
   1408:	iastore
   1409:	dup
   1410:	sipush	206
   1413:	sipush	139
   1416:	iastore
   1417:	dup
   1418:	sipush	207
   1421:	sipush	138
   1424:	iastore
   1425:	dup
   1426:	sipush	208
   1429:	bipush	112
   1431:	iastore
   1432:	dup
   1433:	sipush	209
   1436:	bipush	62
   1438:	iastore
   1439:	dup
   1440:	sipush	210
   1443:	sipush	181
   1446:	iastore
   1447:	dup
   1448:	sipush	211
   1451:	bipush	102
   1453:	iastore
   1454:	dup
   1455:	sipush	212
   1458:	bipush	72
   1460:	iastore
   1461:	dup
   1462:	sipush	213
   1465:	iconst_3
   1466:	iastore
   1467:	dup
   1468:	sipush	214
   1471:	sipush	246
   1474:	iastore
   1475:	dup
   1476:	sipush	215
   1479:	bipush	14
   1481:	iastore
   1482:	dup
   1483:	sipush	216
   1486:	bipush	97
   1488:	iastore
   1489:	dup
   1490:	sipush	217
   1493:	bipush	53
   1495:	iastore
   1496:	dup
   1497:	sipush	218
   1500:	bipush	87
   1502:	iastore
   1503:	dup
   1504:	sipush	219
   1507:	sipush	185
   1510:	iastore
   1511:	dup
   1512:	sipush	220
   1515:	sipush	134
   1518:	iastore
   1519:	dup
   1520:	sipush	221
   1523:	sipush	193
   1526:	iastore
   1527:	dup
   1528:	sipush	222
   1531:	bipush	29
   1533:	iastore
   1534:	dup
   1535:	sipush	223
   1538:	sipush	158
   1541:	iastore
   1542:	dup
   1543:	sipush	224
   1546:	sipush	225
   1549:	iastore
   1550:	dup
   1551:	sipush	225
   1554:	sipush	248
   1557:	iastore
   1558:	dup
   1559:	sipush	226
   1562:	sipush	152
   1565:	iastore
   1566:	dup
   1567:	sipush	227
   1570:	bipush	17
   1572:	iastore
   1573:	dup
   1574:	sipush	228
   1577:	bipush	105
   1579:	iastore
   1580:	dup
   1581:	sipush	229
   1584:	sipush	217
   1587:	iastore
   1588:	dup
   1589:	sipush	230
   1592:	sipush	142
   1595:	iastore
   1596:	dup
   1597:	sipush	231
   1600:	sipush	148
   1603:	iastore
   1604:	dup
   1605:	sipush	232
   1608:	sipush	155
   1611:	iastore
   1612:	dup
   1613:	sipush	233
   1616:	bipush	30
   1618:	iastore
   1619:	dup
   1620:	sipush	234
   1623:	sipush	135
   1626:	iastore
   1627:	dup
   1628:	sipush	235
   1631:	sipush	233
   1634:	iastore
   1635:	dup
   1636:	sipush	236
   1639:	sipush	206
   1642:	iastore
   1643:	dup
   1644:	sipush	237
   1647:	bipush	85
   1649:	iastore
   1650:	dup
   1651:	sipush	238
   1654:	bipush	40
   1656:	iastore
   1657:	dup
   1658:	sipush	239
   1661:	sipush	223
   1664:	iastore
   1665:	dup
   1666:	sipush	240
   1669:	sipush	140
   1672:	iastore
   1673:	dup
   1674:	sipush	241
   1677:	sipush	161
   1680:	iastore
   1681:	dup
   1682:	sipush	242
   1685:	sipush	137
   1688:	iastore
   1689:	dup
   1690:	sipush	243
   1693:	bipush	13
   1695:	iastore
   1696:	dup
   1697:	sipush	244
   1700:	sipush	191
   1703:	iastore
   1704:	dup
   1705:	sipush	245
   1708:	sipush	230
   1711:	iastore
   1712:	dup
   1713:	sipush	246
   1716:	bipush	66
   1718:	iastore
   1719:	dup
   1720:	sipush	247
   1723:	bipush	104
   1725:	iastore
   1726:	dup
   1727:	sipush	248
   1730:	bipush	65
   1732:	iastore
   1733:	dup
   1734:	sipush	249
   1737:	sipush	153
   1740:	iastore
   1741:	dup
   1742:	sipush	250
   1745:	bipush	45
   1747:	iastore
   1748:	dup
   1749:	sipush	251
   1752:	bipush	15
   1754:	iastore
   1755:	dup
   1756:	sipush	252
   1759:	sipush	176
   1762:	iastore
   1763:	dup
   1764:	sipush	253
   1767:	bipush	84
   1769:	iastore
   1770:	dup
   1771:	sipush	254
   1774:	sipush	187
   1777:	iastore
   1778:	dup
   1779:	sipush	255
   1782:	bipush	22
   1784:	iastore
   1785:	putstatic	#7; //Field gtable4:[I
   1788:	sipush	256
   1791:	newarray int
   1793:	dup
   1794:	iconst_0
   1795:	ldc	#8; //int 1667483301
   1797:	iastore
   1798:	dup
   1799:	iconst_1
   1800:	ldc	#9; //int 2088564868
   1802:	iastore
   1803:	dup
   1804:	iconst_2
   1805:	ldc	#10; //int 2004348569
   1807:	iastore
   1808:	dup
   1809:	iconst_3
   1810:	ldc	#11; //int 2071721613
   1812:	iastore
   1813:	dup
   1814:	iconst_4
   1815:	ldc	#12; //int -218956019
   1817:	iastore
   1818:	dup
   1819:	iconst_5
   1820:	ldc	#13; //int 1802229437
   1822:	iastore
   1823:	dup
   1824:	bipush	6
   1826:	ldc	#14; //int 1869602481
   1828:	iastore
   1829:	dup
   1830:	bipush	7
   1832:	ldc	#15; //int -976907948
   1834:	iastore
   1835:	dup
   1836:	bipush	8
   1838:	ldc	#16; //int 808476752
   1840:	iastore
   1841:	dup
   1842:	bipush	9
   1844:	ldc	#17; //int 16843267
   1846:	iastore
   1847:	dup
   1848:	bipush	10
   1850:	ldc	#18; //int 1734856361
   1852:	iastore
   1853:	dup
   1854:	bipush	11
   1856:	ldc	#19; //int 724260477
   1858:	iastore
   1859:	dup
   1860:	bipush	12
   1862:	ldc	#20; //int -16849127
   1864:	iastore
   1865:	dup
   1866:	bipush	13
   1868:	ldc	#21; //int -673729182
   1870:	iastore
   1871:	dup
   1872:	bipush	14
   1874:	ldc	#22; //int -1414836762
   1876:	iastore
   1877:	dup
   1878:	bipush	15
   1880:	ldc	#23; //int 1987505306
   1882:	iastore
   1883:	dup
   1884:	bipush	16
   1886:	ldc	#24; //int -892694715
   1888:	iastore
   1889:	dup
   1890:	bipush	17
   1892:	ldc	#25; //int -2105401443
   1894:	iastore
   1895:	dup
   1896:	bipush	18
   1898:	ldc	#26; //int -909539008
   1900:	iastore
   1901:	dup
   1902:	bipush	19
   1904:	ldc	#27; //int 2105408135
   1906:	iastore
   1907:	dup
   1908:	bipush	20
   1910:	ldc	#28; //int -84218091
   1912:	iastore
   1913:	dup
   1914:	bipush	21
   1916:	ldc	#29; //int 1499050731
   1918:	iastore
   1919:	dup
   1920:	bipush	22
   1922:	ldc	#30; //int 1195871945
   1924:	iastore
   1925:	dup
   1926:	bipush	23
   1928:	ldc	#31; //int -252642549
   1930:	iastore
   1931:	dup
   1932:	bipush	24
   1934:	ldc	#32; //int -1381154324
   1936:	iastore
   1937:	dup
   1938:	bipush	25
   1940:	ldc	#33; //int -724257945
   1942:	iastore
   1943:	dup
   1944:	bipush	26
   1946:	ldc	#34; //int -1566416899
   1948:	iastore
   1949:	dup
   1950:	bipush	27
   1952:	ldc	#35; //int -1347467798
   1954:	iastore
   1955:	dup
   1956:	bipush	28
   1958:	ldc	#36; //int -1667488833
   1960:	iastore
   1961:	dup
   1962:	bipush	29
   1964:	ldc	#37; //int -1532734473
   1966:	iastore
   1967:	dup
   1968:	bipush	30
   1970:	ldc	#38; //int 1920132246
   1972:	iastore
   1973:	dup
   1974:	bipush	31
   1976:	ldc	#39; //int -1061119141
   1978:	iastore
   1979:	dup
   1980:	bipush	32
   1982:	ldc	#40; //int -1212713534
   1984:	iastore
   1985:	dup
   1986:	bipush	33
   1988:	ldc	#41; //int -33693412
   1990:	iastore
   1991:	dup
   1992:	bipush	34
   1994:	ldc	#42; //int -1819066962
   1996:	iastore
   1997:	dup
   1998:	bipush	35
   2000:	ldc	#43; //int 640044138
   2002:	iastore
   2003:	dup
   2004:	bipush	36
   2006:	ldc	#44; //int 909536346
   2008:	iastore
   2009:	dup
   2010:	bipush	37
   2012:	ldc	#45; //int 1061125697
   2014:	iastore
   2015:	dup
   2016:	bipush	38
   2018:	ldc	#46; //int -134744830
   2020:	iastore
   2021:	dup
   2022:	bipush	39
   2024:	ldc	#47; //int -859012273
   2026:	iastore
   2027:	dup
   2028:	bipush	40
   2030:	ldc	#48; //int 875849820
   2032:	iastore
   2033:	dup
   2034:	bipush	41
   2036:	ldc	#49; //int -1515892236
   2038:	iastore
   2039:	dup
   2040:	bipush	42
   2042:	ldc	#50; //int -437923532
   2044:	iastore
   2045:	dup
   2046:	bipush	43
   2048:	ldc	#51; //int -235800312
   2050:	iastore
   2051:	dup
   2052:	bipush	44
   2054:	ldc	#52; //int 1903288979
   2056:	iastore
   2057:	dup
   2058:	bipush	45
   2060:	ldc	#53; //int -656888973
   2062:	iastore
   2063:	dup
   2064:	bipush	46
   2066:	ldc	#54; //int 825320019
   2068:	iastore
   2069:	dup
   2070:	bipush	47
   2072:	ldc	#55; //int 353708607
   2074:	iastore
   2075:	dup
   2076:	bipush	48
   2078:	ldc	#56; //int 67373068
   2080:	iastore
   2081:	dup
   2082:	bipush	49
   2084:	ldc	#57; //int -943221422
   2086:	iastore
   2087:	dup
   2088:	bipush	50
   2090:	ldc	#58; //int 589514341
   2092:	iastore
   2093:	dup
   2094:	bipush	51
   2096:	ldc	#59; //int -1010590370
   2098:	iastore
   2099:	dup
   2100:	bipush	52
   2102:	ldc	#60; //int 404238376
   2104:	iastore
   2105:	dup
   2106:	bipush	53
   2108:	ldc	#61; //int -1768540255
   2110:	iastore
   2111:	dup
   2112:	bipush	54
   2114:	ldc	#62; //int 84216335
   2116:	iastore
   2117:	dup
   2118:	bipush	55
   2120:	ldc	#63; //int -1701171275
   2122:	iastore
   2123:	dup
   2124:	bipush	56
   2126:	ldc	#64; //int 117902857
   2128:	iastore
   2129:	dup
   2130:	bipush	57
   2132:	ldc	#65; //int 303178806
   2134:	iastore
   2135:	dup
   2136:	bipush	58
   2138:	ldc	#66; //int -2139087973
   2140:	iastore
   2141:	dup
   2142:	bipush	59
   2144:	ldc	#67; //int -488448195
   2146:	iastore
   2147:	dup
   2148:	bipush	60
   2150:	ldc	#68; //int -336868058
   2152:	iastore
   2153:	dup
   2154:	bipush	61
   2156:	ldc	#69; //int 656887401
   2158:	iastore
   2159:	dup
   2160:	bipush	62
   2162:	ldc	#70; //int -1296924723
   2164:	iastore
   2165:	dup
   2166:	bipush	63
   2168:	ldc	#71; //int 1970662047
   2170:	iastore
   2171:	dup
   2172:	bipush	64
   2174:	ldc	#72; //int 151589403
   2176:	iastore
   2177:	dup
   2178:	bipush	65
   2180:	ldc	#73; //int -2088559202
   2182:	iastore
   2183:	dup
   2184:	bipush	66
   2186:	ldc	#74; //int 741103732
   2188:	iastore
   2189:	dup
   2190:	bipush	67
   2192:	ldc	#75; //int 437924910
   2194:	iastore
   2195:	dup
   2196:	bipush	68
   2198:	ldc	#76; //int 454768173
   2200:	iastore
   2201:	dup
   2202:	bipush	69
   2204:	ldc	#77; //int 1852759218
   2206:	iastore
   2207:	dup
   2208:	bipush	70
   2210:	ldc	#78; //int 1515893998
   2212:	iastore
   2213:	dup
   2214:	bipush	71
   2216:	ldc	#79; //int -1600103429
   2218:	iastore
   2219:	dup
   2220:	bipush	72
   2222:	ldc	#80; //int 1381147894
   2224:	iastore
   2225:	dup
   2226:	bipush	73
   2228:	ldc	#81; //int 993752653
   2230:	iastore
   2231:	dup
   2232:	bipush	74
   2234:	ldc	#82; //int -690571423
   2236:	iastore
   2237:	dup
   2238:	bipush	75
   2240:	ldc	#83; //int -1280082482
   2242:	iastore
   2243:	dup
   2244:	bipush	76
   2246:	ldc	#84; //int 690573947
   2248:	iastore
   2249:	dup
   2250:	bipush	77
   2252:	ldc	#85; //int -471605954
   2254:	iastore
   2255:	dup
   2256:	bipush	78
   2258:	ldc	#86; //int 791633521
   2260:	iastore
   2261:	dup
   2262:	bipush	79
   2264:	ldc	#87; //int -2071719017
   2266:	iastore
   2267:	dup
   2268:	bipush	80
   2270:	ldc	#88; //int 1397991157
   2272:	iastore
   2273:	dup
   2274:	bipush	81
   2276:	ldc	#89; //int -774784664
   2278:	iastore
   2279:	dup
   2280:	bipush	82
   2282:	iconst_0
   2283:	iastore
   2284:	dup
   2285:	bipush	83
   2287:	ldc	#90; //int -303185620
   2289:	iastore
   2290:	dup
   2291:	bipush	84
   2293:	ldc	#91; //int 538984544
   2295:	iastore
   2296:	dup
   2297:	bipush	85
   2299:	ldc	#92; //int -50535649
   2301:	iastore
   2302:	dup
   2303:	bipush	86
   2305:	ldc	#93; //int -1313769016
   2307:	iastore
   2308:	dup
   2309:	bipush	87
   2311:	ldc	#94; //int 1532737261
   2313:	iastore
   2314:	dup
   2315:	bipush	88
   2317:	ldc	#95; //int 1785386174
   2319:	iastore
   2320:	dup
   2321:	bipush	89
   2323:	ldc	#96; //int -875852474
   2325:	iastore
   2326:	dup
   2327:	bipush	90
   2329:	ldc	#97; //int -1094817831
   2331:	iastore
   2332:	dup
   2333:	bipush	91
   2335:	ldc	#98; //int 960066123
   2337:	iastore
   2338:	dup
   2339:	bipush	92
   2341:	ldc	#99; //int 1246401758
   2343:	iastore
   2344:	dup
   2345:	bipush	93
   2347:	ldc	#100; //int 1280088276
   2349:	iastore
   2350:	dup
   2351:	bipush	94
   2353:	ldc	#101; //int 1482207464
   2355:	iastore
   2356:	dup
   2357:	bipush	95
   2359:	ldc	#102; //int -808483510
   2361:	iastore
   2362:	dup
   2363:	bipush	96
   2365:	ldc	#103; //int -791626901
   2367:	iastore
   2368:	dup
   2369:	bipush	97
   2371:	ldc	#104; //int -269499094
   2373:	iastore
   2374:	dup
   2375:	bipush	98
   2377:	ldc	#105; //int -1431679003
   2379:	iastore
   2380:	dup
   2381:	bipush	99
   2383:	ldc	#106; //int -67375850
   2385:	iastore
   2386:	dup
   2387:	bipush	100
   2389:	ldc	#107; //int 1128498885
   2391:	iastore
   2392:	dup
   2393:	bipush	101
   2395:	ldc	#108; //int 1296931543
   2397:	iastore
   2398:	dup
   2399:	bipush	102
   2401:	ldc	#109; //int 859006549
   2403:	iastore
   2404:	dup
   2405:	bipush	103
   2407:	ldc	#110; //int -2054876780
   2409:	iastore
   2410:	dup
   2411:	bipush	104
   2413:	ldc	#111; //int 1162185423
   2415:	iastore
   2416:	dup
   2417:	bipush	105
   2419:	ldc	#112; //int -101062384
   2421:	iastore
   2422:	dup
   2423:	bipush	106
   2425:	ldc	#113; //int 33686534
   2427:	iastore
   2428:	dup
   2429:	bipush	107
   2431:	ldc	#114; //int 2139094657
   2433:	iastore
   2434:	dup
   2435:	bipush	108
   2437:	ldc	#115; //int 1347461360
   2439:	iastore
   2440:	dup
   2441:	bipush	109
   2443:	ldc	#116; //int 1010595908
   2445:	iastore
   2446:	dup
   2447:	bipush	110
   2449:	ldc	#117; //int -1616960070
   2451:	iastore
   2452:	dup
   2453:	bipush	111
   2455:	ldc	#118; //int -1465365533
   2457:	iastore
   2458:	dup
   2459:	bipush	112
   2461:	ldc	#119; //int 1364304627
   2463:	iastore
   2464:	dup
   2465:	bipush	113
   2467:	ldc	#120; //int -1549574658
   2469:	iastore
   2470:	dup
   2471:	bipush	114
   2473:	ldc	#121; //int 1077969088
   2475:	iastore
   2476:	dup
   2477:	bipush	115
   2479:	ldc	#122; //int -1886452342
   2481:	iastore
   2482:	dup
   2483:	bipush	116
   2485:	ldc	#123; //int -1835909203
   2487:	iastore
   2488:	dup
   2489:	bipush	117
   2491:	ldc	#124; //int -1650646596
   2493:	iastore
   2494:	dup
   2495:	bipush	118
   2497:	ldc	#125; //int 943222856
   2499:	iastore
   2500:	dup
   2501:	bipush	119
   2503:	ldc	#126; //int -168431356
   2505:	iastore
   2506:	dup
   2507:	bipush	120
   2509:	ldc	#127; //int -1128504353
   2511:	iastore
   2512:	dup
   2513:	bipush	121
   2515:	ldc	#128; //int -1229555775
   2517:	iastore
   2518:	dup
   2519:	bipush	122
   2521:	ldc	#129; //int -623202443
   2523:	iastore
   2524:	dup
   2525:	bipush	123
   2527:	ldc	#130; //int 555827811
   2529:	iastore
   2530:	dup
   2531:	bipush	124
   2533:	ldc	#131; //int 269492272
   2535:	iastore
   2536:	dup
   2537:	bipush	125
   2539:	sipush	-6886
   2542:	iastore
   2543:	dup
   2544:	bipush	126
   2546:	ldc	#132; //int -202113778
   2548:	iastore
   2549:	dup
   2550:	bipush	127
   2552:	ldc	#133; //int -757940371
   2554:	iastore
   2555:	dup
   2556:	sipush	128
   2559:	ldc	#134; //int -842170036
   2561:	iastore
   2562:	dup
   2563:	sipush	129
   2566:	ldc	#135; //int 202119188
   2568:	iastore
   2569:	dup
   2570:	sipush	130
   2573:	ldc	#136; //int 320022069
   2575:	iastore
   2576:	dup
   2577:	sipush	131
   2580:	ldc	#137; //int -320027857
   2582:	iastore
   2583:	dup
   2584:	sipush	132
   2587:	ldc	#138; //int 1600110305
   2589:	iastore
   2590:	dup
   2591:	sipush	133
   2594:	ldc	#139; //int -1751698014
   2596:	iastore
   2597:	dup
   2598:	sipush	134
   2601:	ldc	#140; //int 1145342156
   2603:	iastore
   2604:	dup
   2605:	sipush	135
   2608:	ldc	#141; //int 387395129
   2610:	iastore
   2611:	dup
   2612:	sipush	136
   2615:	ldc	#142; //int -993750185
   2617:	iastore
   2618:	dup
   2619:	sipush	137
   2622:	ldc	#143; //int -1482205710
   2624:	iastore
   2625:	dup
   2626:	sipush	138
   2629:	ldc	#144; //int 2122251394
   2631:	iastore
   2632:	dup
   2633:	sipush	139
   2636:	ldc	#145; //int 1027439175
   2638:	iastore
   2639:	dup
   2640:	sipush	140
   2643:	ldc	#146; //int 1684326572
   2645:	iastore
   2646:	dup
   2647:	sipush	141
   2650:	ldc	#147; //int 1566423783
   2652:	iastore
   2653:	dup
   2654:	sipush	142
   2657:	ldc	#148; //int 421081643
   2659:	iastore
   2660:	dup
   2661:	sipush	143
   2664:	ldc	#149; //int 1936975509
   2666:	iastore
   2667:	dup
   2668:	sipush	144
   2671:	ldc	#150; //int 1616953504
   2673:	iastore
   2674:	dup
   2675:	sipush	145
   2678:	ldc	#151; //int -2122245736
   2680:	iastore
   2681:	dup
   2682:	sipush	146
   2685:	ldc	#152; //int 1330618065
   2687:	iastore
   2688:	dup
   2689:	sipush	147
   2692:	ldc	#153; //int -589520001
   2694:	iastore
   2695:	dup
   2696:	sipush	148
   2699:	ldc	#154; //int 572671078
   2701:	iastore
   2702:	dup
   2703:	sipush	149
   2706:	ldc	#155; //int 707417214
   2708:	iastore
   2709:	dup
   2710:	sipush	150
   2713:	ldc	#156; //int -1869595733
   2715:	iastore
   2716:	dup
   2717:	sipush	151
   2720:	ldc	#157; //int -2004350077
   2722:	iastore
   2723:	dup
   2724:	sipush	152
   2727:	ldc	#158; //int 1179028682
   2729:	iastore
   2730:	dup
   2731:	sipush	153
   2734:	ldc	#159; //int -286341335
   2736:	iastore
   2737:	dup
   2738:	sipush	154
   2741:	ldc	#160; //int -1195873325
   2743:	iastore
   2744:	dup
   2745:	sipush	155
   2748:	ldc	#161; //int 336865340
   2750:	iastore
   2751:	dup
   2752:	sipush	156
   2755:	ldc	#162; //int -555833479
   2757:	iastore
   2758:	dup
   2759:	sipush	157
   2762:	ldc	#163; //int 1583267042
   2764:	iastore
   2765:	dup
   2766:	sipush	158
   2769:	ldc	#164; //int 185275933
   2771:	iastore
   2772:	dup
   2773:	sipush	159
   2776:	ldc	#165; //int -606360202
   2778:	iastore
   2779:	dup
   2780:	sipush	160
   2783:	ldc	#166; //int -522134725
   2785:	iastore
   2786:	dup
   2787:	sipush	161
   2790:	ldc	#167; //int 842163286
   2792:	iastore
   2793:	dup
   2794:	sipush	162
   2797:	ldc	#168; //int 976909390
   2799:	iastore
   2800:	dup
   2801:	sipush	163
   2804:	ldc	#169; //int 168432670
   2806:	iastore
   2807:	dup
   2808:	sipush	164
   2811:	ldc	#170; //int 1229558491
   2813:	iastore
   2814:	dup
   2815:	sipush	165
   2818:	ldc	#171; //int 101059594
   2820:	iastore
   2821:	dup
   2822:	sipush	166
   2825:	ldc	#172; //int 606357612
   2827:	iastore
   2828:	dup
   2829:	sipush	167
   2832:	ldc	#173; //int 1549580516
   2834:	iastore
   2835:	dup
   2836:	sipush	168
   2839:	ldc	#174; //int -1027432611
   2841:	iastore
   2842:	dup
   2843:	sipush	169
   2846:	ldc	#175; //int -741098130
   2848:	iastore
   2849:	dup
   2850:	sipush	170
   2853:	ldc	#176; //int -1397996561
   2855:	iastore
   2856:	dup
   2857:	sipush	171
   2860:	ldc	#177; //int 1650640038
   2862:	iastore
   2863:	dup
   2864:	sipush	172
   2867:	ldc	#178; //int -1852753496
   2869:	iastore
   2870:	dup
   2871:	sipush	173
   2874:	ldc	#179; //int -1785384540
   2876:	iastore
   2877:	dup
   2878:	sipush	174
   2881:	ldc	#180; //int -454765769
   2883:	iastore
   2884:	dup
   2885:	sipush	175
   2888:	ldc	#181; //int 2038035083
   2890:	iastore
   2891:	dup
   2892:	sipush	176
   2895:	ldc	#182; //int -404237006
   2897:	iastore
   2898:	dup
   2899:	sipush	177
   2902:	ldc	#183; //int -926381245
   2904:	iastore
   2905:	dup
   2906:	sipush	178
   2909:	ldc	#184; //int 926379609
   2911:	iastore
   2912:	dup
   2913:	sipush	179
   2916:	ldc	#185; //int 1835915959
   2918:	iastore
   2919:	dup
   2920:	sipush	180
   2923:	ldc	#186; //int -1920138868
   2925:	iastore
   2926:	dup
   2927:	sipush	181
   2930:	ldc	#187; //int -707415708
   2932:	iastore
   2933:	dup
   2934:	sipush	182
   2937:	ldc	#188; //int 1313774802
   2939:	iastore
   2940:	dup
   2941:	sipush	183
   2944:	ldc	#189; //int -1448523296
   2946:	iastore
   2947:	dup
   2948:	sipush	184
   2951:	ldc	#190; //int 1819072692
   2953:	iastore
   2954:	dup
   2955:	sipush	185
   2958:	ldc	#191; //int 1448520954
   2960:	iastore
   2961:	dup
   2962:	sipush	186
   2965:	ldc	#192; //int -185273593
   2967:	iastore
   2968:	dup
   2969:	sipush	187
   2972:	ldc	#193; //int -353710299
   2974:	iastore
   2975:	dup
   2976:	sipush	188
   2979:	ldc	#194; //int 1701169839
   2981:	iastore
   2982:	dup
   2983:	sipush	189
   2986:	ldc	#195; //int 2054878350
   2988:	iastore
   2989:	dup
   2990:	sipush	190
   2993:	ldc	#196; //int -1364310039
   2995:	iastore
   2996:	dup
   2997:	sipush	191
   3000:	ldc	#197; //int 134746136
   3002:	iastore
   3003:	dup
   3004:	sipush	192
   3007:	ldc	#198; //int -1162186795
   3009:	iastore
   3010:	dup
   3011:	sipush	193
   3014:	ldc	#199; //int 2021191816
   3016:	iastore
   3017:	dup
   3018:	sipush	194
   3021:	ldc	#200; //int 623200879
   3023:	iastore
   3024:	dup
   3025:	sipush	195
   3028:	ldc	#201; //int 774790258
   3030:	iastore
   3031:	dup
   3032:	sipush	196
   3035:	ldc	#202; //int 471611428
   3037:	iastore
   3038:	dup
   3039:	sipush	197
   3042:	ldc	#203; //int -1499047951
   3044:	iastore
   3045:	dup
   3046:	sipush	198
   3049:	ldc	#204; //int -1263242297
   3051:	iastore
   3052:	dup
   3053:	sipush	199
   3056:	ldc	#205; //int -960063663
   3058:	iastore
   3059:	dup
   3060:	sipush	200
   3063:	ldc	#206; //int -387396829
   3065:	iastore
   3066:	dup
   3067:	sipush	201
   3070:	ldc	#207; //int -572677764
   3072:	iastore
   3073:	dup
   3074:	sipush	202
   3077:	ldc	#208; //int 1953818780
   3079:	iastore
   3080:	dup
   3081:	sipush	203
   3084:	ldc	#209; //int 522141217
   3086:	iastore
   3087:	dup
   3088:	sipush	204
   3091:	ldc	#210; //int 1263245021
   3093:	iastore
   3094:	dup
   3095:	sipush	205
   3098:	ldc	#211; //int -1111662116
   3100:	iastore
   3101:	dup
   3102:	sipush	206
   3105:	ldc	#212; //int -1953821306
   3107:	iastore
   3108:	dup
   3109:	sipush	207
   3112:	ldc	#213; //int -1970663547
   3114:	iastore
   3115:	dup
   3116:	sipush	208
   3119:	ldc	#214; //int 1886445712
   3121:	iastore
   3122:	dup
   3123:	sipush	209
   3126:	ldc	#215; //int 1044282434
   3128:	iastore
   3129:	dup
   3130:	sipush	210
   3133:	ldc	#216; //int -1246400060
   3135:	iastore
   3136:	dup
   3137:	sipush	211
   3140:	ldc	#217; //int 1718013098
   3142:	iastore
   3143:	dup
   3144:	sipush	212
   3147:	ldc	#218; //int 1212715224
   3149:	iastore
   3150:	dup
   3151:	sipush	213
   3154:	ldc	#219; //int 50529797
   3156:	iastore
   3157:	dup
   3158:	sipush	214
   3161:	ldc	#220; //int -151587071
   3163:	iastore
   3164:	dup
   3165:	sipush	215
   3168:	ldc	#221; //int 235805714
   3170:	iastore
   3171:	dup
   3172:	sipush	216
   3175:	ldc	#222; //int 1633796771
   3177:	iastore
   3178:	dup
   3179:	sipush	217
   3182:	ldc	#223; //int 892693087
   3184:	iastore
   3185:	dup
   3186:	sipush	218
   3189:	ldc	#224; //int 1465364217
   3191:	iastore
   3192:	dup
   3193:	sipush	219
   3196:	ldc	#225; //int -1179031088
   3198:	iastore
   3199:	dup
   3200:	sipush	220
   3203:	ldc	#226; //int -2038032495
   3205:	iastore
   3206:	dup
   3207:	sipush	221
   3210:	ldc	#227; //int -1044276904
   3212:	iastore
   3213:	dup
   3214:	sipush	222
   3217:	ldc	#228; //int 488454695
   3219:	iastore
   3220:	dup
   3221:	sipush	223
   3224:	ldc	#229; //int -1633802311
   3226:	iastore
   3227:	dup
   3228:	sipush	224
   3231:	ldc	#230; //int -505292488
   3233:	iastore
   3234:	dup
   3235:	sipush	225
   3238:	ldc	#231; //int -117904621
   3240:	iastore
   3241:	dup
   3242:	sipush	226
   3245:	ldc	#232; //int -1734857805
   3247:	iastore
   3248:	dup
   3249:	sipush	227
   3252:	ldc	#233; //int 286335539
   3254:	iastore
   3255:	dup
   3256:	sipush	228
   3259:	ldc	#234; //int 1768542907
   3261:	iastore
   3262:	dup
   3263:	sipush	229
   3266:	ldc	#235; //int -640046736
   3268:	iastore
   3269:	dup
   3270:	sipush	230
   3273:	ldc	#236; //int -1903294583
   3275:	iastore
   3276:	dup
   3277:	sipush	231
   3280:	ldc	#237; //int -1802226777
   3282:	iastore
   3283:	dup
   3284:	sipush	232
   3287:	ldc	#238; //int -1684329034
   3289:	iastore
   3290:	dup
   3291:	sipush	233
   3294:	ldc	#239; //int 505297954
   3296:	iastore
   3297:	dup
   3298:	sipush	234
   3301:	ldc	#240; //int -2021190254
   3303:	iastore
   3304:	dup
   3305:	sipush	235
   3308:	ldc	#241; //int -370554592
   3310:	iastore
   3311:	dup
   3312:	sipush	236
   3315:	ldc	#242; //int -825325751
   3317:	iastore
   3318:	dup
   3319:	sipush	237
   3322:	ldc	#243; //int 1431677695
   3324:	iastore
   3325:	dup
   3326:	sipush	238
   3329:	ldc	#244; //int 673730680
   3331:	iastore
   3332:	dup
   3333:	sipush	239
   3336:	ldc	#245; //int -538991238
   3338:	iastore
   3339:	dup
   3340:	sipush	240
   3343:	ldc	#246; //int -1936981105
   3345:	iastore
   3346:	dup
   3347:	sipush	241
   3350:	ldc	#247; //int -1583261192
   3352:	iastore
   3353:	dup
   3354:	sipush	242
   3357:	ldc	#248; //int -1987507840
   3359:	iastore
   3360:	dup
   3361:	sipush	243
   3364:	ldc	#249; //int 218962455
   3366:	iastore
   3367:	dup
   3368:	sipush	244
   3371:	ldc	#250; //int -1077975590
   3373:	iastore
   3374:	dup
   3375:	sipush	245
   3378:	ldc	#251; //int -421079247
   3380:	iastore
   3381:	dup
   3382:	sipush	246
   3385:	ldc	#252; //int 1111655622
   3387:	iastore
   3388:	dup
   3389:	sipush	247
   3392:	ldc	#253; //int 1751699640
   3394:	iastore
   3395:	dup
   3396:	sipush	248
   3399:	ldc	#254; //int 1094812355
   3401:	iastore
   3402:	dup
   3403:	sipush	249
   3406:	ldc	#255; //int -1718015568
   3408:	iastore
   3409:	dup
   3410:	sipush	250
   3413:	ldc_w	#256; //int 757946999
   3416:	iastore
   3417:	dup
   3418:	sipush	251
   3421:	ldc_w	#257; //int 252648977
   3424:	iastore
   3425:	dup
   3426:	sipush	252
   3429:	ldc_w	#258; //int -1330611253
   3432:	iastore
   3433:	dup
   3434:	sipush	253
   3437:	ldc_w	#259; //int 1414834428
   3440:	iastore
   3441:	dup
   3442:	sipush	254
   3445:	ldc_w	#260; //int -1145344554
   3448:	iastore
   3449:	dup
   3450:	sipush	255
   3453:	ldc_w	#261; //int 370551866
   3456:	iastore
   3457:	putstatic	#4; //Field gtable1:[I
   3460:	sipush	256
   3463:	newarray int
   3465:	dup
   3466:	iconst_0
   3467:	ldc_w	#262; //int 1673962851
   3470:	iastore
   3471:	dup
   3472:	iconst_1
   3473:	ldc_w	#263; //int 2096661628
   3476:	iastore
   3477:	dup
   3478:	iconst_2
   3479:	ldc_w	#264; //int 2012125559
   3482:	iastore
   3483:	dup
   3484:	iconst_3
   3485:	ldc_w	#265; //int 2079755643
   3488:	iastore
   3489:	dup
   3490:	iconst_4
   3491:	ldc_w	#266; //int -218165774
   3494:	iastore
   3495:	dup
   3496:	iconst_5
   3497:	ldc_w	#267; //int 1809235307
   3500:	iastore
   3501:	dup
   3502:	bipush	6
   3504:	ldc_w	#268; //int 1876865391
   3507:	iastore
   3508:	dup
   3509:	bipush	7
   3511:	ldc_w	#269; //int -980331323
   3514:	iastore
   3515:	dup
   3516:	bipush	8
   3518:	ldc_w	#270; //int 811618352
   3521:	iastore
   3522:	dup
   3523:	bipush	9
   3525:	ldc_w	#271; //int 16909057
   3528:	iastore
   3529:	dup
   3530:	bipush	10
   3532:	ldc_w	#272; //int 1741597031
   3535:	iastore
   3536:	dup
   3537:	bipush	11
   3539:	ldc_w	#273; //int 727088427
   3542:	iastore
   3543:	dup
   3544:	bipush	12
   3546:	ldc_w	#274; //int -18408962
   3549:	iastore
   3550:	dup
   3551:	bipush	13
   3553:	ldc_w	#275; //int -675978537
   3556:	iastore
   3557:	dup
   3558:	bipush	14
   3560:	ldc_w	#276; //int -1420958037
   3563:	iastore
   3564:	dup
   3565:	bipush	15
   3567:	ldc_w	#277; //int 1995217526
   3570:	iastore
   3571:	dup
   3572:	bipush	16
   3574:	ldc_w	#278; //int -896580150
   3577:	iastore
   3578:	dup
   3579:	bipush	17
   3581:	ldc_w	#279; //int -2111857278
   3584:	iastore
   3585:	dup
   3586:	bipush	18
   3588:	ldc_w	#280; //int -913751863
   3591:	iastore
   3592:	dup
   3593:	bipush	19
   3595:	ldc_w	#281; //int 2113570685
   3598:	iastore
   3599:	dup
   3600:	bipush	20
   3602:	ldc_w	#282; //int -84994566
   3605:	iastore
   3606:	dup
   3607:	bipush	21
   3609:	ldc_w	#283; //int 1504897881
   3612:	iastore
   3613:	dup
   3614:	bipush	22
   3616:	ldc_w	#284; //int 1200539975
   3619:	iastore
   3620:	dup
   3621:	bipush	23
   3623:	ldc_w	#285; //int -251982864
   3626:	iastore
   3627:	dup
   3628:	bipush	24
   3630:	ldc_w	#286; //int -1388188499
   3633:	iastore
   3634:	dup
   3635:	bipush	25
   3637:	ldc_w	#287; //int -726439980
   3640:	iastore
   3641:	dup
   3642:	bipush	26
   3644:	ldc_w	#288; //int -1570767454
   3647:	iastore
   3648:	dup
   3649:	bipush	27
   3651:	ldc_w	#289; //int -1354372433
   3654:	iastore
   3655:	dup
   3656:	bipush	28
   3658:	ldc_w	#290; //int -1675378788
   3661:	iastore
   3662:	dup
   3663:	bipush	29
   3665:	ldc_w	#291; //int -1538000988
   3668:	iastore
   3669:	dup
   3670:	bipush	30
   3672:	ldc_w	#292; //int 1927583346
   3675:	iastore
   3676:	dup
   3677:	bipush	31
   3679:	ldc_w	#293; //int -1063560256
   3682:	iastore
   3683:	dup
   3684:	bipush	32
   3686:	ldc_w	#294; //int -1217019209
   3689:	iastore
   3690:	dup
   3691:	bipush	33
   3693:	ldc_w	#295; //int -35578627
   3696:	iastore
   3697:	dup
   3698:	bipush	34
   3700:	ldc_w	#296; //int -1824674157
   3703:	iastore
   3704:	dup
   3705:	bipush	35
   3707:	ldc_w	#297; //int 642542118
   3710:	iastore
   3711:	dup
   3712:	bipush	36
   3714:	ldc_w	#298; //int 913070646
   3717:	iastore
   3718:	dup
   3719:	bipush	37
   3721:	ldc_w	#299; //int 1065238847
   3724:	iastore
   3725:	dup
   3726:	bipush	38
   3728:	ldc_w	#300; //int -134937865
   3731:	iastore
   3732:	dup
   3733:	bipush	39
   3735:	ldc_w	#301; //int -863809588
   3738:	iastore
   3739:	dup
   3740:	bipush	40
   3742:	ldc_w	#302; //int 879254580
   3745:	iastore
   3746:	dup
   3747:	bipush	41
   3749:	ldc_w	#303; //int -1521355611
   3752:	iastore
   3753:	dup
   3754:	bipush	42
   3756:	ldc_w	#304; //int -439274267
   3759:	iastore
   3760:	dup
   3761:	bipush	43
   3763:	ldc_w	#305; //int -235337487
   3766:	iastore
   3767:	dup
   3768:	bipush	44
   3770:	ldc_w	#306; //int 1910674289
   3773:	iastore
   3774:	dup
   3775:	bipush	45
   3777:	ldc_w	#307; //int -659852328
   3780:	iastore
   3781:	dup
   3782:	bipush	46
   3784:	ldc_w	#308; //int 828527409
   3787:	iastore
   3788:	dup
   3789:	bipush	47
   3791:	ldc_w	#309; //int 355090197
   3794:	iastore
   3795:	dup
   3796:	bipush	48
   3798:	ldc_w	#310; //int 67636228
   3801:	iastore
   3802:	dup
   3803:	bipush	49
   3805:	ldc_w	#311; //int -946515257
   3808:	iastore
   3809:	dup
   3810:	bipush	50
   3812:	ldc_w	#312; //int 591815971
   3815:	iastore
   3816:	dup
   3817:	bipush	51
   3819:	ldc_w	#313; //int -1013096765
   3822:	iastore
   3823:	dup
   3824:	bipush	52
   3826:	ldc_w	#314; //int 405809176
   3829:	iastore
   3830:	dup
   3831:	bipush	53
   3833:	ldc_w	#315; //int -1774739050
   3836:	iastore
   3837:	dup
   3838:	bipush	54
   3840:	ldc_w	#316; //int 84545285
   3843:	iastore
   3844:	dup
   3845:	bipush	55
   3847:	ldc_w	#317; //int -1708149350
   3850:	iastore
   3851:	dup
   3852:	bipush	56
   3854:	ldc_w	#318; //int 118360327
   3857:	iastore
   3858:	dup
   3859:	bipush	57
   3861:	ldc_w	#319; //int 304363026
   3864:	iastore
   3865:	dup
   3866:	bipush	58
   3868:	ldc_w	#320; //int -2145674368
   3871:	iastore
   3872:	dup
   3873:	bipush	59
   3875:	ldc_w	#321; //int -488686110
   3878:	iastore
   3879:	dup
   3880:	bipush	60
   3882:	ldc_w	#322; //int -338876693
   3885:	iastore
   3886:	dup
   3887:	bipush	61
   3889:	ldc_w	#323; //int 659450151
   3892:	iastore
   3893:	dup
   3894:	bipush	62
   3896:	ldc_w	#324; //int -1300247118
   3899:	iastore
   3900:	dup
   3901:	bipush	63
   3903:	ldc_w	#325; //int 1978310517
   3906:	iastore
   3907:	dup
   3908:	bipush	64
   3910:	ldc_w	#326; //int 152181513
   3913:	iastore
   3914:	dup
   3915:	bipush	65
   3917:	ldc_w	#327; //int -2095210877
   3920:	iastore
   3921:	dup
   3922:	bipush	66
   3924:	ldc_w	#328; //int 743994412
   3927:	iastore
   3928:	dup
   3929:	bipush	67
   3931:	ldc_w	#329; //int 439627290
   3934:	iastore
   3935:	dup
   3936:	bipush	68
   3938:	ldc_w	#330; //int 456535323
   3941:	iastore
   3942:	dup
   3943:	bipush	69
   3945:	ldc_w	#331; //int 1859957358
   3948:	iastore
   3949:	dup
   3950:	bipush	70
   3952:	ldc_w	#332; //int 1521806938
   3955:	iastore
   3956:	dup
   3957:	bipush	71
   3959:	ldc_w	#333; //int -1604584544
   3962:	iastore
   3963:	dup
   3964:	bipush	72
   3966:	ldc_w	#334; //int 1386542674
   3969:	iastore
   3970:	dup
   3971:	bipush	73
   3973:	ldc_w	#335; //int 997608763
   3976:	iastore
   3977:	dup
   3978:	bipush	74
   3980:	ldc_w	#336; //int -692624938
   3983:	iastore
   3984:	dup
   3985:	bipush	75
   3987:	ldc_w	#337; //int -1283600717
   3990:	iastore
   3991:	dup
   3992:	bipush	76
   3994:	ldc_w	#338; //int 693271337
   3997:	iastore
   3998:	dup
   3999:	bipush	77
   4001:	ldc_w	#339; //int -472039709
   4004:	iastore
   4005:	dup
   4006:	bipush	78
   4008:	ldc_w	#340; //int 794718511
   4011:	iastore
   4012:	dup
   4013:	bipush	79
   4015:	ldc_w	#341; //int -2079090812
   4018:	iastore
   4019:	dup
   4020:	bipush	80
   4022:	ldc_w	#342; //int 1403450707
   4025:	iastore
   4026:	dup
   4027:	bipush	81
   4029:	ldc_w	#343; //int -776378159
   4032:	iastore
   4033:	dup
   4034:	bipush	82
   4036:	iconst_0
   4037:	iastore
   4038:	dup
   4039:	bipush	83
   4041:	ldc_w	#344; //int -306107155
   4044:	iastore
   4045:	dup
   4046:	bipush	84
   4048:	ldc_w	#345; //int 541089824
   4051:	iastore
   4052:	dup
   4053:	bipush	85
   4055:	ldc_w	#346; //int -52224004
   4058:	iastore
   4059:	dup
   4060:	bipush	86
   4062:	ldc_w	#347; //int -1317418831
   4065:	iastore
   4066:	dup
   4067:	bipush	87
   4069:	ldc_w	#348; //int 1538714971
   4072:	iastore
   4073:	dup
   4074:	bipush	88
   4076:	ldc_w	#349; //int 1792327274
   4079:	iastore
   4080:	dup
   4081:	bipush	89
   4083:	ldc_w	#350; //int -879933749
   4086:	iastore
   4087:	dup
   4088:	bipush	90
   4090:	ldc_w	#351; //int -1100490306
   4093:	iastore
   4094:	dup
   4095:	bipush	91
   4097:	ldc_w	#352; //int 963791673
   4100:	iastore
   4101:	dup
   4102:	bipush	92
   4104:	ldc_w	#353; //int 1251270218
   4107:	iastore
   4108:	dup
   4109:	bipush	93
   4111:	ldc_w	#354; //int 1285084236
   4114:	iastore
   4115:	dup
   4116:	bipush	94
   4118:	ldc_w	#355; //int 1487988824
   4121:	iastore
   4122:	dup
   4123:	bipush	95
   4125:	ldc_w	#356; //int -813348145
   4128:	iastore
   4129:	dup
   4130:	bipush	96
   4132:	ldc_w	#357; //int -793023536
   4135:	iastore
   4136:	dup
   4137:	bipush	97
   4139:	ldc_w	#358; //int -272291089
   4142:	iastore
   4143:	dup
   4144:	bipush	98
   4146:	ldc_w	#359; //int -1437604438
   4149:	iastore
   4150:	dup
   4151:	bipush	99
   4153:	ldc_w	#360; //int -68348165
   4156:	iastore
   4157:	dup
   4158:	bipush	100
   4160:	ldc_w	#361; //int 1132905795
   4163:	iastore
   4164:	dup
   4165:	bipush	101
   4167:	ldc_w	#362; //int 1301993293
   4170:	iastore
   4171:	dup
   4172:	bipush	102
   4174:	ldc_w	#363; //int 862344499
   4177:	iastore
   4178:	dup
   4179:	bipush	103
   4181:	ldc_w	#364; //int -2062445435
   4184:	iastore
   4185:	dup
   4186:	bipush	104
   4188:	ldc_w	#365; //int 1166724933
   4191:	iastore
   4192:	dup
   4193:	bipush	105
   4195:	ldc_w	#366; //int -102166279
   4198:	iastore
   4199:	dup
   4200:	bipush	106
   4202:	ldc_w	#367; //int 33818114
   4205:	iastore
   4206:	dup
   4207:	bipush	107
   4209:	ldc_w	#368; //int 2147385727
   4212:	iastore
   4213:	dup
   4214:	bipush	108
   4216:	ldc_w	#369; //int 1352724560
   4219:	iastore
   4220:	dup
   4221:	bipush	109
   4223:	ldc_w	#370; //int 1014514748
   4226:	iastore
   4227:	dup
   4228:	bipush	110
   4230:	ldc_w	#371; //int -1624917345
   4233:	iastore
   4234:	dup
   4235:	bipush	111
   4237:	ldc_w	#372; //int -1471421528
   4240:	iastore
   4241:	dup
   4242:	bipush	112
   4244:	ldc_w	#373; //int 1369633617
   4247:	iastore
   4248:	dup
   4249:	bipush	113
   4251:	ldc_w	#374; //int -1554121053
   4254:	iastore
   4255:	dup
   4256:	bipush	114
   4258:	ldc_w	#375; //int 1082179648
   4261:	iastore
   4262:	dup
   4263:	bipush	115
   4265:	ldc_w	#376; //int -1895462257
   4268:	iastore
   4269:	dup
   4270:	bipush	116
   4272:	ldc_w	#377; //int -1841320558
   4275:	iastore
   4276:	dup
   4277:	bipush	117
   4279:	ldc_w	#378; //int -1658733411
   4282:	iastore
   4283:	dup
   4284:	bipush	118
   4286:	ldc_w	#379; //int 946882616
   4289:	iastore
   4290:	dup
   4291:	bipush	119
   4293:	ldc_w	#380; //int -168753931
   4296:	iastore
   4297:	dup
   4298:	bipush	120
   4300:	ldc_w	#381; //int -1134305348
   4303:	iastore
   4304:	dup
   4305:	bipush	121
   4307:	ldc_w	#382; //int -1233665610
   4310:	iastore
   4311:	dup
   4312:	bipush	122
   4314:	ldc_w	#383; //int -626035238
   4317:	iastore
   4318:	dup
   4319:	bipush	123
   4321:	ldc_w	#384; //int 557998881
   4324:	iastore
   4325:	dup
   4326:	bipush	124
   4328:	ldc_w	#385; //int 270544912
   4331:	iastore
   4332:	dup
   4333:	bipush	125
   4335:	ldc_w	#386; //int -1762561
   4338:	iastore
   4339:	dup
   4340:	bipush	126
   4342:	ldc_w	#387; //int -201519373
   4345:	iastore
   4346:	dup
   4347:	bipush	127
   4349:	ldc_w	#388; //int -759206446
   4352:	iastore
   4353:	dup
   4354:	sipush	128
   4357:	ldc_w	#389; //int -847164211
   4360:	iastore
   4361:	dup
   4362:	sipush	129
   4365:	ldc_w	#390; //int 202904588
   4368:	iastore
   4369:	dup
   4370:	sipush	130
   4373:	ldc_w	#391; //int 321271059
   4376:	iastore
   4377:	dup
   4378:	sipush	131
   4381:	ldc_w	#392; //int -322752532
   4384:	iastore
   4385:	dup
   4386:	sipush	132
   4389:	ldc_w	#393; //int 1606345055
   4392:	iastore
   4393:	dup
   4394:	sipush	133
   4397:	ldc_w	#394; //int -1758092649
   4400:	iastore
   4401:	dup
   4402:	sipush	134
   4405:	ldc_w	#395; //int 1149815876
   4408:	iastore
   4409:	dup
   4410:	sipush	135
   4413:	ldc_w	#396; //int 388905239
   4416:	iastore
   4417:	dup
   4418:	sipush	136
   4421:	ldc_w	#397; //int -996976700
   4424:	iastore
   4425:	dup
   4426:	sipush	137
   4429:	ldc_w	#398; //int -1487539545
   4432:	iastore
   4433:	dup
   4434:	sipush	138
   4437:	ldc_w	#399; //int 2130477694
   4440:	iastore
   4441:	dup
   4442:	sipush	139
   4445:	ldc_w	#400; //int 1031423805
   4448:	iastore
   4449:	dup
   4450:	sipush	140
   4453:	ldc_w	#401; //int 1690872932
   4456:	iastore
   4457:	dup
   4458:	sipush	141
   4461:	ldc_w	#402; //int 1572530013
   4464:	iastore
   4465:	dup
   4466:	sipush	142
   4469:	ldc_w	#403; //int 422718233
   4472:	iastore
   4473:	dup
   4474:	sipush	143
   4477:	ldc_w	#404; //int 1944491379
   4480:	iastore
   4481:	dup
   4482:	sipush	144
   4485:	ldc_w	#405; //int 1623236704
   4488:	iastore
   4489:	dup
   4490:	sipush	145
   4493:	ldc_w	#406; //int -2129028991
   4496:	iastore
   4497:	dup
   4498:	sipush	146
   4501:	ldc_w	#407; //int 1335808335
   4504:	iastore
   4505:	dup
   4506:	sipush	147
   4509:	ldc_w	#408; //int -593264676
   4512:	iastore
   4513:	dup
   4514:	sipush	148
   4517:	ldc_w	#409; //int 574907938
   4520:	iastore
   4521:	dup
   4522:	sipush	149
   4525:	ldc_w	#410; //int 710180394
   4528:	iastore
   4529:	dup
   4530:	sipush	150
   4533:	ldc_w	#411; //int -1875137648
   4536:	iastore
   4537:	dup
   4538:	sipush	151
   4541:	ldc_w	#412; //int -2012511352
   4544:	iastore
   4545:	dup
   4546:	sipush	152
   4549:	ldc_w	#413; //int 1183631942
   4552:	iastore
   4553:	dup
   4554:	sipush	153
   4557:	ldc_w	#414; //int -288937490
   4560:	iastore
   4561:	dup
   4562:	sipush	154
   4565:	ldc_w	#415; //int -1200893000
   4568:	iastore
   4569:	dup
   4570:	sipush	155
   4573:	ldc_w	#416; //int 338181140
   4576:	iastore
   4577:	dup
   4578:	sipush	156
   4581:	ldc_w	#417; //int -559449634
   4584:	iastore
   4585:	dup
   4586:	sipush	157
   4589:	ldc_w	#418; //int 1589437022
   4592:	iastore
   4593:	dup
   4594:	sipush	158
   4597:	ldc_w	#419; //int 185998603
   4600:	iastore
   4601:	dup
   4602:	sipush	159
   4605:	ldc_w	#420; //int -609388837
   4608:	iastore
   4609:	dup
   4610:	sipush	160
   4613:	ldc_w	#421; //int -522503200
   4616:	iastore
   4617:	dup
   4618:	sipush	161
   4621:	ldc_w	#422; //int 845436466
   4624:	iastore
   4625:	dup
   4626:	sipush	162
   4629:	ldc_w	#423; //int 980700730
   4632:	iastore
   4633:	dup
   4634:	sipush	163
   4637:	ldc_w	#424; //int 169090570
   4640:	iastore
   4641:	dup
   4642:	sipush	164
   4645:	ldc_w	#425; //int 1234361161
   4648:	iastore
   4649:	dup
   4650:	sipush	165
   4653:	ldc_w	#426; //int 101452294
   4656:	iastore
   4657:	dup
   4658:	sipush	166
   4661:	ldc_w	#427; //int 608726052
   4664:	iastore
   4665:	dup
   4666:	sipush	167
   4669:	ldc_w	#428; //int 1555620956
   4672:	iastore
   4673:	dup
   4674:	sipush	168
   4677:	ldc_w	#429; //int -1029743166
   4680:	iastore
   4681:	dup
   4682:	sipush	169
   4685:	ldc_w	#430; //int -742560045
   4688:	iastore
   4689:	dup
   4690:	sipush	170
   4693:	ldc_w	#431; //int -1404833876
   4696:	iastore
   4697:	dup
   4698:	sipush	171
   4701:	ldc_w	#432; //int 1657054818
   4704:	iastore
   4705:	dup
   4706:	sipush	172
   4709:	ldc_w	#433; //int -1858492271
   4712:	iastore
   4713:	dup
   4714:	sipush	173
   4717:	ldc_w	#434; //int -1791908715
   4720:	iastore
   4721:	dup
   4722:	sipush	174
   4725:	ldc_w	#435; //int -455919644
   4728:	iastore
   4729:	dup
   4730:	sipush	175
   4733:	ldc_w	#436; //int 2045938553
   4736:	iastore
   4737:	dup
   4738:	sipush	176
   4741:	ldc_w	#437; //int -405458201
   4744:	iastore
   4745:	dup
   4746:	sipush	177
   4749:	ldc_w	#438; //int -930397240
   4752:	iastore
   4753:	dup
   4754:	sipush	178
   4757:	ldc_w	#439; //int 929978679
   4760:	iastore
   4761:	dup
   4762:	sipush	179
   4765:	ldc_w	#440; //int 1843050349
   4768:	iastore
   4769:	dup
   4770:	sipush	180
   4773:	ldc_w	#441; //int -1929278323
   4776:	iastore
   4777:	dup
   4778:	sipush	181
   4781:	ldc_w	#442; //int -709794603
   4784:	iastore
   4785:	dup
   4786:	sipush	182
   4789:	ldc_w	#443; //int 1318900302
   4792:	iastore
   4793:	dup
   4794:	sipush	183
   4797:	ldc_w	#444; //int -1454776151
   4800:	iastore
   4801:	dup
   4802:	sipush	184
   4805:	ldc_w	#445; //int 1826141292
   4808:	iastore
   4809:	dup
   4810:	sipush	185
   4813:	ldc_w	#446; //int 1454176854
   4816:	iastore
   4817:	dup
   4818:	sipush	186
   4821:	ldc_w	#447; //int -185399308
   4824:	iastore
   4825:	dup
   4826:	sipush	187
   4829:	ldc_w	#448; //int -355523094
   4832:	iastore
   4833:	dup
   4834:	sipush	188
   4837:	ldc_w	#449; //int 1707781989
   4840:	iastore
   4841:	dup
   4842:	sipush	189
   4845:	ldc_w	#450; //int 2062847610
   4848:	iastore
   4849:	dup
   4850:	sipush	190
   4853:	ldc_w	#451; //int -1371018834
   4856:	iastore
   4857:	dup
   4858:	sipush	191
   4861:	ldc_w	#452; //int 135272456
   4864:	iastore
   4865:	dup
   4866:	sipush	192
   4869:	ldc_w	#453; //int -1167075910
   4872:	iastore
   4873:	dup
   4874:	sipush	193
   4877:	ldc_w	#454; //int 2029029496
   4880:	iastore
   4881:	dup
   4882:	sipush	194
   4885:	ldc_w	#455; //int 625635109
   4888:	iastore
   4889:	dup
   4890:	sipush	195
   4893:	ldc_w	#456; //int 777810478
   4896:	iastore
   4897:	dup
   4898:	sipush	196
   4901:	ldc_w	#457; //int 473441308
   4904:	iastore
   4905:	dup
   4906:	sipush	197
   4909:	ldc_w	#458; //int -1504185946
   4912:	iastore
   4913:	dup
   4914:	sipush	198
   4917:	ldc_w	#459; //int -1267480652
   4920:	iastore
   4921:	dup
   4922:	sipush	199
   4925:	ldc_w	#460; //int -963161658
   4928:	iastore
   4929:	dup
   4930:	sipush	200
   4933:	ldc_w	#461; //int -389340184
   4936:	iastore
   4937:	dup
   4938:	sipush	201
   4941:	ldc_w	#462; //int -576619299
   4944:	iastore
   4945:	dup
   4946:	sipush	202
   4949:	ldc_w	#463; //int 1961401460
   4952:	iastore
   4953:	dup
   4954:	sipush	203
   4957:	ldc_w	#464; //int 524165407
   4960:	iastore
   4961:	dup
   4962:	sipush	204
   4965:	ldc_w	#465; //int 1268178251
   4968:	iastore
   4969:	dup
   4970:	sipush	205
   4973:	ldc_w	#466; //int -1117659971
   4976:	iastore
   4977:	dup
   4978:	sipush	206
   4981:	ldc_w	#467; //int -1962047861
   4984:	iastore
   4985:	dup
   4986:	sipush	207
   4989:	ldc_w	#468; //int -1978694262
   4992:	iastore
   4993:	dup
   4994:	sipush	208
   4997:	ldc_w	#469; //int 1893765232
   5000:	iastore
   5001:	dup
   5002:	sipush	209
   5005:	ldc_w	#470; //int 1048330814
   5008:	iastore
   5009:	dup
   5010:	sipush	210
   5013:	ldc_w	#471; //int -1250835275
   5016:	iastore
   5017:	dup
   5018:	sipush	211
   5021:	ldc_w	#472; //int 1724688998
   5024:	iastore
   5025:	dup
   5026:	sipush	212
   5029:	ldc_w	#473; //int 1217452104
   5032:	iastore
   5033:	dup
   5034:	sipush	213
   5037:	ldc_w	#474; //int 50726147
   5040:	iastore
   5041:	dup
   5042:	sipush	214
   5045:	ldc_w	#475; //int -151584266
   5048:	iastore
   5049:	dup
   5050:	sipush	215
   5053:	ldc_w	#476; //int 236720654
   5056:	iastore
   5057:	dup
   5058:	sipush	216
   5061:	ldc_w	#477; //int 1640145761
   5064:	iastore
   5065:	dup
   5066:	sipush	217
   5069:	ldc_w	#478; //int 896163637
   5072:	iastore
   5073:	dup
   5074:	sipush	218
   5077:	ldc_w	#479; //int 1471084887
   5080:	iastore
   5081:	dup
   5082:	sipush	219
   5085:	ldc_w	#480; //int -1184247623
   5088:	iastore
   5089:	dup
   5090:	sipush	220
   5093:	ldc_w	#481; //int -2045275770
   5096:	iastore
   5097:	dup
   5098:	sipush	221
   5101:	ldc_w	#482; //int -1046914879
   5104:	iastore
   5105:	dup
   5106:	sipush	222
   5109:	ldc_w	#483; //int 490350365
   5112:	iastore
   5113:	dup
   5114:	sipush	223
   5117:	ldc_w	#484; //int -1641563746
   5120:	iastore
   5121:	dup
   5122:	sipush	224
   5125:	ldc_w	#485; //int -505857823
   5128:	iastore
   5129:	dup
   5130:	sipush	225
   5133:	ldc_w	#486; //int -118811656
   5136:	iastore
   5137:	dup
   5138:	sipush	226
   5141:	ldc_w	#487; //int -1741966440
   5144:	iastore
   5145:	dup
   5146:	sipush	227
   5149:	ldc_w	#488; //int 287453969
   5152:	iastore
   5153:	dup
   5154:	sipush	228
   5157:	ldc_w	#489; //int 1775418217
   5160:	iastore
   5161:	dup
   5162:	sipush	229
   5165:	ldc_w	#490; //int -643206951
   5168:	iastore
   5169:	dup
   5170:	sipush	230
   5173:	ldc_w	#491; //int -1912108658
   5176:	iastore
   5177:	dup
   5178:	sipush	231
   5181:	ldc_w	#492; //int -1808554092
   5184:	iastore
   5185:	dup
   5186:	sipush	232
   5189:	ldc_w	#493; //int -1691502949
   5192:	iastore
   5193:	dup
   5194:	sipush	233
   5197:	ldc_w	#494; //int 507257374
   5200:	iastore
   5201:	dup
   5202:	sipush	234
   5205:	ldc_w	#495; //int -2028629369
   5208:	iastore
   5209:	dup
   5210:	sipush	235
   5213:	ldc_w	#496; //int -372694807
   5216:	iastore
   5217:	dup
   5218:	sipush	236
   5221:	ldc_w	#497; //int -829994546
   5224:	iastore
   5225:	dup
   5226:	sipush	237
   5229:	ldc_w	#498; //int 1437269845
   5232:	iastore
   5233:	dup
   5234:	sipush	238
   5237:	ldc_w	#499; //int 676362280
   5240:	iastore
   5241:	dup
   5242:	sipush	239
   5245:	ldc_w	#500; //int -542803233
   5248:	iastore
   5249:	dup
   5250:	sipush	240
   5253:	ldc_w	#501; //int -1945923700
   5256:	iastore
   5257:	dup
   5258:	sipush	241
   5261:	ldc_w	#502; //int -1587939167
   5264:	iastore
   5265:	dup
   5266:	sipush	242
   5269:	ldc_w	#503; //int -1995865975
   5272:	iastore
   5273:	dup
   5274:	sipush	243
   5277:	ldc_w	#504; //int 219813645
   5280:	iastore
   5281:	dup
   5282:	sipush	244
   5285:	ldc_w	#505; //int -1083843905
   5288:	iastore
   5289:	dup
   5290:	sipush	245
   5293:	ldc_w	#506; //int -422104602
   5296:	iastore
   5297:	dup
   5298:	sipush	246
   5301:	ldc_w	#507; //int 1115997762
   5304:	iastore
   5305:	dup
   5306:	sipush	247
   5309:	ldc_w	#508; //int 1758509160
   5312:	iastore
   5313:	dup
   5314:	sipush	248
   5317:	ldc_w	#509; //int 1099088705
   5320:	iastore
   5321:	dup
   5322:	sipush	249
   5325:	ldc_w	#510; //int -1725321063
   5328:	iastore
   5329:	dup
   5330:	sipush	250
   5333:	ldc_w	#511; //int 760903469
   5336:	iastore
   5337:	dup
   5338:	sipush	251
   5341:	ldc_w	#512; //int 253628687
   5344:	iastore
   5345:	dup
   5346:	sipush	252
   5349:	ldc_w	#513; //int -1334064208
   5352:	iastore
   5353:	dup
   5354:	sipush	253
   5357:	ldc_w	#514; //int 1420360788
   5360:	iastore
   5361:	dup
   5362:	sipush	254
   5365:	ldc_w	#515; //int -1150429509
   5368:	iastore
   5369:	dup
   5370:	sipush	255
   5373:	ldc_w	#516; //int 371997206
   5376:	iastore
   5377:	putstatic	#5; //Field gtable2:[I
   5380:	sipush	256
   5383:	newarray int
   5385:	dup
   5386:	iconst_0
   5387:	ldc_w	#517; //int -1520213050
   5390:	iastore
   5391:	dup
   5392:	iconst_1
   5393:	ldc_w	#518; //int -2072216328
   5396:	iastore
   5397:	dup
   5398:	iconst_2
   5399:	ldc_w	#519; //int -1720223762
   5402:	iastore
   5403:	dup
   5404:	iconst_3
   5405:	ldc_w	#520; //int -1921287178
   5408:	iastore
   5409:	dup
   5410:	iconst_4
   5411:	ldc_w	#521; //int 234025727
   5414:	iastore
   5415:	dup
   5416:	iconst_5
   5417:	ldc_w	#522; //int -1117033514
   5420:	iastore
   5421:	dup
   5422:	bipush	6
   5424:	ldc_w	#523; //int -1318096930
   5427:	iastore
   5428:	dup
   5429:	bipush	7
   5431:	ldc_w	#524; //int 1422247313
   5434:	iastore
   5435:	dup
   5436:	bipush	8
   5438:	ldc_w	#525; //int 1345335392
   5441:	iastore
   5442:	dup
   5443:	bipush	9
   5445:	ldc_w	#526; //int 50397442
   5448:	iastore
   5449:	dup
   5450:	bipush	10
   5452:	ldc_w	#527; //int -1452841010
   5455:	iastore
   5456:	dup
   5457:	bipush	11
   5459:	ldc_w	#528; //int 2099981142
   5462:	iastore
   5463:	dup
   5464:	bipush	12
   5466:	ldc_w	#529; //int 436141799
   5469:	iastore
   5470:	dup
   5471:	bipush	13
   5473:	ldc_w	#530; //int 1658312629
   5476:	iastore
   5477:	dup
   5478:	bipush	14
   5480:	ldc_w	#531; //int -424957107
   5483:	iastore
   5484:	dup
   5485:	bipush	15
   5487:	ldc_w	#532; //int -1703512340
   5490:	iastore
   5491:	dup
   5492:	bipush	16
   5494:	ldc_w	#533; //int 1170918031
   5497:	iastore
   5498:	dup
   5499:	bipush	17
   5501:	ldc_w	#534; //int -1652391393
   5504:	iastore
   5505:	dup
   5506:	bipush	18
   5508:	ldc_w	#535; //int 1086966153
   5511:	iastore
   5512:	dup
   5513:	bipush	19
   5515:	ldc_w	#536; //int -2021818886
   5518:	iastore
   5519:	dup
   5520:	bipush	20
   5522:	ldc_w	#537; //int 368769775
   5525:	iastore
   5526:	dup
   5527:	bipush	21
   5529:	ldc_w	#538; //int -346465870
   5532:	iastore
   5533:	dup
   5534:	bipush	22
   5536:	ldc_w	#539; //int -918075506
   5539:	iastore
   5540:	dup
   5541:	bipush	23
   5543:	ldc_w	#540; //int 200339707
   5546:	iastore
   5547:	dup
   5548:	bipush	24
   5550:	ldc_w	#541; //int -324162239
   5553:	iastore
   5554:	dup
   5555:	bipush	25
   5557:	ldc_w	#542; //int 1742001331
   5560:	iastore
   5561:	dup
   5562:	bipush	26
   5564:	ldc_w	#543; //int -39673249
   5567:	iastore
   5568:	dup
   5569:	bipush	27
   5571:	ldc_w	#544; //int -357585083
   5574:	iastore
   5575:	dup
   5576:	bipush	28
   5578:	ldc_w	#545; //int -1080255453
   5581:	iastore
   5582:	dup
   5583:	bipush	29
   5585:	ldc_w	#546; //int -140204973
   5588:	iastore
   5589:	dup
   5590:	bipush	30
   5592:	ldc_w	#547; //int -1770884380
   5595:	iastore
   5596:	dup
   5597:	bipush	31
   5599:	ldc_w	#548; //int 1539358875
   5602:	iastore
   5603:	dup
   5604:	bipush	32
   5606:	ldc_w	#549; //int -1028147339
   5609:	iastore
   5610:	dup
   5611:	bipush	33
   5613:	ldc_w	#550; //int 486407649
   5616:	iastore
   5617:	dup
   5618:	bipush	34
   5620:	ldc_w	#551; //int -1366060227
   5623:	iastore
   5624:	dup
   5625:	bipush	35
   5627:	ldc_w	#552; //int 1780885068
   5630:	iastore
   5631:	dup
   5632:	bipush	36
   5634:	ldc_w	#553; //int 1513502316
   5637:	iastore
   5638:	dup
   5639:	bipush	37
   5641:	ldc_w	#554; //int 1094664062
   5644:	iastore
   5645:	dup
   5646:	bipush	38
   5648:	ldc_w	#555; //int 49805301
   5651:	iastore
   5652:	dup
   5653:	bipush	39
   5655:	ldc_w	#556; //int 1338821763
   5658:	iastore
   5659:	dup
   5660:	bipush	40
   5662:	ldc_w	#557; //int 1546925160
   5665:	iastore
   5666:	dup
   5667:	bipush	41
   5669:	ldc_w	#558; //int -190470831
   5672:	iastore
   5673:	dup
   5674:	bipush	42
   5676:	ldc_w	#559; //int 887481809
   5679:	iastore
   5680:	dup
   5681:	bipush	43
   5683:	ldc_w	#560; //int 150073849
   5686:	iastore
   5687:	dup
   5688:	bipush	44
   5690:	ldc_w	#561; //int -1821281822
   5693:	iastore
   5694:	dup
   5695:	bipush	45
   5697:	ldc_w	#562; //int 1943591083
   5700:	iastore
   5701:	dup
   5702:	bipush	46
   5704:	ldc_w	#563; //int 1395732834
   5707:	iastore
   5708:	dup
   5709:	bipush	47
   5711:	ldc_w	#564; //int 1058346282
   5714:	iastore
   5715:	dup
   5716:	bipush	48
   5718:	ldc_w	#565; //int 201589768
   5721:	iastore
   5722:	dup
   5723:	bipush	49
   5725:	ldc_w	#566; //int 1388824469
   5728:	iastore
   5729:	dup
   5730:	bipush	50
   5732:	ldc_w	#567; //int 1696801606
   5735:	iastore
   5736:	dup
   5737:	bipush	51
   5739:	ldc_w	#568; //int 1589887901
   5742:	iastore
   5743:	dup
   5744:	bipush	52
   5746:	ldc_w	#569; //int 672667696
   5749:	iastore
   5750:	dup
   5751:	bipush	53
   5753:	ldc_w	#570; //int -1583966665
   5756:	iastore
   5757:	dup
   5758:	bipush	54
   5760:	ldc_w	#571; //int 251987210
   5763:	iastore
   5764:	dup
   5765:	bipush	55
   5767:	ldc_w	#572; //int -1248159185
   5770:	iastore
   5771:	dup
   5772:	bipush	56
   5774:	ldc_w	#573; //int 151455502
   5777:	iastore
   5778:	dup
   5779:	bipush	57
   5781:	ldc_w	#574; //int 907153956
   5784:	iastore
   5785:	dup
   5786:	bipush	58
   5788:	ldc_w	#575; //int -1686077413
   5791:	iastore
   5792:	dup
   5793:	bipush	59
   5795:	ldc_w	#576; //int 1038279391
   5798:	iastore
   5799:	dup
   5800:	bipush	60
   5802:	ldc_w	#577; //int 652995533
   5805:	iastore
   5806:	dup
   5807:	bipush	61
   5809:	ldc_w	#578; //int 1764173646
   5812:	iastore
   5813:	dup
   5814:	bipush	62
   5816:	ldc_w	#579; //int -843926913
   5819:	iastore
   5820:	dup
   5821:	bipush	63
   5823:	ldc_w	#580; //int -1619692054
   5826:	iastore
   5827:	dup
   5828:	bipush	64
   5830:	ldc_w	#581; //int 453576978
   5833:	iastore
   5834:	dup
   5835:	bipush	65
   5837:	ldc_w	#582; //int -1635548387
   5840:	iastore
   5841:	dup
   5842:	bipush	66
   5844:	ldc_w	#583; //int 1949051992
   5847:	iastore
   5848:	dup
   5849:	bipush	67
   5851:	ldc_w	#584; //int 773462580
   5854:	iastore
   5855:	dup
   5856:	bipush	68
   5858:	ldc_w	#585; //int 756751158
   5861:	iastore
   5862:	dup
   5863:	bipush	69
   5865:	ldc_w	#586; //int -1301385508
   5868:	iastore
   5869:	dup
   5870:	bipush	70
   5872:	ldc_w	#587; //int -296068428
   5875:	iastore
   5876:	dup
   5877:	bipush	71
   5879:	ldc_w	#588; //int -73359269
   5882:	iastore
   5883:	dup
   5884:	bipush	72
   5886:	ldc_w	#589; //int -162377052
   5889:	iastore
   5890:	dup
   5891:	bipush	73
   5893:	ldc_w	#590; //int 1295727478
   5896:	iastore
   5897:	dup
   5898:	bipush	74
   5900:	ldc_w	#591; //int 1641469623
   5903:	iastore
   5904:	dup
   5905:	bipush	75
   5907:	ldc_w	#592; //int -827083907
   5910:	iastore
   5911:	dup
   5912:	bipush	76
   5914:	ldc_w	#593; //int 2066295122
   5917:	iastore
   5918:	dup
   5919:	bipush	77
   5921:	ldc_w	#594; //int 1055122397
   5924:	iastore
   5925:	dup
   5926:	bipush	78
   5928:	ldc_w	#595; //int 1898917726
   5931:	iastore
   5932:	dup
   5933:	bipush	79
   5935:	ldc_w	#596; //int -1752923117
   5938:	iastore
   5939:	dup
   5940:	bipush	80
   5942:	ldc_w	#597; //int -179088474
   5945:	iastore
   5946:	dup
   5947:	bipush	81
   5949:	ldc_w	#598; //int 1758581177
   5952:	iastore
   5953:	dup
   5954:	bipush	82
   5956:	iconst_0
   5957:	iastore
   5958:	dup
   5959:	bipush	83
   5961:	ldc_w	#599; //int 753790401
   5964:	iastore
   5965:	dup
   5966:	bipush	84
   5968:	ldc_w	#600; //int 1612718144
   5971:	iastore
   5972:	dup
   5973:	bipush	85
   5975:	ldc_w	#601; //int 536673507
   5978:	iastore
   5979:	dup
   5980:	bipush	86
   5982:	ldc_w	#602; //int -927878791
   5985:	iastore
   5986:	dup
   5987:	bipush	87
   5989:	ldc_w	#603; //int -312779850
   5992:	iastore
   5993:	dup
   5994:	bipush	88
   5996:	ldc_w	#604; //int -1100322092
   5999:	iastore
   6000:	dup
   6001:	bipush	89
   6003:	ldc_w	#605; //int 1187761037
   6006:	iastore
   6007:	dup
   6008:	bipush	90
   6010:	ldc_w	#606; //int -641810841
   6013:	iastore
   6014:	dup
   6015:	bipush	91
   6017:	ldc_w	#607; //int 1262041458
   6020:	iastore
   6021:	dup
   6022:	bipush	92
   6024:	ldc_w	#608; //int -565556588
   6027:	iastore
   6028:	dup
   6029:	bipush	93
   6031:	ldc_w	#609; //int -733197160
   6034:	iastore
   6035:	dup
   6036:	bipush	94
   6038:	ldc_w	#610; //int -396863312
   6041:	iastore
   6042:	dup
   6043:	bipush	95
   6045:	ldc_w	#611; //int 1255133061
   6048:	iastore
   6049:	dup
   6050:	bipush	96
   6052:	ldc_w	#612; //int 1808847035
   6055:	iastore
   6056:	dup
   6057:	bipush	97
   6059:	ldc_w	#613; //int 720367557
   6062:	iastore
   6063:	dup
   6064:	bipush	98
   6066:	ldc_w	#614; //int -441800113
   6069:	iastore
   6070:	dup
   6071:	bipush	99
   6073:	ldc_w	#615; //int 385612781
   6076:	iastore
   6077:	dup
   6078:	bipush	100
   6080:	ldc_w	#616; //int -985447546
   6083:	iastore
   6084:	dup
   6085:	bipush	101
   6087:	ldc_w	#617; //int -682799718
   6090:	iastore
   6091:	dup
   6092:	bipush	102
   6094:	ldc_w	#618; //int 1429418854
   6097:	iastore
   6098:	dup
   6099:	bipush	103
   6101:	ldc_w	#619; //int -1803188975
   6104:	iastore
   6105:	dup
   6106:	bipush	104
   6108:	ldc_w	#620; //int -817543798
   6111:	iastore
   6112:	dup
   6113:	bipush	105
   6115:	ldc_w	#621; //int 284817897
   6118:	iastore
   6119:	dup
   6120:	bipush	106
   6122:	ldc_w	#622; //int 100794884
   6125:	iastore
   6126:	dup
   6127:	bipush	107
   6129:	ldc_w	#623; //int -2122350594
   6132:	iastore
   6133:	dup
   6134:	bipush	108
   6136:	ldc_w	#624; //int -263171936
   6139:	iastore
   6140:	dup
   6141:	bipush	109
   6143:	ldc_w	#625; //int 1144798328
   6146:	iastore
   6147:	dup
   6148:	bipush	110
   6150:	ldc_w	#626; //int -1163944155
   6153:	iastore
   6154:	dup
   6155:	bipush	111
   6157:	ldc_w	#627; //int -475486133
   6160:	iastore
   6161:	dup
   6162:	bipush	112
   6164:	ldc_w	#628; //int -212774494
   6167:	iastore
   6168:	dup
   6169:	bipush	113
   6171:	ldc_w	#629; //int -22830243
   6174:	iastore
   6175:	dup
   6176:	bipush	114
   6178:	ldc_w	#630; //int -1069531008
   6181:	iastore
   6182:	dup
   6183:	bipush	115
   6185:	ldc_w	#631; //int -1970303227
   6188:	iastore
   6189:	dup
   6190:	bipush	116
   6192:	ldc_w	#632; //int -1382903233
   6195:	iastore
   6196:	dup
   6197:	bipush	117
   6199:	ldc_w	#633; //int -1130521311
   6202:	iastore
   6203:	dup
   6204:	bipush	118
   6206:	ldc_w	#634; //int 1211644016
   6209:	iastore
   6210:	dup
   6211:	bipush	119
   6213:	ldc_w	#635; //int 83228145
   6216:	iastore
   6217:	dup
   6218:	bipush	120
   6220:	ldc_w	#636; //int -541279133
   6223:	iastore
   6224:	dup
   6225:	bipush	121
   6227:	ldc_w	#637; //int -1044990345
   6230:	iastore
   6231:	dup
   6232:	bipush	122
   6234:	ldc_w	#638; //int 1977277103
   6237:	iastore
   6238:	dup
   6239:	bipush	123
   6241:	ldc_w	#639; //int 1663115586
   6244:	iastore
   6245:	dup
   6246:	bipush	124
   6248:	ldc_w	#640; //int 806359072
   6251:	iastore
   6252:	dup
   6253:	bipush	125
   6255:	ldc_w	#641; //int 452984805
   6258:	iastore
   6259:	dup
   6260:	bipush	126
   6262:	ldc_w	#642; //int 250868733
   6265:	iastore
   6266:	dup
   6267:	bipush	127
   6269:	ldc_w	#643; //int 1842533055
   6272:	iastore
   6273:	dup
   6274:	sipush	128
   6277:	ldc_w	#644; //int 1288555905
   6280:	iastore
   6281:	dup
   6282:	sipush	129
   6285:	ldc_w	#645; //int 336333848
   6288:	iastore
   6289:	dup
   6290:	sipush	130
   6293:	ldc_w	#646; //int 890442534
   6296:	iastore
   6297:	dup
   6298:	sipush	131
   6301:	ldc_w	#647; //int 804056259
   6304:	iastore
   6305:	dup
   6306:	sipush	132
   6309:	ldc_w	#648; //int -513843266
   6312:	iastore
   6313:	dup
   6314:	sipush	133
   6317:	ldc_w	#649; //int -1567123659
   6320:	iastore
   6321:	dup
   6322:	sipush	134
   6325:	ldc_w	#650; //int -867941240
   6328:	iastore
   6329:	dup
   6330:	sipush	135
   6333:	ldc_w	#651; //int 957814574
   6336:	iastore
   6337:	dup
   6338:	sipush	136
   6341:	ldc_w	#652; //int 1472513171
   6344:	iastore
   6345:	dup
   6346:	sipush	137
   6349:	ldc_w	#653; //int -223893675
   6352:	iastore
   6353:	dup
   6354:	sipush	138
   6357:	ldc_w	#654; //int -2105639172
   6360:	iastore
   6361:	dup
   6362:	sipush	139
   6365:	ldc_w	#655; //int 1195195770
   6368:	iastore
   6369:	dup
   6370:	sipush	140
   6373:	ldc_w	#656; //int -1402706744
   6376:	iastore
   6377:	dup
   6378:	sipush	141
   6381:	ldc_w	#657; //int -413311558
   6384:	iastore
   6385:	dup
   6386:	sipush	142
   6389:	ldc_w	#658; //int 723065138
   6392:	iastore
   6393:	dup
   6394:	sipush	143
   6397:	ldc_w	#659; //int -1787595802
   6400:	iastore
   6401:	dup
   6402:	sipush	144
   6405:	ldc_w	#660; //int -1604296512
   6408:	iastore
   6409:	dup
   6410:	sipush	145
   6413:	ldc_w	#661; //int -1736343271
   6416:	iastore
   6417:	dup
   6418:	sipush	146
   6421:	ldc_w	#662; //int -783331426
   6424:	iastore
   6425:	dup
   6426:	sipush	147
   6429:	ldc_w	#663; //int 2145180835
   6432:	iastore
   6433:	dup
   6434:	sipush	148
   6437:	ldc_w	#664; //int 1713513028
   6440:	iastore
   6441:	dup
   6442:	sipush	149
   6445:	ldc_w	#665; //int 2116692564
   6448:	iastore
   6449:	dup
   6450:	sipush	150
   6453:	ldc_w	#666; //int -1416589253
   6456:	iastore
   6457:	dup
   6458:	sipush	151
   6461:	ldc_w	#667; //int -2088204277
   6464:	iastore
   6465:	dup
   6466:	sipush	152
   6469:	ldc_w	#668; //int -901364084
   6472:	iastore
   6473:	dup
   6474:	sipush	153
   6477:	ldc_w	#669; //int 703524551
   6480:	iastore
   6481:	dup
   6482:	sipush	154
   6485:	ldc_w	#670; //int -742868885
   6488:	iastore
   6489:	dup
   6490:	sipush	155
   6493:	ldc_w	#671; //int 1007948840
   6496:	iastore
   6497:	dup
   6498:	sipush	156
   6501:	ldc_w	#672; //int 2044649127
   6504:	iastore
   6505:	dup
   6506:	sipush	157
   6509:	ldc_w	#673; //int -497131844
   6512:	iastore
   6513:	dup
   6514:	sipush	158
   6517:	ldc_w	#674; //int 487262998
   6520:	iastore
   6521:	dup
   6522:	sipush	159
   6525:	ldc_w	#675; //int 1994120109
   6528:	iastore
   6529:	dup
   6530:	sipush	160
   6533:	ldc_w	#676; //int 1004593371
   6536:	iastore
   6537:	dup
   6538:	sipush	161
   6541:	ldc_w	#677; //int 1446130276
   6544:	iastore
   6545:	dup
   6546:	sipush	162
   6549:	ldc_w	#678; //int 1312438900
   6552:	iastore
   6553:	dup
   6554:	sipush	163
   6557:	ldc_w	#679; //int 503974420
   6560:	iastore
   6561:	dup
   6562:	sipush	164
   6565:	ldc_w	#680; //int -615954030
   6568:	iastore
   6569:	dup
   6570:	sipush	165
   6573:	ldc_w	#681; //int 168166924
   6576:	iastore
   6577:	dup
   6578:	sipush	166
   6581:	ldc_w	#682; //int 1814307912
   6584:	iastore
   6585:	dup
   6586:	sipush	167
   6589:	ldc_w	#683; //int -463709000
   6592:	iastore
   6593:	dup
   6594:	sipush	168
   6597:	ldc_w	#684; //int 1573044895
   6600:	iastore
   6601:	dup
   6602:	sipush	169
   6605:	ldc_w	#685; //int 1859376061
   6608:	iastore
   6609:	dup
   6610:	sipush	170
   6613:	ldc_w	#686; //int -273896381
   6616:	iastore
   6617:	dup
   6618:	sipush	171
   6621:	ldc_w	#687; //int -1503501628
   6624:	iastore
   6625:	dup
   6626:	sipush	172
   6629:	ldc_w	#688; //int -1466855111
   6632:	iastore
   6633:	dup
   6634:	sipush	173
   6637:	ldc_w	#689; //int -1533700815
   6640:	iastore
   6641:	dup
   6642:	sipush	174
   6645:	ldc_w	#690; //int 937747667
   6648:	iastore
   6649:	dup
   6650:	sipush	175
   6653:	ldc_w	#691; //int -1954973198
   6656:	iastore
   6657:	dup
   6658:	sipush	176
   6661:	ldc_w	#692; //int 854058965
   6664:	iastore
   6665:	dup
   6666:	sipush	177
   6669:	ldc_w	#693; //int 1137232011
   6672:	iastore
   6673:	dup
   6674:	sipush	178
   6677:	ldc_w	#694; //int 1496790894
   6680:	iastore
   6681:	dup
   6682:	sipush	179
   6685:	ldc_w	#695; //int -1217565222
   6688:	iastore
   6689:	dup
   6690:	sipush	180
   6693:	ldc_w	#696; //int -1936880383
   6696:	iastore
   6697:	dup
   6698:	sipush	181
   6701:	ldc_w	#697; //int 1691735473
   6704:	iastore
   6705:	dup
   6706:	sipush	182
   6709:	ldc_w	#698; //int -766620004
   6712:	iastore
   6713:	dup
   6714:	sipush	183
   6717:	ldc_w	#699; //int -525751991
   6720:	iastore
   6721:	dup
   6722:	sipush	184
   6725:	ldc_w	#700; //int -1267962664
   6728:	iastore
   6729:	dup
   6730:	sipush	185
   6733:	ldc_w	#701; //int -95005012
   6736:	iastore
   6737:	dup
   6738:	sipush	186
   6741:	ldc_w	#702; //int 133494003
   6744:	iastore
   6745:	dup
   6746:	sipush	187
   6749:	ldc_w	#703; //int 636152527
   6752:	iastore
   6753:	dup
   6754:	sipush	188
   6757:	ldc_w	#704; //int -1352309302
   6760:	iastore
   6761:	dup
   6762:	sipush	189
   6765:	ldc_w	#705; //int -1904575756
   6768:	iastore
   6769:	dup
   6770:	sipush	190
   6773:	ldc_w	#706; //int -374428089
   6776:	iastore
   6777:	dup
   6778:	sipush	191
   6781:	ldc_w	#707; //int 403179536
   6784:	iastore
   6785:	dup
   6786:	sipush	192
   6789:	ldc_w	#708; //int -709182865
   6792:	iastore
   6793:	dup
   6794:	sipush	193
   6797:	ldc_w	#709; //int -2005370640
   6800:	iastore
   6801:	dup
   6802:	sipush	194
   6805:	ldc_w	#710; //int 1864705354
   6808:	iastore
   6809:	dup
   6810:	sipush	195
   6813:	ldc_w	#711; //int 1915629148
   6816:	iastore
   6817:	dup
   6818:	sipush	196
   6821:	ldc_w	#712; //int 605822008
   6824:	iastore
   6825:	dup
   6826:	sipush	197
   6829:	ldc_w	#713; //int -240736681
   6832:	iastore
   6833:	dup
   6834:	sipush	198
   6837:	ldc_w	#714; //int -944458637
   6840:	iastore
   6841:	dup
   6842:	sipush	199
   6845:	ldc_w	#715; //int 1371981463
   6848:	iastore
   6849:	dup
   6850:	sipush	200
   6853:	ldc_w	#716; //int 602466507
   6856:	iastore
   6857:	dup
   6858:	sipush	201
   6861:	ldc_w	#717; //int 2094914977
   6864:	iastore
   6865:	dup
   6866:	sipush	202
   6869:	ldc_w	#718; //int -1670089496
   6872:	iastore
   6873:	dup
   6874:	sipush	203
   6877:	ldc_w	#719; //int 555687742
   6880:	iastore
   6881:	dup
   6882:	sipush	204
   6885:	ldc_w	#720; //int -582268010
   6888:	iastore
   6889:	dup
   6890:	sipush	205
   6893:	ldc_w	#721; //int -591544991
   6896:	iastore
   6897:	dup
   6898:	sipush	206
   6901:	ldc_w	#722; //int -2037675251
   6904:	iastore
   6905:	dup
   6906:	sipush	207
   6909:	ldc_w	#723; //int -2054518257
   6912:	iastore
   6913:	dup
   6914:	sipush	208
   6917:	ldc_w	#724; //int -1871679264
   6920:	iastore
   6921:	dup
   6922:	sipush	209
   6925:	ldc_w	#725; //int 1111375484
   6928:	iastore
   6929:	dup
   6930:	sipush	210
   6933:	ldc_w	#726; //int -994724495
   6936:	iastore
   6937:	dup
   6938:	sipush	211
   6941:	ldc_w	#727; //int -1436129588
   6944:	iastore
   6945:	dup
   6946:	sipush	212
   6949:	ldc_w	#728; //int -666351472
   6952:	iastore
   6953:	dup
   6954:	sipush	213
   6957:	ldc_w	#729; //int 84083462
   6960:	iastore
   6961:	dup
   6962:	sipush	214
   6965:	ldc_w	#730; //int 32962295
   6968:	iastore
   6969:	dup
   6970:	sipush	215
   6973:	ldc_w	#731; //int 302911004
   6976:	iastore
   6977:	dup
   6978:	sipush	216
   6981:	ldc_w	#732; //int -1553899070
   6984:	iastore
   6985:	dup
   6986:	sipush	217
   6989:	ldc_w	#733; //int 1597322602
   6992:	iastore
   6993:	dup
   6994:	sipush	218
   6997:	ldc_w	#734; //int -111716434
   7000:	iastore
   7001:	dup
   7002:	sipush	219
   7005:	ldc_w	#735; //int -793134743
   7008:	iastore
   7009:	dup
   7010:	sipush	220
   7013:	ldc_w	#736; //int -1853454825
   7016:	iastore
   7017:	dup
   7018:	sipush	221
   7021:	ldc_w	#737; //int 1489093017
   7024:	iastore
   7025:	dup
   7026:	sipush	222
   7029:	ldc_w	#738; //int 656219450
   7032:	iastore
   7033:	dup
   7034:	sipush	223
   7037:	ldc_w	#739; //int -1180787161
   7040:	iastore
   7041:	dup
   7042:	sipush	224
   7045:	ldc_w	#740; //int 954327513
   7048:	iastore
   7049:	dup
   7050:	sipush	225
   7053:	ldc_w	#741; //int 335083755
   7056:	iastore
   7057:	dup
   7058:	sipush	226
   7061:	ldc_w	#742; //int -1281845205
   7064:	iastore
   7065:	dup
   7066:	sipush	227
   7069:	ldc_w	#743; //int 856756514
   7072:	iastore
   7073:	dup
   7074:	sipush	228
   7077:	ldc_w	#744; //int -1150719534
   7080:	iastore
   7081:	dup
   7082:	sipush	229
   7085:	ldc_w	#745; //int 1893325225
   7088:	iastore
   7089:	dup
   7090:	sipush	230
   7093:	ldc_w	#746; //int -1987146233
   7096:	iastore
   7097:	dup
   7098:	sipush	231
   7101:	ldc_w	#747; //int -1483434957
   7104:	iastore
   7105:	dup
   7106:	sipush	232
   7109:	ldc_w	#748; //int -1231316179
   7112:	iastore
   7113:	dup
   7114:	sipush	233
   7117:	ldc_w	#749; //int 572399164
   7120:	iastore
   7121:	dup
   7122:	sipush	234
   7125:	ldc_w	#750; //int -1836611819
   7128:	iastore
   7129:	dup
   7130:	sipush	235
   7133:	ldc_w	#751; //int 552200649
   7136:	iastore
   7137:	dup
   7138:	sipush	236
   7141:	ldc_w	#752; //int 1238290055
   7144:	iastore
   7145:	dup
   7146:	sipush	237
   7149:	ldc_w	#753; //int -11184726
   7152:	iastore
   7153:	dup
   7154:	sipush	238
   7157:	ldc_w	#754; //int 2015897680
   7160:	iastore
   7161:	dup
   7162:	sipush	239
   7165:	ldc_w	#755; //int 2061492133
   7168:	iastore
   7169:	dup
   7170:	sipush	240
   7173:	ldc_w	#756; //int -1886614525
   7176:	iastore
   7177:	dup
   7178:	sipush	241
   7181:	ldc_w	#757; //int -123625127
   7184:	iastore
   7185:	dup
   7186:	sipush	242
   7189:	ldc_w	#758; //int -2138470135
   7192:	iastore
   7193:	dup
   7194:	sipush	243
   7197:	ldc_w	#759; //int 386731290
   7200:	iastore
   7201:	dup
   7202:	sipush	244
   7205:	ldc_w	#760; //int -624967835
   7208:	iastore
   7209:	dup
   7210:	sipush	245
   7213:	ldc_w	#761; //int 837215959
   7216:	iastore
   7217:	dup
   7218:	sipush	246
   7221:	ldc_w	#762; //int -968736124
   7224:	iastore
   7225:	dup
   7226:	sipush	247
   7229:	ldc_w	#763; //int -1201116976
   7232:	iastore
   7233:	dup
   7234:	sipush	248
   7237:	ldc_w	#764; //int -1019133566
   7240:	iastore
   7241:	dup
   7242:	sipush	249
   7245:	ldc_w	#765; //int -1332111063
   7248:	iastore
   7249:	dup
   7250:	sipush	250
   7253:	ldc_w	#766; //int 1999449434
   7256:	iastore
   7257:	dup
   7258:	sipush	251
   7261:	ldc_w	#767; //int 286199582
   7264:	iastore
   7265:	dup
   7266:	sipush	252
   7269:	ldc_w	#768; //int -877612933
   7272:	iastore
   7273:	dup
   7274:	sipush	253
   7277:	ldc_w	#769; //int -61582168
   7280:	iastore
   7281:	dup
   7282:	sipush	254
   7285:	ldc_w	#770; //int -692339859
   7288:	iastore
   7289:	dup
   7290:	sipush	255
   7293:	ldc_w	#771; //int 974525996
   7296:	iastore
   7297:	putstatic	#3; //Field gtable0:[I
   7300:	sipush	256
   7303:	newarray int
   7305:	dup
   7306:	iconst_0
   7307:	ldc_w	#772; //int -962239645
   7310:	iastore
   7311:	dup
   7312:	iconst_1
   7313:	ldc_w	#773; //int -125535108
   7316:	iastore
   7317:	dup
   7318:	iconst_2
   7319:	ldc_w	#774; //int -291932297
   7322:	iastore
   7323:	dup
   7324:	iconst_3
   7325:	ldc_w	#775; //int -158499973
   7328:	iastore
   7329:	dup
   7330:	iconst_4
   7331:	ldc_w	#776; //int -15863054
   7334:	iastore
   7335:	dup
   7336:	iconst_5
   7337:	ldc_w	#777; //int -692229269
   7340:	iastore
   7341:	dup
   7342:	bipush	6
   7344:	ldc_w	#778; //int -558796945
   7347:	iastore
   7348:	dup
   7349:	bipush	7
   7351:	ldc_w	#779; //int -1856715323
   7354:	iastore
   7355:	dup
   7356:	bipush	8
   7358:	ldc_w	#780; //int 1615867952
   7361:	iastore
   7362:	dup
   7363:	bipush	9
   7365:	ldc_w	#781; //int 33751297
   7368:	iastore
   7369:	dup
   7370:	bipush	10
   7372:	ldc_w	#782; //int -827758745
   7375:	iastore
   7376:	dup
   7377:	bipush	11
   7379:	ldc_w	#783; //int 1451043627
   7382:	iastore
   7383:	dup
   7384:	bipush	12
   7386:	ldc_w	#784; //int -417726722
   7389:	iastore
   7390:	dup
   7391:	bipush	13
   7393:	ldc_w	#785; //int -1251813417
   7396:	iastore
   7397:	dup
   7398:	bipush	14
   7400:	ldc_w	#786; //int 1306962859
   7403:	iastore
   7404:	dup
   7405:	bipush	15
   7407:	ldc_w	#787; //int -325421450
   7410:	iastore
   7411:	dup
   7412:	bipush	16
   7414:	ldc_w	#788; //int -1891251510
   7417:	iastore
   7418:	dup
   7419:	bipush	17
   7421:	ldc_w	#789; //int 530416258
   7424:	iastore
   7425:	dup
   7426:	bipush	18
   7428:	ldc_w	#790; //int -1992242743
   7431:	iastore
   7432:	dup
   7433:	bipush	19
   7435:	ldc_w	#791; //int -91783811
   7438:	iastore
   7439:	dup
   7440:	bipush	20
   7442:	ldc_w	#792; //int -283772166
   7445:	iastore
   7446:	dup
   7447:	bipush	21
   7449:	ldc_w	#793; //int -1293199015
   7452:	iastore
   7453:	dup
   7454:	bipush	22
   7456:	ldc_w	#794; //int -1899411641
   7459:	iastore
   7460:	dup
   7461:	bipush	23
   7463:	ldc_w	#795; //int -83103504
   7466:	iastore
   7467:	dup
   7468:	bipush	24
   7470:	ldc_w	#796; //int 1106029997
   7473:	iastore
   7474:	dup
   7475:	bipush	25
   7477:	ldc_w	#797; //int -1285040940
   7480:	iastore
   7481:	dup
   7482:	bipush	26
   7484:	ldc_w	#798; //int 1610457762
   7487:	iastore
   7488:	dup
   7489:	bipush	27
   7491:	ldc_w	#799; //int 1173008303
   7494:	iastore
   7495:	dup
   7496:	bipush	28
   7498:	ldc_w	#800; //int 599760028
   7501:	iastore
   7502:	dup
   7503:	bipush	29
   7505:	ldc_w	#801; //int 1408738468
   7508:	iastore
   7509:	dup
   7510:	bipush	30
   7512:	ldc_w	#802; //int -459902350
   7515:	iastore
   7516:	dup
   7517:	bipush	31
   7519:	ldc_w	#803; //int -1688485696
   7522:	iastore
   7523:	dup
   7524:	bipush	32
   7526:	ldc_w	#804; //int 1975695287
   7529:	iastore
   7530:	dup
   7531:	bipush	33
   7533:	ldc_w	#805; //int -518193667
   7536:	iastore
   7537:	dup
   7538:	bipush	34
   7540:	ldc_w	#806; //int 1034851219
   7543:	iastore
   7544:	dup
   7545:	bipush	35
   7547:	ldc_w	#807; //int 1282024998
   7550:	iastore
   7551:	dup
   7552:	bipush	36
   7554:	ldc_w	#808; //int 1817851446
   7557:	iastore
   7558:	dup
   7559:	bipush	37
   7561:	ldc_w	#809; //int 2118205247
   7564:	iastore
   7565:	dup
   7566:	bipush	38
   7568:	ldc_w	#810; //int -184354825
   7571:	iastore
   7572:	dup
   7573:	bipush	39
   7575:	ldc_w	#811; //int -2091922228
   7578:	iastore
   7579:	dup
   7580:	bipush	40
   7582:	ldc_w	#812; //int 1750873140
   7585:	iastore
   7586:	dup
   7587:	bipush	41
   7589:	ldc_w	#813; //int 1374987685
   7592:	iastore
   7593:	dup
   7594:	bipush	42
   7596:	ldc_w	#814; //int -785062427
   7599:	iastore
   7600:	dup
   7601:	bipush	43
   7603:	ldc_w	#815; //int -116854287
   7606:	iastore
   7607:	dup
   7608:	bipush	44
   7610:	ldc_w	#816; //int -493653647
   7613:	iastore
   7614:	dup
   7615:	bipush	45
   7617:	ldc_w	#817; //int -1418471208
   7620:	iastore
   7621:	dup
   7622:	bipush	46
   7624:	ldc_w	#818; //int 1649619249
   7627:	iastore
   7628:	dup
   7629:	bipush	47
   7631:	ldc_w	#819; //int 708777237
   7634:	iastore
   7635:	dup
   7636:	bipush	48
   7638:	ldc_w	#820; //int 135005188
   7641:	iastore
   7642:	dup
   7643:	bipush	49
   7645:	ldc_w	#821; //int -1789737017
   7648:	iastore
   7649:	dup
   7650:	bipush	50
   7652:	ldc_w	#822; //int 1181033251
   7655:	iastore
   7656:	dup
   7657:	bipush	51
   7659:	ldc_w	#823; //int -1654733885
   7662:	iastore
   7663:	dup
   7664:	bipush	52
   7666:	ldc_w	#824; //int 807933976
   7669:	iastore
   7670:	dup
   7671:	bipush	53
   7673:	ldc_w	#825; //int 933336726
   7676:	iastore
   7677:	dup
   7678:	bipush	54
   7680:	ldc_w	#826; //int 168756485
   7683:	iastore
   7684:	dup
   7685:	bipush	55
   7687:	ldc_w	#827; //int 800430746
   7690:	iastore
   7691:	dup
   7692:	bipush	56
   7694:	ldc_w	#828; //int 235472647
   7697:	iastore
   7698:	dup
   7699:	bipush	57
   7701:	ldc_w	#829; //int 607523346
   7704:	iastore
   7705:	dup
   7706:	bipush	58
   7708:	ldc_w	#830; //int 463175808
   7711:	iastore
   7712:	dup
   7713:	bipush	59
   7715:	ldc_w	#831; //int -549592350
   7718:	iastore
   7719:	dup
   7720:	bipush	60
   7722:	ldc_w	#832; //int -853087253
   7725:	iastore
   7726:	dup
   7727:	bipush	61
   7729:	ldc_w	#833; //int 1315514151
   7732:	iastore
   7733:	dup
   7734:	bipush	62
   7736:	ldc_w	#834; //int 2144187058
   7739:	iastore
   7740:	dup
   7741:	bipush	63
   7743:	ldc_w	#835; //int -358648459
   7746:	iastore
   7747:	dup
   7748:	bipush	64
   7750:	ldc_w	#836; //int 303761673
   7753:	iastore
   7754:	dup
   7755:	bipush	65
   7757:	ldc_w	#837; //int 496927619
   7760:	iastore
   7761:	dup
   7762:	bipush	66
   7764:	ldc_w	#838; //int 1484008492
   7767:	iastore
   7768:	dup
   7769:	bipush	67
   7771:	ldc_w	#839; //int 875436570
   7774:	iastore
   7775:	dup
   7776:	bipush	68
   7778:	ldc_w	#840; //int 908925723
   7781:	iastore
   7782:	dup
   7783:	bipush	69
   7785:	ldc_w	#841; //int -592286098
   7788:	iastore
   7789:	dup
   7790:	bipush	70
   7792:	ldc_w	#842; //int -1259447718
   7795:	iastore
   7796:	dup
   7797:	bipush	71
   7799:	ldc_w	#843; //int 1543217312
   7802:	iastore
   7803:	dup
   7804:	bipush	72
   7806:	ldc_w	#844; //int -1527360942
   7809:	iastore
   7810:	dup
   7811:	bipush	73
   7813:	ldc_w	#845; //int 1984772923
   7816:	iastore
   7817:	dup
   7818:	bipush	74
   7820:	ldc_w	#846; //int -1218324778
   7823:	iastore
   7824:	dup
   7825:	bipush	75
   7827:	ldc_w	#847; //int 2110698419
   7830:	iastore
   7831:	dup
   7832:	bipush	76
   7834:	ldc_w	#848; //int 1383803177
   7837:	iastore
   7838:	dup
   7839:	bipush	77
   7841:	ldc_w	#849; //int -583080989
   7844:	iastore
   7845:	dup
   7846:	bipush	78
   7848:	ldc_w	#850; //int 1584475951
   7851:	iastore
   7852:	dup
   7853:	bipush	79
   7855:	ldc_w	#851; //int 328696964
   7858:	iastore
   7859:	dup
   7860:	bipush	80
   7862:	ldc_w	#852; //int -1493871789
   7865:	iastore
   7866:	dup
   7867:	bipush	81
   7869:	ldc_w	#853; //int -1184312879
   7872:	iastore
   7873:	dup
   7874:	bipush	82
   7876:	iconst_0
   7877:	iastore
   7878:	dup
   7879:	bipush	83
   7881:	ldc_w	#854; //int -1054020115
   7884:	iastore
   7885:	dup
   7886:	bipush	84
   7888:	ldc_w	#855; //int 1080041504
   7891:	iastore
   7892:	dup
   7893:	bipush	85
   7895:	ldc_w	#856; //int -484442884
   7898:	iastore
   7899:	dup
   7900:	bipush	86
   7902:	ldc_w	#857; //int 2043195825
   7905:	iastore
   7906:	dup
   7907:	bipush	87
   7909:	ldc_w	#858; //int -1225958565
   7912:	iastore
   7913:	dup
   7914:	bipush	88
   7916:	ldc_w	#859; //int -725718422
   7919:	iastore
   7920:	dup
   7921:	bipush	89
   7923:	ldc_w	#860; //int -1924740149
   7926:	iastore
   7927:	dup
   7928:	bipush	90
   7930:	ldc_w	#861; //int 1742323390
   7933:	iastore
   7934:	dup
   7935:	bipush	91
   7937:	ldc_w	#862; //int 1917532473
   7940:	iastore
   7941:	dup
   7942:	bipush	92
   7944:	ldc_w	#863; //int -1797371318
   7947:	iastore
   7948:	dup
   7949:	bipush	93
   7951:	ldc_w	#864; //int -1730917300
   7954:	iastore
   7955:	dup
   7956:	bipush	94
   7958:	ldc_w	#865; //int -1326950312
   7961:	iastore
   7962:	dup
   7963:	bipush	95
   7965:	ldc_w	#866; //int -2058694705
   7968:	iastore
   7969:	dup
   7970:	bipush	96
   7972:	ldc_w	#867; //int -1150562096
   7975:	iastore
   7976:	dup
   7977:	bipush	97
   7979:	ldc_w	#868; //int -987041809
   7982:	iastore
   7983:	dup
   7984:	bipush	98
   7986:	ldc_w	#869; //int 1340451498
   7989:	iastore
   7990:	dup
   7991:	bipush	99
   7993:	ldc_w	#870; //int -317260805
   7996:	iastore
   7997:	dup
   7998:	bipush	100
   8000:	ldc_w	#871; //int -2033892541
   8003:	iastore
   8004:	dup
   8005:	bipush	101
   8007:	ldc_w	#872; //int -1697166003
   8010:	iastore
   8011:	dup
   8012:	bipush	102
   8014:	ldc_w	#873; //int 1716859699
   8017:	iastore
   8018:	dup
   8019:	bipush	103
   8021:	ldc_w	#874; //int 294946181
   8024:	iastore
   8025:	dup
   8026:	bipush	104
   8028:	ldc_w	#875; //int -1966127803
   8031:	iastore
   8032:	dup
   8033:	bipush	105
   8035:	ldc_w	#876; //int -384763399
   8038:	iastore
   8039:	dup
   8040:	bipush	106
   8042:	ldc_w	#877; //int 67502594
   8045:	iastore
   8046:	dup
   8047:	bipush	107
   8049:	ldc_w	#878; //int -25067649
   8052:	iastore
   8053:	dup
   8054:	bipush	108
   8056:	ldc_w	#879; //int -1594863536
   8059:	iastore
   8060:	dup
   8061:	bipush	109
   8063:	ldc_w	#880; //int 2017737788
   8066:	iastore
   8067:	dup
   8068:	bipush	110
   8070:	ldc_w	#881; //int 632987551
   8073:	iastore
   8074:	dup
   8075:	bipush	111
   8077:	ldc_w	#882; //int 1273211048
   8080:	iastore
   8081:	dup
   8082:	bipush	112
   8084:	ldc_w	#883; //int -1561112239
   8087:	iastore
   8088:	dup
   8089:	bipush	113
   8091:	ldc_w	#884; //int 1576969123
   8094:	iastore
   8095:	dup
   8096:	bipush	114
   8098:	ldc_w	#885; //int -2134884288
   8101:	iastore
   8102:	dup
   8103:	bipush	115
   8105:	ldc_w	#886; //int 92966799
   8108:	iastore
   8109:	dup
   8110:	bipush	116
   8112:	ldc_w	#887; //int 1068339858
   8115:	iastore
   8116:	dup
   8117:	bipush	117
   8119:	ldc_w	#888; //int 566009245
   8122:	iastore
   8123:	dup
   8124:	bipush	118
   8126:	ldc_w	#889; //int 1883781176
   8129:	iastore
   8130:	dup
   8131:	bipush	119
   8133:	ldc_w	#890; //int -251333131
   8136:	iastore
   8137:	dup
   8138:	bipush	120
   8140:	ldc_w	#891; //int 1675607228
   8143:	iastore
   8144:	dup
   8145:	bipush	121
   8147:	ldc_w	#892; //int 2009183926
   8150:	iastore
   8151:	dup
   8152:	bipush	122
   8154:	ldc_w	#893; //int -1351230758
   8157:	iastore
   8158:	dup
   8159:	bipush	123
   8161:	ldc_w	#894; //int 1113792801
   8164:	iastore
   8165:	dup
   8166:	bipush	124
   8168:	ldc_w	#895; //int 540020752
   8171:	iastore
   8172:	dup
   8173:	bipush	125
   8175:	ldc_w	#896; //int -451215361
   8178:	iastore
   8179:	dup
   8180:	bipush	126
   8182:	ldc_w	#897; //int -49351693
   8185:	iastore
   8186:	dup
   8187:	bipush	127
   8189:	ldc_w	#898; //int -1083321646
   8192:	iastore
   8193:	dup
   8194:	sipush	128
   8197:	ldc_w	#899; //int -2125673011
   8200:	iastore
   8201:	dup
   8202:	sipush	129
   8205:	ldc_w	#900; //int 403966988
   8208:	iastore
   8209:	dup
   8210:	sipush	130
   8213:	ldc_w	#901; //int 641012499
   8216:	iastore
   8217:	dup
   8218:	sipush	131
   8221:	ldc_w	#902; //int -1020269332
   8224:	iastore
   8225:	dup
   8226:	sipush	132
   8229:	ldc_w	#903; //int -1092526241
   8232:	iastore
   8233:	dup
   8234:	sipush	133
   8237:	ldc_w	#904; //int 899848087
   8240:	iastore
   8241:	dup
   8242:	sipush	134
   8245:	ldc_w	#905; //int -1999879100
   8248:	iastore
   8249:	dup
   8250:	sipush	135
   8253:	ldc_w	#906; //int 775493399
   8256:	iastore
   8257:	dup
   8258:	sipush	136
   8261:	ldc_w	#907; //int -1822964540
   8264:	iastore
   8265:	dup
   8266:	sipush	137
   8269:	ldc_w	#908; //int 1441965991
   8272:	iastore
   8273:	dup
   8274:	sipush	138
   8277:	ldc_w	#909; //int -58556802
   8280:	iastore
   8281:	dup
   8282:	sipush	139
   8285:	ldc_w	#910; //int 2051489085
   8288:	iastore
   8289:	dup
   8290:	sipush	140
   8293:	ldc_w	#911; //int -928226204
   8296:	iastore
   8297:	dup
   8298:	sipush	141
   8301:	ldc_w	#912; //int -1159242403
   8304:	iastore
   8305:	dup
   8306:	sipush	142
   8309:	ldc_w	#913; //int 841685273
   8312:	iastore
   8313:	dup
   8314:	sipush	143
   8317:	ldc_w	#914; //int -426413197
   8320:	iastore
   8321:	dup
   8322:	sipush	144
   8325:	ldc_w	#915; //int -1063231392
   8328:	iastore
   8329:	dup
   8330:	sipush	145
   8333:	ldc_w	#916; //int 429425025
   8336:	iastore
   8337:	dup
   8338:	sipush	146
   8341:	ldc_w	#917; //int -1630449841
   8344:	iastore
   8345:	dup
   8346:	sipush	147
   8349:	ldc_w	#918; //int -1551901476
   8352:	iastore
   8353:	dup
   8354:	sipush	148
   8357:	ldc_w	#919; //int 1147544098
   8360:	iastore
   8361:	dup
   8362:	sipush	149
   8365:	ldc_w	#920; //int 1417554474
   8368:	iastore
   8369:	dup
   8370:	sipush	150
   8373:	ldc_w	#921; //int 1001099408
   8376:	iastore
   8377:	dup
   8378:	sipush	151
   8381:	ldc_w	#922; //int 193169544
   8384:	iastore
   8385:	dup
   8386:	sipush	152
   8389:	ldc_w	#923; //int -1932900794
   8392:	iastore
   8393:	dup
   8394:	sipush	153
   8397:	ldc_w	#924; //int -953553170
   8400:	iastore
   8401:	dup
   8402:	sipush	154
   8405:	ldc_w	#925; //int 1809037496
   8408:	iastore
   8409:	dup
   8410:	sipush	155
   8413:	ldc_w	#926; //int 675025940
   8416:	iastore
   8417:	dup
   8418:	sipush	156
   8421:	ldc_w	#927; //int -1485185314
   8424:	iastore
   8425:	dup
   8426:	sipush	157
   8429:	ldc_w	#928; //int -1126015394
   8432:	iastore
   8433:	dup
   8434:	sipush	158
   8437:	ldc_w	#929; //int 371002123
   8440:	iastore
   8441:	dup
   8442:	sipush	159
   8445:	ldc_w	#930; //int -1384719397
   8448:	iastore
   8449:	dup
   8450:	sipush	160
   8453:	ldc_w	#931; //int -616832800
   8456:	iastore
   8457:	dup
   8458:	sipush	161
   8461:	ldc_w	#932; //int 1683370546
   8464:	iastore
   8465:	dup
   8466:	sipush	162
   8469:	ldc_w	#933; //int 1951283770
   8472:	iastore
   8473:	dup
   8474:	sipush	163
   8477:	ldc_w	#934; //int 337512970
   8480:	iastore
   8481:	dup
   8482:	sipush	164
   8485:	ldc_w	#935; //int -1831122615
   8488:	iastore
   8489:	dup
   8490:	sipush	165
   8493:	ldc_w	#936; //int 201983494
   8496:	iastore
   8497:	dup
   8498:	sipush	166
   8501:	ldc_w	#937; //int 1215046692
   8504:	iastore
   8505:	dup
   8506:	sipush	167
   8509:	ldc_w	#938; //int -1192993700
   8512:	iastore
   8513:	dup
   8514:	sipush	168
   8517:	ldc_w	#939; //int -1621245246
   8520:	iastore
   8521:	dup
   8522:	sipush	169
   8525:	ldc_w	#940; //int -1116810285
   8528:	iastore
   8529:	dup
   8530:	sipush	170
   8533:	ldc_w	#941; //int 1139780780
   8536:	iastore
   8537:	dup
   8538:	sipush	171
   8541:	ldc_w	#942; //int -995728798
   8544:	iastore
   8545:	dup
   8546:	sipush	172
   8549:	ldc_w	#943; //int 967348625
   8552:	iastore
   8553:	dup
   8554:	sipush	173
   8557:	ldc_w	#944; //int 832869781
   8560:	iastore
   8561:	dup
   8562:	sipush	174
   8565:	ldc_w	#945; //int -751311644
   8568:	iastore
   8569:	dup
   8570:	sipush	175
   8573:	ldc_w	#946; //int -225740423
   8576:	iastore
   8577:	dup
   8578:	sipush	176
   8581:	ldc_w	#947; //int -718084121
   8584:	iastore
   8585:	dup
   8586:	sipush	177
   8589:	ldc_w	#948; //int -1958491960
   8592:	iastore
   8593:	dup
   8594:	sipush	178
   8597:	ldc_w	#949; //int 1851340599
   8600:	iastore
   8601:	dup
   8602:	sipush	179
   8605:	ldc_w	#950; //int -625513107
   8608:	iastore
   8609:	dup
   8610:	sipush	180
   8613:	ldc_w	#951; //int 25988493
   8616:	iastore
   8617:	dup
   8618:	sipush	181
   8621:	ldc_w	#952; //int -1318791723
   8624:	iastore
   8625:	dup
   8626:	sipush	182
   8629:	ldc_w	#953; //int -1663938994
   8632:	iastore
   8633:	dup
   8634:	sipush	183
   8637:	ldc_w	#954; //int 1239460265
   8640:	iastore
   8641:	dup
   8642:	sipush	184
   8645:	ldc_w	#955; //int -659264404
   8648:	iastore
   8649:	dup
   8650:	sipush	185
   8653:	ldc_w	#956; //int -1392880042
   8656:	iastore
   8657:	dup
   8658:	sipush	186
   8661:	ldc_w	#957; //int -217582348
   8664:	iastore
   8665:	dup
   8666:	sipush	187
   8669:	ldc_w	#958; //int -819598614
   8672:	iastore
   8673:	dup
   8674:	sipush	188
   8677:	ldc_w	#959; //int -894474907
   8680:	iastore
   8681:	dup
   8682:	sipush	189
   8685:	ldc_w	#960; //int -191989126
   8688:	iastore
   8689:	dup
   8690:	sipush	190
   8693:	ldc_w	#961; //int 1206496942
   8696:	iastore
   8697:	dup
   8698:	sipush	191
   8701:	ldc_w	#962; //int 270010376
   8704:	iastore
   8705:	dup
   8706:	sipush	192
   8709:	ldc_w	#963; //int 1876277946
   8712:	iastore
   8713:	dup
   8714:	sipush	193
   8717:	ldc_w	#964; //int -259491720
   8720:	iastore
   8721:	dup
   8722:	sipush	194
   8725:	ldc_w	#965; //int 1248797989
   8728:	iastore
   8729:	dup
   8730:	sipush	195
   8733:	ldc_w	#966; //int 1550986798
   8736:	iastore
   8737:	dup
   8738:	sipush	196
   8741:	ldc_w	#967; //int 941890588
   8744:	iastore
   8745:	dup
   8746:	sipush	197
   8749:	ldc_w	#968; //int 1475454630
   8752:	iastore
   8753:	dup
   8754:	sipush	198
   8757:	ldc_w	#969; //int 1942467764
   8760:	iastore
   8761:	dup
   8762:	sipush	199
   8765:	ldc_w	#970; //int -1756248378
   8768:	iastore
   8769:	dup
   8770:	sipush	200
   8773:	ldc_w	#971; //int -886839064
   8776:	iastore
   8777:	dup
   8778:	sipush	201
   8781:	ldc_w	#972; //int -1585652259
   8784:	iastore
   8785:	dup
   8786:	sipush	202
   8789:	ldc_w	#973; //int -392399756
   8792:	iastore
   8793:	dup
   8794:	sipush	203
   8797:	ldc_w	#974; //int 1042358047
   8800:	iastore
   8801:	dup
   8802:	sipush	204
   8805:	ldc_w	#975; //int -1763882165
   8808:	iastore
   8809:	dup
   8810:	sipush	205
   8813:	ldc_w	#976; //int 1641856445
   8816:	iastore
   8817:	dup
   8818:	sipush	206
   8821:	ldc_w	#977; //int 226921355
   8824:	iastore
   8825:	dup
   8826:	sipush	207
   8829:	ldc_w	#978; //int 260409994
   8832:	iastore
   8833:	dup
   8834:	sipush	208
   8837:	ldc_w	#979; //int -527404944
   8840:	iastore
   8841:	dup
   8842:	sipush	209
   8845:	ldc_w	#980; //int 2084716094
   8848:	iastore
   8849:	dup
   8850:	sipush	210
   8853:	ldc_w	#981; //int 1908716981
   8856:	iastore
   8857:	dup
   8858:	sipush	211
   8861:	ldc_w	#982; //int -861247898
   8864:	iastore
   8865:	dup
   8866:	sipush	212
   8869:	ldc_w	#983; //int -1864873912
   8872:	iastore
   8873:	dup
   8874:	sipush	213
   8877:	ldc_w	#984; //int 100991747
   8880:	iastore
   8881:	dup
   8882:	sipush	214
   8885:	ldc_w	#985; //int -150866186
   8888:	iastore
   8889:	dup
   8890:	sipush	215
   8893:	ldc_w	#986; //int 470945294
   8896:	iastore
   8897:	dup
   8898:	sipush	216
   8901:	ldc_w	#987; //int -1029480095
   8904:	iastore
   8905:	dup
   8906:	sipush	217
   8909:	ldc_w	#988; //int 1784624437
   8912:	iastore
   8913:	dup
   8914:	sipush	218
   8917:	ldc_w	#989; //int -1359390889
   8920:	iastore
   8921:	dup
   8922:	sipush	219
   8925:	ldc_w	#990; //int 1775286713
   8928:	iastore
   8929:	dup
   8930:	sipush	220
   8933:	ldc_w	#991; //int 395413126
   8936:	iastore
   8937:	dup
   8938:	sipush	221
   8941:	ldc_w	#992; //int -1722236479
   8944:	iastore
   8945:	dup
   8946:	sipush	222
   8949:	ldc_w	#993; //int 975641885
   8952:	iastore
   8953:	dup
   8954:	sipush	223
   8957:	ldc_w	#994; //int 666476190
   8960:	iastore
   8961:	dup
   8962:	sipush	224
   8965:	ldc_w	#995; //int -650583583
   8968:	iastore
   8969:	dup
   8970:	sipush	225
   8973:	ldc_w	#996; //int -351012616
   8976:	iastore
   8977:	dup
   8978:	sipush	226
   8981:	ldc_w	#997; //int 733190296
   8984:	iastore
   8985:	dup
   8986:	sipush	227
   8989:	ldc_w	#998; //int 573772049
   8992:	iastore
   8993:	dup
   8994:	sipush	228
   8997:	ldc_w	#999; //int -759469719
   9000:	iastore
   9001:	dup
   9002:	sipush	229
   9005:	ldc_w	#1000; //int -1452221991
   9008:	iastore
   9009:	dup
   9010:	sipush	230
   9013:	ldc_w	#1001; //int 126455438
   9016:	iastore
   9017:	dup
   9018:	sipush	231
   9021:	ldc_w	#1002; //int 866620564
   9024:	iastore
   9025:	dup
   9026:	sipush	232
   9029:	ldc_w	#1003; //int 766942107
   9032:	iastore
   9033:	dup
   9034:	sipush	233
   9037:	ldc_w	#1004; //int 1008868894
   9040:	iastore
   9041:	dup
   9042:	sipush	234
   9045:	ldc_w	#1005; //int 361924487
   9048:	iastore
   9049:	dup
   9050:	sipush	235
   9053:	ldc_w	#1006; //int -920589847
   9056:	iastore
   9057:	dup
   9058:	sipush	236
   9061:	ldc_w	#1007; //int -2025206066
   9064:	iastore
   9065:	dup
   9066:	sipush	237
   9069:	ldc_w	#1008; //int -1426107051
   9072:	iastore
   9073:	dup
   9074:	sipush	238
   9077:	ldc_w	#1009; //int 1350051880
   9080:	iastore
   9081:	dup
   9082:	sipush	239
   9085:	ldc_w	#1010; //int -1518673953
   9088:	iastore
   9089:	dup
   9090:	sipush	240
   9093:	ldc_w	#1011; //int 59739276
   9096:	iastore
   9097:	dup
   9098:	sipush	241
   9101:	ldc_w	#1012; //int 1509466529
   9104:	iastore
   9105:	dup
   9106:	sipush	242
   9109:	ldc_w	#1013; //int 159418761
   9112:	iastore
   9113:	dup
   9114:	sipush	243
   9117:	ldc_w	#1014; //int 437718285
   9120:	iastore
   9121:	dup
   9122:	sipush	244
   9125:	ldc_w	#1015; //int 1708834751
   9128:	iastore
   9129:	dup
   9130:	sipush	245
   9133:	ldc_w	#1016; //int -684595482
   9136:	iastore
   9137:	dup
   9138:	sipush	246
   9141:	ldc_w	#1017; //int -2067381694
   9144:	iastore
   9145:	dup
   9146:	sipush	247
   9149:	ldc_w	#1018; //int -793221016
   9152:	iastore
   9153:	dup
   9154:	sipush	248
   9157:	ldc_w	#1019; //int -2101132991
   9160:	iastore
   9161:	dup
   9162:	sipush	249
   9165:	ldc_w	#1020; //int 699439513
   9168:	iastore
   9169:	dup
   9170:	sipush	250
   9173:	ldc_w	#1021; //int 1517759789
   9176:	iastore
   9177:	dup
   9178:	sipush	251
   9181:	ldc_w	#1022; //int 504434447
   9184:	iastore
   9185:	dup
   9186:	sipush	252
   9189:	ldc_w	#1023; //int 2076946608
   9192:	iastore
   9193:	dup
   9194:	sipush	253
   9197:	ldc_w	#1024; //int -1459858348
   9200:	iastore
   9201:	dup
   9202:	sipush	254
   9205:	ldc_w	#1025; //int 1842789307
   9208:	iastore
   9209:	dup
   9210:	sipush	255
   9213:	ldc_w	#1026; //int 742004246
   9216:	iastore
   9217:	putstatic	#6; //Field gtable3:[I
   9220:	return

}

